Workbook

Sheet 工作表1
A1: Resources Plan
B2: Resurce Count | C2: Man Day | D2: Hiring Period | E2: Cost
A3: {=_xlfn.UNIQUE('Project Planning - B'!G11:G179)} -> Patrick -BA | B3: 1 | C3: =SUMIF('Project Planning - B'!G11:G179, A3,'Project Planning - B'!H11:H179) -> 15 | D3: =TEXT(_xlfn.MINIFS('Project Planning - B'!$I$11:$I$180, 'Project Planning - B'!$G$11:$G$180, A3), "yyyy/mm/dd") & " - " & TEXT(_xlfn.MAXIFS('Project Planning - B'!$J$11:$J$180, 'Project Planning - B'!$G$11:$G$180, A3), "yyyy/mm/dd") -> 2025/11/24 - 2026/01/12
A4: Kent | B4: 1 | C4: =SUMIF('Project Planning - B'!G11:G180, A4,'Project Planning - B'!H11:H180) -> 67 | D4: =TEXT(_xlfn.MINIFS('Project Planning - B'!$I$11:$I$180, 'Project Planning - B'!$G$11:$G$180, A4), "yyyy/mm/dd") & " - " & TEXT(_xlfn.MAXIFS('Project Planning - B'!$J$11:$J$180, 'Project Planning - B'!$G$11:$G$180, A4), "yyyy/mm/dd") -> 2025/12/12 - 2026/08/06 | E4: 0
A5: BA/Testing | B5: 1 | C5: =SUMIF('Project Planning - B'!G11:G181, A5,'Project Planning - B'!H11:H181) -> 136 | D5: =TEXT(_xlfn.MINIFS('Project Planning - B'!$I$11:$I$180, 'Project Planning - B'!$G$11:$G$180, A5), "yyyy/mm/dd") & " - " & TEXT(_xlfn.MAXIFS('Project Planning - B'!$J$11:$J$180, 'Project Planning - B'!$G$11:$G$180, A5), "yyyy/mm/dd") -> 2025/12/31 - 2026/08/17 | E5: 0
A6: FrontEnd | B6: 1 | C6: =SUMIF('Project Planning - B'!G11:G182, A6,'Project Planning - B'!H11:H182) -> 58 | D6: =TEXT(_xlfn.MINIFS('Project Planning - B'!$I$11:$I$180, 'Project Planning - B'!$G$11:$G$180, A6), "yyyy/mm/dd") & " - " & TEXT(_xlfn.MAXIFS('Project Planning - B'!$J$11:$J$180, 'Project Planning - B'!$G$11:$G$180, A6), "yyyy/mm/dd") -> 2025/12/24 - 2026/07/23
A7: New AP Lead | B7: 1 | C7: =SUMIF('Project Planning - B'!G11:G183, A7,'Project Planning - B'!H11:H183) -> 72 | D7: =TEXT(_xlfn.MINIFS('Project Planning - B'!$I$11:$I$180, 'Project Planning - B'!$G$11:$G$180, A7), "yyyy/mm/dd") & " - " & TEXT(_xlfn.MAXIFS('Project Planning - B'!$J$11:$J$180, 'Project Planning - B'!$G$11:$G$180, A7), "yyyy/mm/dd") -> 2026/01/21 - 2026/08/14

Sheet Project Planning - B
C1: DMS Development
B3: TOTAL TASKS | C3: =COUNTA(E11:E1048576) -> 169 | G3: DURATION | H3: =H5-H4+1 -> 267 | J3: Overall Progress
B4: Completed | C4: =COUNTIF(L11:L1048576,B4) -> 0 | G4: START | H4: =MIN(I11:I1048576) -> 45985 | L4: =SUM(#REF!) -> #REF! | N4: Team Member | O4: FTE | P4: Cost / Monthly | T4: Difficulty Level | U4: MD
B5: In progress | C5: =COUNTIF(L11:L1048576,B5) -> 9 | G5: FINISH | H5: =MAX(J11:J1048576) -> 46251 | L5: =SUM(H11:H179) -> 348 | N5: Kent | O5: 1 | Q5: 1 year | T5: Low | U5: 1-2
B6: Not Started | C6: =COUNTIF(L11:L1048576,B6) -> 160 | N6: BA/Testing | O6: 1 | P6: =145000*1.05 -> 152250 | Q6: =P6*12 -> 1827000 | T6: Mid | U6: 3-5
D7: New SA and Engineer training | H7: 1/5/2026 - 1/9/2026 | J7: =1-J5 -> 1 | N7: AP Lead | O7: 1 | Q7: Onboard after Chinese New Year | T7: High | U7: 6-8
N8: FrontEnd1 | O8: 1 | P8: =145000*1.05 -> 152250 | Q8: =P8*12 -> 1827000
N9: Patrick-BA | O9: 0.5
A10: SPRINT | B10: EPIC | C10: FEATURE | D10: TASKS | E10: STORIES | F10: Difficulty Level | G10: RESPONSIBLE | H10: Man Day Required | I10: START | J10: FINISH | K10: DURATION | L10: STATUS
A11: Sprint 1 | B11: Dividend Distribution | C11: Data Mapping, Data Migration & Create Tables in DB | D11: BA | E11: Data Related Detail Requirement Analysis | F11: Mid | G11: Patrick -BA | H11: 3 | I11: 45985 | J11: =WORKDAY(I11,K11) -> 45993 | K11: =H11/$O$9 -> 6 | L11: In progress
A12: Sprint 1 | B12: Dividend Distribution | C12: Data Mapping, Data Migration & Create Tables in DB | D12: BA | E12: Data Related Document Detail Requirement | F12: Mid | G12: Patrick -BA | H12: 3 | I12: =WORKDAY(J11,1) -> 45994 | J12: =WORKDAY(I12,K12) -> 46002 | K12: =H12/$O$9 -> 6 | L12: In progress
A13: Sprint 1 | B13: Dividend Distribution | C13: Data Mapping, Data Migration & Create Tables in DB | D13: Development | E13: Data Mapping - Development | F13: Mid | G13: Kent | H13: 3 | I13: =WORKDAY(J12,1) -> 46003 | J13: =WORKDAY(I13,K13) -> 46008 | K13: =H13/$O$5 -> 3 | L13: In progress
A14: Sprint 1 | B14: Dividend Distribution | C14: Data Mapping, Data Migration & Create Tables in DB | D14: Development | E14: Data Migration - Development | F14: High | G14: Kent | H14: 5 | I14: =WORKDAY(J13,1) -> 46009 | J14: =WORKDAY(I14,K14) -> 46016 | K14: =H14/$O$5 -> 5 | L14: Not Started
A15: Sprint 2 | B15: Dividend Distribution | C15: Data Mapping, Data Migration & Create Tables in DB | D15: Development | E15: Create Tables in DB - Development | F15: Low | G15: Kent | H15: 2 | I15: =WORKDAY(J14,1) -> 46017 | J15: =WORKDAY(I15,K15) -> 46021 | K15: =H15/$O$5 -> 2 | L15: Not Started
A16: Sprint 2 | B16: Dividend Distribution | C16: Data Mapping, Data Migration & Create Tables in DB | D16: Testing | E16: Data Related QA - unit testing | F16: Mid | G16: BA/Testing | H16: 3 | I16: =WORKDAY(J15,1) -> 46022 | J16: =WORKDAY(I16,K16) -> 46027 | K16: =H16/$O$5 -> 3 | L16: Not Started
A17: Sprint 2 | B17: Dividend Distribution | C17: Maintain Distributable Balance 可分配餘額維護作業 | D17: BA | E17: Maintain Distributable Balance Detail Requirement Analysis | F17: {=_xlfn.IFS(H17="","", H17<=2,"Low", H17<=5,"Mid", H17<=8,"High", TRUE,"Out of Range")} -> Low | G17: Patrick -BA | H17: 1.5 | I17: =WORKDAY(J12,1) -> 46003 | J17: =WORKDAY(I17,K17) -> 46008 | K17: =H17/$O$9 -> 3 | L17: In progress
A18: Sprint 2 | B18: Dividend Distribution | C18: Maintain Distributable Balance 可分配餘額維護作業 | D18: BA | E18: Maintain Distributable Document Detail Requirement | F18: {=_xlfn.IFS(H18="","", H18<=2,"Low", H18<=5,"Mid", H18<=8,"High", TRUE,"Out of Range")} -> Low | G18: Patrick -BA | H18: 1.5 | I18: =WORKDAY(J17,1) -> 46009 | J18: =WORKDAY(I18,K18) -> 46014 | K18: =H18/$O$9 -> 3 | L18: In progress
A19: Sprint 2 | B19: Dividend Distribution | C19: Maintain Distributable Balance 可分配餘額維護作業 | D19: Development | E19: Maintain Distributable Balance - Development 1 | F19: {=_xlfn.IFS(H19="","", H19<=2,"Low", H19<=5,"Mid", H19<=8,"High", TRUE,"Out of Range")} -> Low | G19: FrontEnd | H19: 1 | I19: =WORKDAY(J18,1) -> 46015 | J19: =WORKDAY(I19,K19) -> 46016 | K19: =H19/$O$5 -> 1 | L19: Not Started
A20: Sprint 3 | B20: Dividend Distribution | C20: Maintain Distributable Balance 可分配餘額維護作業 | D20: Development | E20: Maintain Distributable Balance - Development 2 | F20: {=_xlfn.IFS(H20="","", H20<=2,"Low", H20<=5,"Mid", H20<=8,"High", TRUE,"Out of Range")} -> High | G20: Kent | H20: 7 | I20: =WORKDAY(J15,1) -> 46022 | J20: =WORKDAY(I20,K20) -> 46031 | K20: =H20/$O$5 -> 7 | L20: Not Started
A21: Sprint 3 | B21: Dividend Distribution | C21: Maintain Distributable Balance 可分配餘額維護作業 | D21: Testing | E21: Maintain Distributable Balance QA - unit testing | F21: {=_xlfn.IFS(H21="","", H21<=2,"Low", H21<=5,"Mid", H21<=8,"High", TRUE,"Out of Range")} -> Mid | G21: BA/Testing | H21: 3 | I21: =WORKDAY(J20,1) -> 46034 | J21: =WORKDAY(I21,K21) -> 46037 | K21: =H21/$O$5 -> 3 | L21: Not Started
A22: Sprint 3 | B22: Dividend Distribution | C22: Domestic Dividend Information Inquiry 境內配息資訊查詢作業 | D22: BA | E22: Domestic Dividend Information Inquiry Detail Requirement Analysis | F22: {=_xlfn.IFS(H22="","", H22<=2,"Low", H22<=5,"Mid", H22<=8,"High", TRUE,"Out of Range")} -> Low | G22: Patrick -BA | H22: 1.5 | I22: =WORKDAY(J18,1) -> 46015 | J22: =WORKDAY(I22,K22) -> 46020 | K22: =H22/$O$9 -> 3 | L22: In progress
A23: Sprint 3 | B23: Dividend Distribution | C23: Domestic Dividend Information Inquiry 境內配息資訊查詢作業 | D23: BA | E23: Domestic Dividend Information Inquiry Document Detail Requirement | F23: {=_xlfn.IFS(H23="","", H23<=2,"Low", H23<=5,"Mid", H23<=8,"High", TRUE,"Out of Range")} -> Low | G23: Patrick -BA | H23: 1.5 | I23: =WORKDAY(J19,1) -> 46017 | J23: =WORKDAY(I23,K23) -> 46022 | K23: =H23/$O$9 -> 3 | L23: In progress
A24: Sprint 4 | B24: Dividend Distribution | C24: Domestic Dividend Information Inquiry 境內配息資訊查詢作業 | D24: Development | E24: Domestic Dividend Information Inquiry - Development 1 | F24: {=_xlfn.IFS(H24="","", H24<=2,"Low", H24<=5,"Mid", H24<=8,"High", TRUE,"Out of Range")} -> Mid | G24: FrontEnd | H24: 4 | I24: =WORKDAY(J23,1) -> 46023 | J24: =WORKDAY(I24,K24) -> 46029 | K24: =H24/$O$5 -> 4 | L24: Not Started
A25: Sprint 4 | B25: Dividend Distribution | C25: Domestic Dividend Information Inquiry 境內配息資訊查詢作業 | D25: Development | E25: Domestic Dividend Information Inquiry - Development 2 | F25: {=_xlfn.IFS(H25="","", H25<=2,"Low", H25<=5,"Mid", H25<=8,"High", TRUE,"Out of Range")} -> Mid | G25: Kent | H25: 4 | I25: =WORKDAY(J20,1) -> 46034 | J25: =WORKDAY(I25,K25) -> 46038 | K25: =H25/$O$5 -> 4 | L25: Not Started
A26: Sprint 5 | B26: Dividend Distribution | C26: Domestic Dividend Information Inquiry 境內配息資訊查詢作業 | D26: Testing | E26: Domestic Dividend Information Inquiry QA - unit testing | F26: {=_xlfn.IFS(H26="","", H26<=2,"Low", H26<=5,"Mid", H26<=8,"High", TRUE,"Out of Range")} -> Low | G26: BA/Testing | H26: 2 | I26: =WORKDAY(J25,1) -> 46041 | J26: =WORKDAY(I26,K26) -> 46043 | K26: =H26/$O$5 -> 2 | L26: Not Started
A27: Sprint 3 | B27: Dividend Distribution | C27: Upload Domestic Dividend Composition Info to EC 境內配息組成資訊上傳EC | D27: BA | E27: Upload Domestic Dividend Composition Info to EC - Detail Requirement Analysis | F27: {=_xlfn.IFS(H27="","", H27<=2,"Low", H27<=5,"Mid", H27<=8,"High", TRUE,"Out of Range")} -> Low | G27: Patrick -BA | H27: 1.5 | I27: =WORKDAY(J23,1) -> 46023 | J27: =WORKDAY(I27,K27) -> 46028 | K27: =H27/$O$9 -> 3 | L27: In progress
A28: Sprint 3 | B28: Dividend Distribution | C28: Upload Domestic Dividend Composition Info to EC 境內配息組成資訊上傳EC | D28: BA | E28: Upload Domestic Dividend Composition Info to EC - Document Detail Requirement | F28: {=_xlfn.IFS(H28="","", H28<=2,"Low", H28<=5,"Mid", H28<=8,"High", TRUE,"Out of Range")} -> Low | G28: Patrick -BA | H28: 1.5 | I28: =WORKDAY(J27,1) -> 46029 | J28: =WORKDAY(I28,K28) -> 46034 | K28: =H28/$O$9 -> 3 | L28: In progress
A29: Sprint 5 | B29: Dividend Distribution | C29: Upload Domestic Dividend Composition Info to EC 境內配息組成資訊上傳EC | D29: Development | E29: Upload Domestic Dividend Composition Info to EC - Development 1 | F29: {=_xlfn.IFS(H29="","", H29<=2,"Low", H29<=5,"Mid", H29<=8,"High", TRUE,"Out of Range")} -> Mid | G29: FrontEnd | H29: 4 | I29: =WORKDAY(J24,1) -> 46030 | J29: =WORKDAY(I29,K29) -> 46036 | K29: =H29/$O$5 -> 4 | L29: Not Started
A30: Sprint 5 | B30: Dividend Distribution | C30: Upload Domestic Dividend Composition Info to EC 境內配息組成資訊上傳EC | D30: Development | E30: Upload Domestic Dividend Composition Info to EC - Development 2 | F30: {=_xlfn.IFS(H30="","", H30<=2,"Low", H30<=5,"Mid", H30<=8,"High", TRUE,"Out of Range")} -> Mid | G30: Kent | H30: 4 | I30: =WORKDAY(J25,1) -> 46041 | J30: =WORKDAY(I30,K30) -> 46045 | K30: =H30/$O$5 -> 4 | L30: Not Started
A31: Sprint 6 | B31: Dividend Distribution | C31: Upload Domestic Dividend Composition Info to EC 境內配息組成資訊上傳EC | D31: Testing | E31: Upload Domestic Dividend Composition Info to EC QA - unit testing | F31: {=_xlfn.IFS(H31="","", H31<=2,"Low", H31<=5,"Mid", H31<=8,"High", TRUE,"Out of Range")} -> Low | G31: BA/Testing | H31: 1 | I31: =WORKDAY(J30,1) -> 46048 | J31: 46048 | K31: 1 | L31: Not Started
A32: Sprint 1 | B32: Mandate | C32: Data Mapping, Data Migration & Create Tables in DB | D32: BA | E32: Data Mapping, Data Migration & Create Tables in DB Requirement Analysis | F32: {=_xlfn.IFS(H32="","", H32<=2,"Low", H32<=5,"Mid", H32<=8,"High", TRUE,"Out of Range")} -> Mid | G32: BA/Testing | H32: 3 | I32: 46035 | J32: 46037 | K32: =H32/$O$6 -> 3 | L32: Not Started
A33: Sprint 2 | B33: Mandate | C33: Data Mapping, Data Migration & Create Tables in DB | D33: BA | E33: Data Mapping, Data Migration & Create Tables in DB Requirement | F33: {=_xlfn.IFS(H33="","", H33<=2,"Low", H33<=5,"Mid", H33<=8,"High", TRUE,"Out of Range")} -> Mid | G33: BA/Testing | H33: 3 | I33: 46038 | J33: 46042 | K33: =H33/$O$6 -> 3 | L33: Not Started
A34: Sprint 2 | B34: Mandate | C34: Data Mapping, Data Migration & Create Tables in DB | D34: Development | E34: Data Mapping - Development | F34: {=_xlfn.IFS(H34="","", H34<=2,"Low", H34<=5,"Mid", H34<=8,"High", TRUE,"Out of Range")} -> Mid | G34: New AP Lead | H34: 4 | I34: 46043 | J34: 46048 | K34: =H34/$O$7 -> 4 | L34: Not Started
A35: Sprint 3 | B35: Mandate | C35: Data Mapping, Data Migration & Create Tables in DB | D35: Development | E35: Data Migration - Development | F35: {=_xlfn.IFS(H35="","", H35<=2,"Low", H35<=5,"Mid", H35<=8,"High", TRUE,"Out of Range")} -> Mid | G35: New AP Lead | H35: 4 | I35: 46049 | J35: 46052 | K35: =H35/$O$7 -> 4 | L35: Not Started
A36: Sprint 4 | B36: Mandate | C36: Data Mapping, Data Migration & Create Tables in DB | D36: Development | E36: Create Tables in DB - Development | F36: {=_xlfn.IFS(H36="","", H36<=2,"Low", H36<=5,"Mid", H36<=8,"High", TRUE,"Out of Range")} -> Low | G36: New AP Lead | H36: 2 | I36: 46055 | J36: 46056 | K36: =H36/$O$7 -> 2 | L36: Not Started
A37: Sprint 5 | B37: Mandate | C37: Data Mapping, Data Migration & Create Tables in DB | D37: Testing | E37: Data Related QA - unit testing | F37: {=_xlfn.IFS(H37="","", H37<=2,"Low", H37<=5,"Mid", H37<=8,"High", TRUE,"Out of Range")} -> Mid | G37: BA/Testing | H37: 3 | I37: 46057 | J37: 46059 | K37: =H37/$O$5 -> 3 | L37: Not Started
A38: Sprint 4 | B38: Mandate | C38: FAS 8111 Mandate Client Information Maintenance 全委委託人資料維護 | D38: BA | E38: Mandate Client Information Maintenance Requirement Analysis | F38: {=_xlfn.IFS(H38="","", H38<=2,"Low", H38<=5,"Mid", H38<=8,"High", TRUE,"Out of Range")} -> Low | G38: BA/Testing | H38: 2 | I38: 46043 | J38: 46044 | K38: =H38/$O$7 -> 2 | L38: Not Started
A39: Sprint 4 | B39: Mandate | C39: FAS 8111 Mandate Client Information Maintenance 全委委託人資料維護 | D39: BA | E39: Mandate Client Information Maintenance Requirement | F39: {=_xlfn.IFS(H39="","", H39<=2,"Low", H39<=5,"Mid", H39<=8,"High", TRUE,"Out of Range")} -> Low | G39: BA/Testing | H39: 2 | I39: 46045 | J39: 46045 | K39: 1 | L39: Not Started
A40: Sprint 4 | B40: Mandate | C40: FAS 8111 Mandate Client Information Maintenance 全委委託人資料維護 | D40: Development | E40: Mandate Client Information Maintenance - Development 1 | F40: {=_xlfn.IFS(H40="","", H40<=2,"Low", H40<=5,"Mid", H40<=8,"High", TRUE,"Out of Range")} -> Low | G40: FrontEnd | H40: 2 | I40: 46049 | J40: 46050 | K40: =H40/$O$8 -> 2 | L40: Not Started
A41: Sprint 5 | B41: Mandate | C41: FAS 8111 Mandate Client Information Maintenance 全委委託人資料維護 | D41: Development | E41: Mandate Client Information Maintenance - Development 2 | F41: {=_xlfn.IFS(H41="","", H41<=2,"Low", H41<=5,"Mid", H41<=8,"High", TRUE,"Out of Range")} -> High | G41: New AP Lead | H41: 8 | I41: 46057 | J41: 46066 | K41: =H41/$O$7 -> 8 | L41: Not Started
A42: Sprint 5 | B42: Mandate | C42: FAS 8111 Mandate Client Information Maintenance 全委委託人資料維護 | D42: Testing | E42: Mandate Client Information Maintenance QA - unit-testing | F42: {=_xlfn.IFS(H42="","", H42<=2,"Low", H42<=5,"Mid", H42<=8,"High", TRUE,"Out of Range")} -> Low | G42: BA/Testing | H42: 2 | I42: 46076 | J42: 46077 | K42: =H42/$O$5 -> 2 | L42: Not Started
A43: Sprint 6 | B43: Mandate | C43: FAS 8112 Mandate Contract Information Maintenance 全委契約資料維護 | D43: BA | E43: Mandate Contract Information Maintenance Requirement Analysis | F43: {=_xlfn.IFS(H43="","", H43<=2,"Low", H43<=5,"Mid", H43<=8,"High", TRUE,"Out of Range")} -> Low | G43: BA/Testing | H43: 2 | I43: 46049 | J43: 46050 | K43: =H43/$O$7 -> 2 | L43: Not Started
A44: Sprint 6 | B44: Mandate | C44: FAS 8112 Mandate Contract Information Maintenance 全委契約資料維護 | D44: BA | E44: Mandate Contract Information Maintenance Requirement | F44: {=_xlfn.IFS(H44="","", H44<=2,"Low", H44<=5,"Mid", H44<=8,"High", TRUE,"Out of Range")} -> Low | G44: BA/Testing | H44: 2 | I44: 46051 | J44: 46052 | K44: =H44/$O$7 -> 2 | L44: Not Started
A45: Sprint 6 | B45: Mandate | C45: FAS 8112 Mandate Contract Information Maintenance 全委契約資料維護 | D45: Development | E45: Mandate Contract Information Maintenance - Development 1 | F45: {=_xlfn.IFS(H45="","", H45<=2,"Low", H45<=5,"Mid", H45<=8,"High", TRUE,"Out of Range")} -> Low | G45: FrontEnd | H45: 2 | I45: 46055 | J45: 46056 | K45: =H45/$O$8 -> 2 | L45: Not Started
A46: Sprint 7 | B46: Mandate | C46: FAS 8112 Mandate Contract Information Maintenance 全委契約資料維護 | D46: Development | E46: Mandate Contract Information Maintenance - Development 2 | F46: {=_xlfn.IFS(H46="","", H46<=2,"Low", H46<=5,"Mid", H46<=8,"High", TRUE,"Out of Range")} -> High | G46: Kent | H46: 8 | I46: 46055 | J46: 46064 | K46: =H46/$O$7 -> 8 | L46: Not Started
A47: Sprint 8 | B47: Mandate | C47: FAS 8112 Mandate Contract Information Maintenance 全委契約資料維護 | D47: Testing | E47: Mandate Contract Information Maintenance QA - unit-testing | F47: {=_xlfn.IFS(H47="","", H47<=2,"Low", H47<=5,"Mid", H47<=8,"High", TRUE,"Out of Range")} -> Low | G47: BA/Testing | H47: 2 | I47: 46078 | J47: 46079 | K47: =H47/$O$5 -> 2 | L47: Not Started
A48: Sprint 6 | B48: Mandate | C48: FAS 8121 Mandate Subscription Data Entry 全委申購資料登錄 | D48: BA | E48: Mandate Subscription Data Entry Requirement Analysis | F48: {=_xlfn.IFS(H48="","", H48<=2,"Low", H48<=5,"Mid", H48<=8,"High", TRUE,"Out of Range")} -> Low | G48: BA/Testing | H48: 2 | I48: 46055 | J48: 46056 | K48: =H48/$O$5 -> 2 | L48: Not Started
A49: Sprint 7 | B49: Mandate | C49: FAS 8121 Mandate Subscription Data Entry 全委申購資料登錄 | D49: BA | E49: Mandate Subscription Data Entry Requirement Doc | F49: {=_xlfn.IFS(H49="","", H49<=2,"Low", H49<=5,"Mid", H49<=8,"High", TRUE,"Out of Range")} -> Low | G49: BA/Testing | H49: 2 | I49: 46062 | J49: 46063 | K49: =H49/$O$5 -> 2 | L49: Not Started
A50: Sprint 7 | B50: Mandate | C50: FAS 8121 Mandate Subscription Data Entry 全委申購資料登錄 | D50: Development | E50: Mandate Subscription Data Entry - Development 1 | F50: {=_xlfn.IFS(H50="","", H50<=2,"Low", H50<=5,"Mid", H50<=8,"High", TRUE,"Out of Range")} -> Low | G50: FrontEnd | H50: 2 | I50: 46064 | J50: 46065 | K50: =H50/$O$8 -> 2 | L50: Not Started
A51: Sprint 8 | B51: Mandate | C51: FAS 8121 Mandate Subscription Data Entry 全委申購資料登錄 | D51: Development | E51: Mandate Subscription Data Entry - Development 2 | F51: {=_xlfn.IFS(H51="","", H51<=2,"Low", H51<=5,"Mid", H51<=8,"High", TRUE,"Out of Range")} -> High | G51: New AP Lead | H51: 8 | I51: 46076 | J51: 46085 | K51: =H51/$O$5 -> 8 | L51: Not Started
A52: Sprint 9 | B52: Mandate | C52: FAS 8121 Mandate Subscription Data Entry 全委申購資料登錄 | D52: Testing | E52: Mandate Subscription Data Entry QA - unit-testing | F52: {=_xlfn.IFS(H52="","", H52<=2,"Low", H52<=5,"Mid", H52<=8,"High", TRUE,"Out of Range")} -> Low | G52: BA/Testing | H52: 2 | I52: 46086 | J52: 46087 | K52: =H52/$O$5 -> 2 | L52: Not Started
A53: Sprint 9 | B53: Mandate | C53: FAS 8122 Mandate Redemption Data Entry 全委買回資料登錄 | D53: BA | E53: Mandate Redemption Data Entry Requirement Analysis | F53: {=_xlfn.IFS(H53="","", H53<=2,"Low", H53<=5,"Mid", H53<=8,"High", TRUE,"Out of Range")} -> Low | G53: BA/Testing | H53: 1 | I53: 46080 | J53: 46080 | K53: =H53/$O$5 -> 1 | L53: Not Started
A54: Sprint 9 | B54: Mandate | C54: FAS 8122 Mandate Redemption Data Entry 全委買回資料登錄 | D54: BA | E54: Mandate Redemption Data Entry Requirement Doc | F54: {=_xlfn.IFS(H54="","", H54<=2,"Low", H54<=5,"Mid", H54<=8,"High", TRUE,"Out of Range")} -> Low | G54: BA/Testing | H54: 2 | I54: 46083 | J54: 46084 | K54: =H54/$O$5 -> 2 | L54: Not Started
A55: Sprint 9 | B55: Mandate | C55: FAS 8122 Mandate Redemption Data Entry 全委買回資料登錄 | D55: Development | E55: Mandate Redemption Data Entry - Development 1 | F55: {=_xlfn.IFS(H55="","", H55<=2,"Low", H55<=5,"Mid", H55<=8,"High", TRUE,"Out of Range")} -> Low | G55: FrontEnd | H55: 1 | I55: 46085 | J55: 46085 | K55: =H55/$O$8 -> 1 | L55: Not Started
A56: Sprint 10 | B56: Mandate | C56: FAS 8122 Mandate Redemption Data Entry 全委買回資料登錄 | D56: Development | E56: Mandate Redemption Data Entry - Development 2 | F56: {=_xlfn.IFS(H56="","", H56<=2,"Low", H56<=5,"Mid", H56<=8,"High", TRUE,"Out of Range")} -> Mid | G56: Kent | H56: 3 | I56: 46086 | J56: 46090 | K56: =H56/$O$5 -> 3 | L56: Not Started
A57: Sprint 11 | B57: Mandate | C57: FAS 8122 Mandate Redemption Data Entry 全委買回資料登錄 | D57: Testing | E57: Mandate Redemption Data Entry QA - unit-testing | F57: {=_xlfn.IFS(H57="","", H57<=2,"Low", H57<=5,"Mid", H57<=8,"High", TRUE,"Out of Range")} -> Low | G57: BA/Testing | H57: 2 | I57: 46091 | J57: 46092 | K57: =H57/$O$5 -> 2 | L57: Not Started
A58: Sprint 11 | B58: Mandate | C58: FAS 8151 Mandate Fund NAV Inquiry 全委基金淨值查詢 | D58: BA | E58: Mandate Fund NAV Inquiry Requirement Analysis | F58: {=_xlfn.IFS(H58="","", H58<=2,"Low", H58<=5,"Mid", H58<=8,"High", TRUE,"Out of Range")} -> Low | G58: BA/Testing | H58: 1 | I58: 46085 | J58: 46085 | K58: =H58/$O$5 -> 1 | L58: Not Started
A59: Sprint 11 | B59: Mandate | C59: FAS 8151 Mandate Fund NAV Inquiry 全委基金淨值查詢 | D59: BA | E59: Mandate Fund NAV Inquiry Requirement Doc | F59: {=_xlfn.IFS(H59="","", H59<=2,"Low", H59<=5,"Mid", H59<=8,"High", TRUE,"Out of Range")} -> Low | G59: BA/Testing | H59: 2 | I59: 46090 | J59: 46091 | K59: =H59/$O$5 -> 2 | L59: Not Started
A60: Sprint 11 | B60: Mandate | C60: FAS 8151 Mandate Fund NAV Inquiry 全委基金淨值查詢 | D60: Development | E60: Mandate Fund NAV Inquiry - Development 1 | F60: {=_xlfn.IFS(H60="","", H60<=2,"Low", H60<=5,"Mid", H60<=8,"High", TRUE,"Out of Range")} -> Low | G60: FrontEnd | H60: 2 | I60: 46092 | J60: 46093 | K60: =H60/$O$8 -> 2 | L60: Not Started
A61: Sprint 12 | B61: Mandate | C61: FAS 8151 Mandate Fund NAV Inquiry 全委基金淨值查詢 | D61: Development | E61: Mandate Fund NAV Inquiry - Development 2 | F61: {=_xlfn.IFS(H61="","", H61<=2,"Low", H61<=5,"Mid", H61<=8,"High", TRUE,"Out of Range")} -> Low | G61: New AP Lead | H61: 2 | I61: 46092 | J61: 46093 | K61: =H61/$O$5 -> 2 | L61: Not Started
A62: Sprint 12 | B62: Mandate | C62: FAS 8151 Mandate Fund NAV Inquiry 全委基金淨值查詢 | D62: Testing | E62: Mandate Fund NAV Inquiry QA - unit-testing | F62: {=_xlfn.IFS(H62="","", H62<=2,"Low", H62<=5,"Mid", H62<=8,"High", TRUE,"Out of Range")} -> Low | G62: BA/Testing | H62: 2 | I62: 46094 | J62: 46097 | K62: =H62/$O$5 -> 2 | L62: Not Started
A63: Sprint 12 | B63: Mandate | C63: FAS 8152 Mandate Account Holdings Inquiry 全委帳戶庫存查詢 | D63: BA | E63: Mandate Fund NAV Inquiry Requirement Analysis | F63: {=_xlfn.IFS(H63="","", H63<=2,"Low", H63<=5,"Mid", H63<=8,"High", TRUE,"Out of Range")} -> Low | G63: BA/Testing | H63: 1 | I63: 46092 | J63: 46092 | K63: =H63/$O$5 -> 1 | L63: Not Started
A64: Sprint 13 | B64: Mandate | C64: FAS 8152 Mandate Account Holdings Inquiry 全委帳戶庫存查詢 | D64: BA | E64: Mandate Fund NAV Inquiry Requirement Doc | F64: {=_xlfn.IFS(H64="","", H64<=2,"Low", H64<=5,"Mid", H64<=8,"High", TRUE,"Out of Range")} -> Low | G64: BA/Testing | H64: 1 | I64: 46093 | J64: 46093 | K64: =H64/$O$5 -> 1 | L64: Not Started
A65: Sprint 13 | B65: Mandate | C65: FAS 8152 Mandate Account Holdings Inquiry 全委帳戶庫存查詢 | D65: Development | E65: Mandate Fund NAV Inquiry - Development 1 | F65: {=_xlfn.IFS(H65="","", H65<=2,"Low", H65<=5,"Mid", H65<=8,"High", TRUE,"Out of Range")} -> Low | G65: FrontEnd | H65: 1 | I65: 46098 | J65: 46098 | K65: =H65/$O$8 -> 1 | L65: Not Started
A66: Sprint 13 | B66: Mandate | C66: FAS 8152 Mandate Account Holdings Inquiry 全委帳戶庫存查詢 | D66: Development | E66: Mandate Fund NAV Inquiry - Development 2 | F66: {=_xlfn.IFS(H66="","", H66<=2,"Low", H66<=5,"Mid", H66<=8,"High", TRUE,"Out of Range")} -> Mid | G66: Kent | H66: 3 | I66: 46098 | J66: 46100 | K66: =H66/$O$5 -> 3 | L66: Not Started
A67: Sprint 13 | B67: Mandate | C67: FAS 8152 Mandate Account Holdings Inquiry 全委帳戶庫存查詢 | D67: Testing | E67: Mandate Fund NAV Inquiry QA - unit-testing | F67: {=_xlfn.IFS(H67="","", H67<=2,"Low", H67<=5,"Mid", H67<=8,"High", TRUE,"Out of Range")} -> Low | G67: BA/Testing | H67: 1 | I67: 46101 | J67: 46101 | K67: =H67/$O$5 -> 1 | L67: Not Started
A68: Sprint 5 | B68: Mandate | C68: FAS 81611 Subscription Details Report 申購資料明細表 | D68: BA | E68: Subscription Details Report Requirement Analysis | F68: {=_xlfn.IFS(H68="","", H68<=2,"Low", H68<=5,"Mid", H68<=8,"High", TRUE,"Out of Range")} -> Low | G68: BA/Testing | H68: 1 | I68: 46098 | J68: 46098 | K68: =H68/$O$6 -> 1 | L68: Not Started
A69: Sprint 6 | B69: Mandate | C69: FAS 81611 Subscription Details Report 申購資料明細表 | D69: BA | E69: Subscription Details Report Requirement | F69: {=_xlfn.IFS(H69="","", H69<=2,"Low", H69<=5,"Mid", H69<=8,"High", TRUE,"Out of Range")} -> Low | G69: BA/Testing | H69: 1 | I69: 46099 | J69: 46099 | K69: =H69/$O$6 -> 1 | L69: Not Started
A70: Sprint 6 | B70: Mandate | C70: FAS 81611 Subscription Details Report 申購資料明細表 | D70: Development | E70: Subscription Details Report - Development 1 | F70: {=_xlfn.IFS(H70="","", H70<=2,"Low", H70<=5,"Mid", H70<=8,"High", TRUE,"Out of Range")} -> Low | G70: FrontEnd | H70: 1 | I70: 46104 | J70: 46104 | K70: =H70/$O$8 -> 1 | L70: Not Started
A71: Sprint 6 | B71: Mandate | C71: FAS 81611 Subscription Details Report 申購資料明細表 | D71: Development | E71: Subscription Details Report - Development 2 | F71: {=_xlfn.IFS(H71="","", H71<=2,"Low", H71<=5,"Mid", H71<=8,"High", TRUE,"Out of Range")} -> Low | G71: New AP Lead | H71: 2 | I71: 46104 | J71: 46105 | K71: =H71/$O$7 -> 2 | L71: Not Started
A72: Sprint 7 | B72: Mandate | C72: FAS 81611 Subscription Details Report 申購資料明細表 | D72: Testing | E72: Subscription Details Report QA - unit-testing | F72: {=_xlfn.IFS(H72="","", H72<=2,"Low", H72<=5,"Mid", H72<=8,"High", TRUE,"Out of Range")} -> Low | G72: BA/Testing | H72: 1 | I72: 46106 | J72: 46106 | K72: =H72/$O$5 -> 1 | L72: Not Started
A73: Sprint 7 | B73: Mandate | C73: FAS 81621 Redemption Details Report 買回資料明細表 | D73: BA | E73: Redemption Details Report Requirement Analysis | F73: {=_xlfn.IFS(H73="","", H73<=2,"Low", H73<=5,"Mid", H73<=8,"High", TRUE,"Out of Range")} -> Low | G73: BA/Testing | H73: 2 | I73: 46104 | J73: 46105 | K73: =H73/$O$6 -> 2 | L73: Not Started
A74: Sprint 8 | B74: Mandate | C74: FAS 81621 Redemption Details Report 買回資料明細表 | D74: BA | E74: Redemption Details Report Requirement | F74: {=_xlfn.IFS(H74="","", H74<=2,"Low", H74<=5,"Mid", H74<=8,"High", TRUE,"Out of Range")} -> Low | G74: BA/Testing | H74: 2 | I74: 46107 | J74: 46108 | K74: =H74/$O$6 -> 2 | L74: Not Started
A75: Sprint 8 | B75: Mandate | C75: FAS 81621 Redemption Details Report 買回資料明細表 | D75: Development | E75: Redemption Details Report - Development 1 | F75: {=_xlfn.IFS(H75="","", H75<=2,"Low", H75<=5,"Mid", H75<=8,"High", TRUE,"Out of Range")} -> Mid | G75: FrontEnd | H75: 3 | I75: 46111 | J75: 46113 | K75: =H75/$O$8 -> 3 | L75: Not Started
A76: Sprint 8 | B76: Mandate | C76: FAS 81621 Redemption Details Report 買回資料明細表 | D76: Development | E76: Redemption Details Report - Development 2 | F76: {=_xlfn.IFS(H76="","", H76<=2,"Low", H76<=5,"Mid", H76<=8,"High", TRUE,"Out of Range")} -> Mid | G76: New AP Lead | H76: 5 | I76: 46111 | J76: 46119 | K76: =H76/$O$7 -> 5 | L76: Not Started
A77: Sprint 9 | B77: Mandate | C77: FAS 81621 Redemption Details Report 買回資料明細表 | D77: Testing | E77: Redemption Details Report QA - unit-testing | F77: {=_xlfn.IFS(H77="","", H77<=2,"Low", H77<=5,"Mid", H77<=8,"High", TRUE,"Out of Range")} -> Low | G77: BA/Testing | H77: 1 | I77: 46120 | J77: 46120 | K77: =H77/$O$5 -> 1 | L77: Not Started
A78: Sprint 9 | B78: Mandate | C78: FAS 8171 Mandate NAV Import Process (State Street) 全委淨值匯入作業(道富) | D78: BA | E78: Mandate NAV Import Process (State Street) Requirement Analysis | F78: {=_xlfn.IFS(H78="","", H78<=2,"Low", H78<=5,"Mid", H78<=8,"High", TRUE,"Out of Range")} -> Low | G78: BA/Testing | H78: 1 | I78: 46111 | J78: 46111 | K78: =H78/$O$6 -> 1 | L78: Not Started
A79: Sprint 10 | B79: Mandate | C79: FAS 8171 Mandate NAV Import Process (State Street) 全委淨值匯入作業(道富) | D79: BA | E79: Mandate NAV Import Process (State Street) Requirement | F79: {=_xlfn.IFS(H79="","", H79<=2,"Low", H79<=5,"Mid", H79<=8,"High", TRUE,"Out of Range")} -> Low | G79: BA/Testing | H79: 2 | I79: 46112 | J79: 46113 | K79: =H79/$O$6 -> 2 | L79: Not Started
A80: Sprint 10 | B80: Mandate | C80: FAS 8171 Mandate NAV Import Process (State Street) 全委淨值匯入作業(道富) | D80: Development | E80: Mandate NAV Import Process (State Street) - Development 1 | F80: {=_xlfn.IFS(H80="","", H80<=2,"Low", H80<=5,"Mid", H80<=8,"High", TRUE,"Out of Range")} -> Low | G80: FrontEnd | H80: 2 | I80: 46114 | J80: 46119 | K80: =H80/$O$8 -> 2 | L80: Not Started
A81: Sprint 11 | B81: Mandate | C81: FAS 8171 Mandate NAV Import Process (State Street) 全委淨值匯入作業(道富) | D81: Development | E81: Mandate NAV Import Process (State Street) - Development 2 | F81: {=_xlfn.IFS(H81="","", H81<=2,"Low", H81<=5,"Mid", H81<=8,"High", TRUE,"Out of Range")} -> Mid | G81: New AP Lead | H81: 4 | I81: 46120 | J81: 46125 | K81: =H81/$O$7 -> 4 | L81: Not Started
A82: Sprint 12 | B82: Mandate | C82: FAS 8171 Mandate NAV Import Process (State Street) 全委淨值匯入作業(道富) | D82: Testing | E82: Mandate NAV Import Process (State Street) QA - unit-testing | F82: {=_xlfn.IFS(H82="","", H82<=2,"Low", H82<=5,"Mid", H82<=8,"High", TRUE,"Out of Range")} -> Low | G82: BA/Testing | H82: 2 | I82: 46126 | J82: 46127 | K82: =H82/$O$5 -> 2 | L82: Not Started
A83: Sprint 12 | B83: Mandate | C83: FAS 81811 Generate Mandate Subscription/Redemption Data 全委申贖資料產生 | D83: BA | E83: Generate Mandate Subscription/Redemption Data Requirement Analysis | F83: {=_xlfn.IFS(H83="","", H83<=2,"Low", H83<=5,"Mid", H83<=8,"High", TRUE,"Out of Range")} -> Low | G83: BA/Testing | H83: 1 | I83: 46114 | J83: 46114 | K83: =H83/$O$6 -> 1 | L83: Not Started
A84: Sprint 12 | B84: Mandate | C84: FAS 81811 Generate Mandate Subscription/Redemption Data 全委申贖資料產生 | D84: BA | E84: Generate Mandate Subscription/Redemption Data Requirement | F84: {=_xlfn.IFS(H84="","", H84<=2,"Low", H84<=5,"Mid", H84<=8,"High", TRUE,"Out of Range")} -> Low | G84: BA/Testing | H84: 1 | I84: 46121 | J84: 46121 | K84: =H84/$O$6 -> 1 | L84: Not Started
A85: Sprint 13 | B85: Mandate | C85: FAS 81811 Generate Mandate Subscription/Redemption Data 全委申贖資料產生 | D85: Development | E85: Generate Mandate Subscription/Redemption Data - Development 1 | F85: {=_xlfn.IFS(H85="","", H85<=2,"Low", H85<=5,"Mid", H85<=8,"High", TRUE,"Out of Range")} -> Low | G85: FrontEnd | H85: 2 | I85: 46122 | J85: 46125 | K85: =H85/$O$8 -> 2 | L85: Not Started
A86: Sprint 13 | B86: Mandate | C86: FAS 81811 Generate Mandate Subscription/Redemption Data 全委申贖資料產生 | D86: Development | E86: Generate Mandate Subscription/Redemption Data - Development 2 | F86: {=_xlfn.IFS(H86="","", H86<=2,"Low", H86<=5,"Mid", H86<=8,"High", TRUE,"Out of Range")} -> Mid | G86: New AP Lead | H86: 3 | I86: 46126 | J86: 46128 | K86: =H86/$O$7 -> 3 | L86: Not Started
A87: Sprint 14 | B87: Mandate | C87: FAS 81811 Generate Mandate Subscription/Redemption Data 全委申贖資料產生 | D87: Testing | E87: Generate Mandate Subscription/Redemption Data QA - unit-testing | F87: {=_xlfn.IFS(H87="","", H87<=2,"Low", H87<=5,"Mid", H87<=8,"High", TRUE,"Out of Range")} -> Low | G87: BA/Testing | H87: 1 | I87: 46129 | J87: 46129 | K87: =H87/$O$5 -> 1 | L87: Not Started
A88: Sprint 15 | B88: Mandate | C88: FAS 81812 Export Mandate Subscription/Redemption Data 全委申贖資料匯出 | D88: BA | E88: Export Mandate Subscription/Redemption Data Requirement Analysis | F88: {=_xlfn.IFS(H88="","", H88<=2,"Low", H88<=5,"Mid", H88<=8,"High", TRUE,"Out of Range")} -> Low | G88: BA/Testing | H88: 2 | I88: 46122 | J88: 46125 | K88: =H88/$O$6 -> 2 | L88: Not Started
A89: Sprint 15 | B89: Mandate | C89: FAS 81812 Export Mandate Subscription/Redemption Data 全委申贖資料匯出 | D89: BA | E89: Export Mandate Subscription/Redemption Data Requirement | F89: {=_xlfn.IFS(H89="","", H89<=2,"Low", H89<=5,"Mid", H89<=8,"High", TRUE,"Out of Range")} -> Low | G89: BA/Testing | H89: 2 | I89: 46132 | J89: 46133 | K89: =H89/$O$6 -> 2 | L89: Not Started
A90: Sprint 15 | B90: Mandate | C90: FAS 81812 Export Mandate Subscription/Redemption Data 全委申贖資料匯出 | D90: Development | E90: Export Mandate Subscription/Redemption Data - Development 1 | F90: {=_xlfn.IFS(H90="","", H90<=2,"Low", H90<=5,"Mid", H90<=8,"High", TRUE,"Out of Range")} -> Low | G90: FrontEnd | H90: 2 | I90: 46134 | J90: 46135 | K90: =H90/$O$8 -> 2 | L90: Not Started
A91: Sprint 16 | B91: Mandate | C91: FAS 81812 Export Mandate Subscription/Redemption Data 全委申贖資料匯出 | D91: Development | E91: Export Mandate Subscription/Redemption Data - Development 2 | F91: {=_xlfn.IFS(H91="","", H91<=2,"Low", H91<=5,"Mid", H91<=8,"High", TRUE,"Out of Range")} -> Mid | G91: New AP Lead | H91: 5 | I91: 46134 | J91: 46140 | K91: =H91/$O$7 -> 5 | L91: Not Started
A92: Sprint 16 | B92: Mandate | C92: FAS 81812 Export Mandate Subscription/Redemption Data 全委申贖資料匯出 | D92: Testing | E92: Export Mandate Subscription/Redemption Data QA - unit-testing | F92: {=_xlfn.IFS(H92="","", H92<=2,"Low", H92<=5,"Mid", H92<=8,"High", TRUE,"Out of Range")} -> Low | G92: BA/Testing | H92: 2 | I92: 46141 | J92: 46142 | K92: =H92/$O$5 -> 2 | L92: Not Started
A93: Sprint 17 | B93: Mandate | C93: FAS 81831 Generate SSB Mandate Subscription/Redemption Data 產生SSB全委申贖資料 | D93: BA | E93: Generate SSB Mandate Subscription/Redemption Data Requirement Analysis | F93: {=_xlfn.IFS(H93="","", H93<=2,"Low", H93<=5,"Mid", H93<=8,"High", TRUE,"Out of Range")} -> Low | G93: BA/Testing | H93: 1 | I93: 46134 | J93: 46134 | K93: =H93/$O$6 -> 1 | L93: Not Started
A94: Sprint 17 | B94: Mandate | C94: FAS 81831 Generate SSB Mandate Subscription/Redemption Data 產生SSB全委申贖資料 | D94: BA | E94: Generate SSB Mandate Subscription/Redemption Data Requirement | F94: {=_xlfn.IFS(H94="","", H94<=2,"Low", H94<=5,"Mid", H94<=8,"High", TRUE,"Out of Range")} -> Low | G94: BA/Testing | H94: 1 | I94: 46135 | J94: 46135 | K94: =H94/$O$6 -> 1 | L94: Not Started
A95: Sprint 17 | B95: Mandate | C95: FAS 81831 Generate SSB Mandate Subscription/Redemption Data 產生SSB全委申贖資料 | D95: Development | E95: Generate SSB Mandate Subscription/Redemption Data - Development 1 | F95: {=_xlfn.IFS(H95="","", H95<=2,"Low", H95<=5,"Mid", H95<=8,"High", TRUE,"Out of Range")} -> Low | G95: FrontEnd | H95: 2 | I95: 46136 | J95: 46139 | K95: =H95/$O$8 -> 2 | L95: Not Started
A96: Sprint 18 | B96: Mandate | C96: FAS 81831 Generate SSB Mandate Subscription/Redemption Data 產生SSB全委申贖資料 | D96: Development | E96: Generate SSB Mandate Subscription/Redemption Data - Development 2 | F96: {=_xlfn.IFS(H96="","", H96<=2,"Low", H96<=5,"Mid", H96<=8,"High", TRUE,"Out of Range")} -> Mid | G96: New AP Lead | H96: 3 | I96: 46141 | J96: 46146 | K96: =H96/$O$7 -> 3 | L96: Not Started
A97: Sprint 19 | B97: Mandate | C97: FAS 81831 Generate SSB Mandate Subscription/Redemption Data 產生SSB全委申贖資料 | D97: Testing | E97: Generate SSB Mandate Subscription/Redemption Data QA - unit-testing | F97: {=_xlfn.IFS(H97="","", H97<=2,"Low", H97<=5,"Mid", H97<=8,"High", TRUE,"Out of Range")} -> Low | G97: BA/Testing | H97: 1 | I97: 46147 | J97: 46147 | K97: =H97/$O$5 -> 1 | L97: Not Started
A98: Sprint 19 | B98: Mandate | C98: FAS 81832 Export SSB Mandate Subscription/Redemption Data 匯出SSB全委申贖資料 | D98: BA | E98: Export SSB Mandate Subscription/Redemption Data Requirement Analysis | F98: {=_xlfn.IFS(H98="","", H98<=2,"Low", H98<=5,"Mid", H98<=8,"High", TRUE,"Out of Range")} -> Low | G98: BA/Testing | H98: 2 | I98: 46136 | J98: 46139 | K98: =H98/$O$6 -> 2 | L98: Not Started
A99: Sprint 19 | B99: Mandate | C99: FAS 81832 Export SSB Mandate Subscription/Redemption Data 匯出SSB全委申贖資料 | D99: BA | E99: Export SSB Mandate Subscription/Redemption Data Requirement | F99: {=_xlfn.IFS(H99="","", H99<=2,"Low", H99<=5,"Mid", H99<=8,"High", TRUE,"Out of Range")} -> Low | G99: BA/Testing | H99: 2 | I99: 46140 | J99: 46146 | K99: =H99/$O$6 -> 2 | L99: Not Started
A100: Sprint 19 | B100: Mandate | C100: FAS 81832 Export SSB Mandate Subscription/Redemption Data 匯出SSB全委申贖資料 | D100: Development | E100: Export SSB Mandate Subscription/Redemption Data - Development 1 | F100: {=_xlfn.IFS(H100="","", H100<=2,"Low", H100<=5,"Mid", H100<=8,"High", TRUE,"Out of Range")} -> Mid | G100: FrontEnd | H100: 3 | I100: 46147 | J100: 46149 | K100: =H100/$O$8 -> 3 | L100: Not Started
A101: Sprint 20 | B101: Mandate | C101: FAS 81832 Export SSB Mandate Subscription/Redemption Data 匯出SSB全委申贖資料 | D101: Development | E101: Export SSB Mandate Subscription/Redemption Data - Development 2 | F101: {=_xlfn.IFS(H101="","", H101<=2,"Low", H101<=5,"Mid", H101<=8,"High", TRUE,"Out of Range")} -> Mid | G101: New AP Lead | H101: 5 | I101: 46147 | J101: 46153 | K101: =H101/$O$7 -> 5 | L101: Not Started
...

Sheet Project Planning - A
C1: DMS Development
B3: TOTAL TASKS | C3: =COUNTA(E18:E1048576) -> 199 | F3: DURATION | G3: =G5-G4+1 -> 762 | I3: Overall Progress | M3: Team Member | N3: FTE | O3: Cost / Monthly | P3: 1 year
B4: Completed | C4: =COUNTIF(K18:K1048576,B4) -> 2 | F4: START | G4: =MIN(H12:H1048576) -> 45717 | K4: =SUM(G12:G17) -> 24 | M4: Kent | N4: 1
B5: In progress | C5: =COUNTIF(K18:K1048576,B5) -> 7 | F5: FINISH | G5: =MAX(I12:I1048576) -> 46478 | K5: =SUM(G12:G216) -> 419 | M5: AP Lead | N5: 1
B6: Not Started | C6: =COUNTIF(K18:K1048576,B6) -> 191 | M6: FrontEnd1 | N6: 1 | O6: =145000*1.05 -> 152250 | P6: =O6*12 -> 1827000
I7: =1-I5 -> 1 | K7: =K4/K5 -> 0.057279236 | M7: Patrick-BA | N7: 0.5
A11: SPRINT | B11: EPIC | C11: FEATURE | D11: TASKS | E11: STORIES | F11: RESPONSIBLE | G11: Man Day Required | H11: START | I11: FINISH | J11: DURATION | K11: STATUS
A12: Sprint 0 | B12: Shareholders' Meeting & Management | C12: Data Mapping, Data Migration & Create Tables in DB | D12: BA | E12: Data Mapping, Data Migration & Create Tables in DB Requirement Analysis | F12: BA | G12: 3 | H12: 45915 | I12: =WORKDAY(H12,J12) -> 45918 | J12: =G12/$N$4 -> 3 | K12: Completed
A13: Sprint 0 | B13: Shareholders' Meeting & Management | C13: Data Mapping, Data Migration & Create Tables in DB | D13: BA | E13: Data Mapping, Data Migration & Create Tables in DB Requirement | F13: BA | G13: 3 | H13: =WORKDAY(I12,1) -> 45919 | I13: =WORKDAY(H13,J13) -> 45924 | J13: =G13/$N$4 -> 3 | K13: Completed
A14: Sprint 0 | B14: Shareholders' Meeting & Management | C14: Data Mapping, Data Migration & Create Tables in DB | D14: Development | E14: Data Mapping - Development | F14: Kent | G14: 5 | H14: =WORKDAY(I13,1) -> 45925 | I14: =WORKDAY(H14,J14) -> 45932 | J14: =G14/$N$4 -> 5 | K14: Completed
A15: Sprint 0 | B15: Shareholders' Meeting & Management | C15: Data Mapping, Data Migration & Create Tables in DB | D15: Development | E15: Data Migration - Development | F15: Kent | G15: 5 | H15: =WORKDAY(I14,1) -> 45933 | I15: =WORKDAY(H15,J15) -> 45940 | J15: =G15/$N$4 -> 5 | K15: Completed
A16: Sprint 0 | B16: Shareholders' Meeting & Management | C16: Data Mapping, Data Migration & Create Tables in DB | D16: Development | E16: Create Tables in DB - Development | F16: Kent | G16: 5 | H16: =WORKDAY(I15,1) -> 45943 | I16: =WORKDAY(H16,J16) -> 45950 | J16: =G16/$N$4 -> 5 | K16: Completed
A17: Sprint 0 | B17: Shareholders' Meeting & Management | C17: Data Mapping, Data Migration & Create Tables in DB | D17: QA | E17: Data Related QA - unit testing | F17: QA | G17: 3 | H17: =WORKDAY(I16,1) -> 45951 | I17: =WORKDAY(H17,J17) -> 45954 | J17: =G17/$N$4 -> 3 | K17: Completed
A18: Sprint 1 | B18: Dividend Distribution | C18: Data Mapping, Data Migration & Create Tables in DB | D18: BA | E18: Data Related Detail Requirement Analysis | F18: Patrick-BA | G18: 3 | H18: 45985 | I18: =WORKDAY(H18,J18) -> 45993 | J18: =G18/$N$7 -> 6 | K18: Completed
A19: Sprint 1 | B19: Dividend Distribution | C19: Data Mapping, Data Migration & Create Tables in DB | D19: BA | E19: Data Related Document Detail Requirement | F19: Patrick-BA | G19: 3 | H19: =WORKDAY(I18,1) -> 45994 | I19: =WORKDAY(H19,J19) -> 46002 | J19: =G19/$N$7 -> 6 | K19: Completed
A20: Sprint 1 | B20: Dividend Distribution | C20: Data Mapping, Data Migration & Create Tables in DB | D20: Development | E20: Data Mapping - Development | F20: Kent | G20: 3 | H20: =WORKDAY(I19,1) -> 46003 | I20: =WORKDAY(H20,J20) -> 46008 | J20: =G20/$N$4 -> 3 | K20: In progress
A21: Sprint 1 | B21: Dividend Distribution | C21: Data Mapping, Data Migration & Create Tables in DB | D21: Development | E21: Data Migration - Development | F21: Kent | G21: 5 | H21: =WORKDAY(I20,1) -> 46009 | I21: =WORKDAY(H21,J21) -> 46016 | J21: =G21/$N$4 -> 5 | K21: Not Started
A22: Sprint 2 | B22: Dividend Distribution | C22: Data Mapping, Data Migration & Create Tables in DB | D22: Development | E22: Create Tables in DB - Development | F22: Kent | G22: 2 | H22: =WORKDAY(I21,1) -> 46017 | I22: =WORKDAY(H22,J22) -> 46021 | J22: =G22/$N$4 -> 2 | K22: Not Started
A23: Sprint 2 | B23: Dividend Distribution | C23: Data Mapping, Data Migration & Create Tables in DB | D23: QA | E23: Data Related QA - unit testing | F23: Kent | G23: 3 | H23: =WORKDAY(I22,1) -> 46022 | I23: =WORKDAY(H23,J23) -> 46027 | J23: =G23/$N$4 -> 3 | K23: Not Started
A24: Sprint 2 | B24: Dividend Distribution | C24: Maintain Distributable Balance 可分配餘額維護作業 | D24: BA | E24: Maintain Distributable Balance Detail Requirement Analysis | F24: Patrick-BA | G24: 1.5 | H24: =WORKDAY(I19,1) -> 46003 | I24: =WORKDAY(H24,J24) -> 46008 | J24: =G24/$N$7 -> 3 | K24: In progress
A25: Sprint 2 | B25: Dividend Distribution | C25: Maintain Distributable Balance 可分配餘額維護作業 | D25: BA | E25: Maintain Distributable Document Detail Requirement | F25: Patrick-BA | G25: 1.5 | H25: =WORKDAY(I24,1) -> 46009 | I25: =WORKDAY(H25,J25) -> 46014 | J25: =G25/$N$7 -> 3 | K25: In progress
A26: Sprint 2 | B26: Dividend Distribution | C26: Maintain Distributable Balance 可分配餘額維護作業 | D26: Development | E26: Maintain Distributable Balance - Development 1 | F26: FrontEnd | G26: 1 | H26: =WORKDAY(I25,1) -> 46015 | I26: =WORKDAY(H26,J26) -> 46016 | J26: =G26/$N$4 -> 1 | K26: Not Started
A27: Sprint 3 | B27: Dividend Distribution | C27: Maintain Distributable Balance 可分配餘額維護作業 | D27: Development | E27: Maintain Distributable Balance - Development 2 | F27: Kent | G27: 7 | H27: =WORKDAY(I22,1) -> 46022 | I27: =WORKDAY(H27,J27) -> 46031 | J27: =G27/$N$4 -> 7 | K27: Not Started
A28: Sprint 3 | B28: Dividend Distribution | C28: Maintain Distributable Balance 可分配餘額維護作業 | D28: QA | E28: Maintain Distributable Balance QA - unit testing | F28: Kent | G28: 3 | H28: =WORKDAY(I27,1) -> 46034 | I28: =WORKDAY(H28,J28) -> 46037 | J28: =G28/$N$4 -> 3 | K28: Not Started
A29: Sprint 3 | B29: Dividend Distribution | C29: Domestic Dividend Information Inquiry 境內配息資訊查詢作業 | D29: BA | E29: Domestic Dividend Information Inquiry Detail Requirement Analysis | F29: Patrick-BA | G29: 1.5 | H29: =WORKDAY(I25,1) -> 46015 | I29: =WORKDAY(H29,J29) -> 46020 | J29: =G29/$N$7 -> 3 | K29: In progress
A30: Sprint 3 | B30: Dividend Distribution | C30: Domestic Dividend Information Inquiry 境內配息資訊查詢作業 | D30: BA | E30: Domestic Dividend Information Inquiry Document Detail Requirement | F30: Patrick-BA | G30: 1.5 | H30: =WORKDAY(I26,1) -> 46017 | I30: =WORKDAY(H30,J30) -> 46022 | J30: =G30/$N$7 -> 3 | K30: In progress
A31: Sprint 4 | B31: Dividend Distribution | C31: Domestic Dividend Information Inquiry 境內配息資訊查詢作業 | D31: Development | E31: Domestic Dividend Information Inquiry - Development 1 | F31: FrontEnd | G31: 4 | H31: =WORKDAY(I30,1) -> 46023 | I31: =WORKDAY(H31,J31) -> 46029 | J31: =G31/$N$4 -> 4 | K31: Not Started
A32: Sprint 4 | B32: Dividend Distribution | C32: Domestic Dividend Information Inquiry 境內配息資訊查詢作業 | D32: Development | E32: Domestic Dividend Information Inquiry - Development 2 | F32: Kent | G32: 4 | H32: =WORKDAY(I28,1) -> 46038 | I32: =WORKDAY(H32,J32) -> 46044 | J32: =G32/$N$4 -> 4 | K32: Not Started
A33: Sprint 5 | B33: Dividend Distribution | C33: Domestic Dividend Information Inquiry 境內配息資訊查詢作業 | D33: QA | E33: Domestic Dividend Information Inquiry QA - unit testing | F33: Kent | G33: 2 | H33: =WORKDAY(I32,1) -> 46045 | I33: =WORKDAY(H33,J33) -> 46049 | J33: =G33/$N$4 -> 2 | K33: Not Started
A34: Sprint 3 | B34: Dividend Distribution | C34: Upload Domestic Dividend Composition Info to EC 境內配息組成資訊上傳EC | D34: BA | E34: Upload Domestic Dividend Composition Info to EC - Detail Requirement Analysis | F34: Patrick-BA | G34: 1.5 | H34: =WORKDAY(I30,1) -> 46023 | I34: =WORKDAY(H34,J34) -> 46028 | J34: =G34/$N$7 -> 3 | K34: In progress
A35: Sprint 3 | B35: Dividend Distribution | C35: Upload Domestic Dividend Composition Info to EC 境內配息組成資訊上傳EC | D35: BA | E35: Upload Domestic Dividend Composition Info to EC - Document Detail Requirement | F35: Patrick-BA | G35: 1.5 | H35: =WORKDAY(I34,1) -> 46029 | I35: =WORKDAY(H35,J35) -> 46034 | J35: =G35/$N$7 -> 3 | K35: In progress
A36: Sprint 5 | B36: Dividend Distribution | C36: Upload Domestic Dividend Composition Info to EC 境內配息組成資訊上傳EC | D36: Development | E36: Upload Domestic Dividend Composition Info to EC - Development 1 | F36: FrontEnd | G36: 4 | H36: =WORKDAY(I31,1) -> 46030 | I36: =WORKDAY(H36,J36) -> 46036 | J36: =G36/$N$4 -> 4 | K36: Not Started
A37: Sprint 5 | B37: Dividend Distribution | C37: Upload Domestic Dividend Composition Info to EC 境內配息組成資訊上傳EC | D37: Development | E37: Upload Domestic Dividend Composition Info to EC - Development 2 | F37: Kent | G37: 4 | H37: =WORKDAY(I33,1) -> 46050 | I37: =WORKDAY(H37,J37) -> 46056 | J37: =G37/$N$4 -> 4 | K37: Not Started
A38: Sprint 6 | B38: Dividend Distribution | C38: Upload Domestic Dividend Composition Info to EC 境內配息組成資訊上傳EC | D38: QA | E38: Upload Domestic Dividend Composition Info to EC QA - unit testing | F38: Kent | G38: 2 | H38: =WORKDAY(I37,1) -> 46057 | I38: =WORKDAY(H38,J38) -> 46059 | J38: =G38/$N$4 -> 2 | K38: Not Started
A39: Sprint 1 | B39: Mandate | C39: Data Mapping, Data Migration & Create Tables in DB | D39: BA | E39: Data Mapping, Data Migration & Create Tables in DB Requirement Analysis | F39: New AP Lead | G39: 3 | H39: 46022 | I39: =WORKDAY(H39,J39) -> 46027 | J39: =IF(F39="New AP Lead", G39/$N$5, IF(F39="Kent", G39/$N$4, "")) -> 3 | K39: Not Started
A40: Sprint 2 | B40: Mandate | C40: Data Mapping, Data Migration & Create Tables in DB | D40: BA | E40: Data Mapping, Data Migration & Create Tables in DB Requirement | F40: New AP Lead | G40: 3 | H40: =WORKDAY(I39,1) -> 46028 | I40: =WORKDAY(H40,J40) -> 46031 | J40: =IF(F40="New AP Lead", G40/$N$5, IF(F40="Kent", G40/$N$4, "")) -> 3 | K40: Not Started
A41: Sprint 2 | B41: Mandate | C41: Data Mapping, Data Migration & Create Tables in DB | D41: Development | E41: Data Mapping - Development | F41: New AP Lead | G41: 4 | H41: =WORKDAY(I39,1) -> 46028 | I41: =WORKDAY(H41,J41) -> 46034 | J41: =IF(F41="New AP Lead", G41/$N$5, IF(F41="Kent", G41/$N$4, "")) -> 4 | K41: Not Started
A42: Sprint 3 | B42: Mandate | C42: Data Mapping, Data Migration & Create Tables in DB | D42: Development | E42: Data Migration - Development | F42: New AP Lead | G42: 4 | H42: =WORKDAY(I41,1) -> 46035 | I42: =WORKDAY(H42,J42) -> 46041 | J42: =IF(F42="New AP Lead", G42/$N$5, IF(F42="Kent", G42/$N$4, "")) -> 4 | K42: Not Started
A43: Sprint 4 | B43: Mandate | C43: Data Mapping, Data Migration & Create Tables in DB | D43: Development | E43: Create Tables in DB - Development | F43: New AP Lead | G43: 2 | H43: =WORKDAY(I42,1) -> 46042 | I43: =WORKDAY(H43,J43) -> 46044 | J43: =IF(F43="New AP Lead", G43/$N$5, IF(F43="Kent", G43/$N$4, "")) -> 2 | K43: Not Started
A44: Sprint 5 | B44: Mandate | C44: Data Mapping, Data Migration & Create Tables in DB | D44: QA | E44: Data Related QA - unit testing | F44: New AP Lead | G44: 3 | H44: =WORKDAY(I43,1) -> 46045 | I44: =WORKDAY(H44,J44) -> 46050 | J44: =IF(F44="New AP Lead", G44/$N$5, IF(F44="Kent", G44/$N$4, "")) -> 3 | K44: Not Started
A45: Sprint 4 | B45: Mandate | C45: FAS 8111 Mandate Client Information Maintenance 全委委託人資料維護 | D45: BA | E45: Mandate Client Information Maintenance Requirement Analysis | F45: New AP Lead | G45: 2 | H45: =WORKDAY(I44,1) -> 46051 | I45: =WORKDAY(H45,J45) -> 46055 | J45: =IF(F45="New AP Lead", G45/$N$5, IF(F45="Kent", G45/$N$4, "")) -> 2 | K45: Not Started
A46: Sprint 4 | B46: Mandate | C46: FAS 8111 Mandate Client Information Maintenance 全委委託人資料維護 | D46: BA | E46: Mandate Client Information Maintenance Requirement | F46: New AP Lead | G46: 2 | H46: =WORKDAY(I45,1) -> 46056 | I46: =WORKDAY(H46,J46) -> 46058 | J46: =IF(F46="New AP Lead", G46/$N$5, IF(F46="Kent", G46/$N$4, "")) -> 2 | K46: Not Started
A47: Sprint 4 | B47: Mandate | C47: FAS 8111 Mandate Client Information Maintenance 全委委託人資料維護 | D47: Development | E47: Mandate Client Information Maintenance - Development 1 | F47: FrontEnd | G47: 2 | H47: =WORKDAY(I46,1) -> 46059 | I47: =WORKDAY(H47,J47) -> 46063 | J47: =G47/$N$6 -> 2 | K47: Not Started
A48: Sprint 5 | B48: Mandate | C48: FAS 8111 Mandate Client Information Maintenance 全委委託人資料維護 | D48: Development | E48: Mandate Client Information Maintenance - Development 2 | F48: New AP Lead | G48: 8 | H48: =WORKDAY(I46,1) -> 46059 | I48: =WORKDAY(H48,J48) -> 46071 | J48: =IF(F48="New AP Lead", G48/$N$5, IF(F48="Kent", G48/$N$4, "")) -> 8 | K48: Not Started
A49: Sprint 5 | B49: Mandate | C49: FAS 8111 Mandate Client Information Maintenance 全委委託人資料維護 | D49: QA | E49: Mandate Client Information Maintenance QA - unit-testing | F49: New AP Lead | G49: 2 | H49: =WORKDAY(I48,1) -> 46072 | I49: =WORKDAY(H49,J49) -> 46076 | J49: =IF(F49="New AP Lead", G49/$N$5, IF(F49="Kent", G49/$N$4, "")) -> 2 | K49: Not Started
A50: Sprint 6 | B50: Mandate | C50: FAS 8112 Mandate Contract Information Maintenance 全委契約資料維護 | D50: BA | E50: Mandate Contract Information Maintenance Requirement Analysis | F50: Kent | G50: 2 | H50: =WORKDAY(I38,1) -> 46062 | I50: =WORKDAY(H50,J50) -> 46064 | J50: =IF(F50="New AP Lead", G50/$N$5, IF(F50="Kent", G50/$N$4, "")) -> 2 | K50: Not Started
A51: Sprint 6 | B51: Mandate | C51: FAS 8112 Mandate Contract Information Maintenance 全委契約資料維護 | D51: BA | E51: Mandate Contract Information Maintenance Requirement | F51: Kent | G51: 2 | H51: =WORKDAY(I50,1) -> 46065 | I51: =WORKDAY(H51,J51) -> 46069 | J51: =IF(F51="New AP Lead", G51/$N$5, IF(F51="Kent", G51/$N$4, "")) -> 2 | K51: Not Started
A52: Sprint 6 | B52: Mandate | C52: FAS 8112 Mandate Contract Information Maintenance 全委契約資料維護 | D52: Development | E52: Mandate Contract Information Maintenance - Development 1 | F52: FrontEnd | G52: 2 | H52: =WORKDAY(I51,1) -> 46070 | I52: =WORKDAY(H52,J52) -> 46072 | J52: =G52/$N$6 -> 2 | K52: Not Started
A53: Sprint 7 | B53: Mandate | C53: FAS 8112 Mandate Contract Information Maintenance 全委契約資料維護 | D53: Development | E53: Mandate Contract Information Maintenance - Development 2 | F53: Kent | G53: 8 | H53: =WORKDAY(I51,1) -> 46070 | I53: =WORKDAY(H53,J53) -> 46080 | J53: =IF(F53="New AP Lead", G53/$N$5, IF(F53="Kent", G53/$N$4, "")) -> 8 | K53: Not Started
A54: Sprint 8 | B54: Mandate | C54: FAS 8112 Mandate Contract Information Maintenance 全委契約資料維護 | D54: QA | E54: Mandate Contract Information Maintenance QA - unit-testing | F54: Kent | G54: 2 | H54: =WORKDAY(I53,1) -> 46083 | I54: =WORKDAY(H54,J54) -> 46085 | J54: =IF(F54="New AP Lead", G54/$N$5, IF(F54="Kent", G54/$N$4, "")) -> 2 | K54: Not Started
A55: Sprint 6 | B55: Mandate | C55: FAS 8121 Mandate Subscription Data Entry 全委申購資料登錄 | D55: BA | E55: Mandate Subscription Data Entry Requirement Analysis | F55: New AP Lead | G55: 2 | H55: =WORKDAY(I49,1) -> 46077 | I55: =WORKDAY(H55,J55) -> 46079 | J55: =IF(F55="New AP Lead", G55/$N$5, IF(F55="Kent", G55/$N$4, "")) -> 2 | K55: Not Started
A56: Sprint 7 | B56: Mandate | C56: FAS 8121 Mandate Subscription Data Entry 全委申購資料登錄 | D56: BA | E56: Mandate Subscription Data Entry Requirement Doc | F56: New AP Lead | G56: 2 | H56: =WORKDAY(I55,1) -> 46080 | I56: =WORKDAY(H56,J56) -> 46084 | J56: =IF(F56="New AP Lead", G56/$N$5, IF(F56="Kent", G56/$N$4, "")) -> 2 | K56: Not Started
A57: Sprint 7 | B57: Mandate | C57: FAS 8121 Mandate Subscription Data Entry 全委申購資料登錄 | D57: Development | E57: Mandate Subscription Data Entry - Development 1 | F57: FrontEnd | G57: 2 | H57: =WORKDAY(I56,1) -> 46085 | I57: =WORKDAY(H57,J57) -> 46087 | J57: =G57/$N$6 -> 2 | K57: Not Started
A58: Sprint 8 | B58: Mandate | C58: FAS 8121 Mandate Subscription Data Entry 全委申購資料登錄 | D58: Development | E58: Mandate Subscription Data Entry - Development 2 | F58: New AP Lead | G58: 8 | H58: =WORKDAY(I56,1) -> 46085 | I58: =WORKDAY(H58,J58) -> 46097 | J58: =IF(F58="New AP Lead", G58/$N$5, IF(F58="Kent", G58/$N$4, "")) -> 8 | K58: Not Started
A59: Sprint 9 | B59: Mandate | C59: FAS 8121 Mandate Subscription Data Entry 全委申購資料登錄 | D59: QA | E59: Mandate Subscription Data Entry QA - unit-testing | F59: New AP Lead | G59: 2 | H59: =WORKDAY(I58,1) -> 46098 | I59: =WORKDAY(H59,J59) -> 46100 | J59: =IF(F59="New AP Lead", G59/$N$5, IF(F59="Kent", G59/$N$4, "")) -> 2 | K59: Not Started
A60: Sprint 9 | B60: Mandate | C60: FAS 8122 Mandate Redemption Data Entry 全委買回資料登錄 | D60: BA | E60: Mandate Redemption Data Entry Requirement Analysis | F60: Kent | G60: 2 | H60: =WORKDAY(I54,1) -> 46086 | I60: =WORKDAY(H60,J60) -> 46090 | J60: =IF(F60="New AP Lead", G60/$N$5, IF(F60="Kent", G60/$N$4, "")) -> 2 | K60: Not Started
A61: Sprint 9 | B61: Mandate | C61: FAS 8122 Mandate Redemption Data Entry 全委買回資料登錄 | D61: BA | E61: Mandate Redemption Data Entry Requirement Doc | F61: Kent | G61: 2 | H61: =WORKDAY(I60,1) -> 46091 | I61: =WORKDAY(H61,J61) -> 46093 | J61: =IF(F61="New AP Lead", G61/$N$5, IF(F61="Kent", G61/$N$4, "")) -> 2 | K61: Not Started
A62: Sprint 9 | B62: Mandate | C62: FAS 8122 Mandate Redemption Data Entry 全委買回資料登錄 | D62: Development | E62: Mandate Redemption Data Entry - Development 1 | F62: FrontEnd | G62: 2 | H62: =WORKDAY(I61,1) -> 46094 | I62: =WORKDAY(H62,J62) -> 46098 | J62: =G62/$N$6 -> 2 | K62: Not Started
A63: Sprint 10 | B63: Mandate | C63: FAS 8122 Mandate Redemption Data Entry 全委買回資料登錄 | D63: Development | E63: Mandate Redemption Data Entry - Development 2 | F63: Kent | G63: 8 | H63: =WORKDAY(I61,1) -> 46094 | I63: =WORKDAY(H63,J63) -> 46106 | J63: =IF(F63="New AP Lead", G63/$N$5, IF(F63="Kent", G63/$N$4, "")) -> 8 | K63: Not Started
A64: Sprint 11 | B64: Mandate | C64: FAS 8122 Mandate Redemption Data Entry 全委買回資料登錄 | D64: QA | E64: Mandate Redemption Data Entry QA - unit-testing | F64: Kent | G64: 2 | H64: =WORKDAY(I63,1) -> 46107 | I64: =WORKDAY(H64,J64) -> 46111 | J64: =IF(F64="New AP Lead", G64/$N$5, IF(F64="Kent", G64/$N$4, "")) -> 2 | K64: Not Started
A65: Sprint 11 | B65: Mandate | C65: FAS 8151 Mandate Fund NAV Inquiry 全委基金淨值查詢 | D65: BA | E65: Mandate Fund NAV Inquiry Requirement Analysis | F65: Kent | G65: 1 | H65: =WORKDAY(I64,1) -> 46112 | I65: =WORKDAY(H65,J65) -> 46113 | J65: =IF(F65="New AP Lead", G65/$N$5, IF(F65="Kent", G65/$N$4, "")) -> 1 | K65: Not Started
A66: Sprint 11 | B66: Mandate | C66: FAS 8151 Mandate Fund NAV Inquiry 全委基金淨值查詢 | D66: BA | E66: Mandate Fund NAV Inquiry Requirement Doc | F66: Kent | G66: 2 | H66: =WORKDAY(I65,1) -> 46114 | I66: =WORKDAY(H66,J66) -> 46118 | J66: =IF(F66="New AP Lead", G66/$N$5, IF(F66="Kent", G66/$N$4, "")) -> 2 | K66: Not Started
A67: Sprint 11 | B67: Mandate | C67: FAS 8151 Mandate Fund NAV Inquiry 全委基金淨值查詢 | D67: Development | E67: Mandate Fund NAV Inquiry - Development 1 | F67: Kent | G67: 1 | H67: =WORKDAY(I66,1) -> 46119 | I67: =WORKDAY(H67,J67) -> 46120 | J67: =G67/$N$6 -> 1 | K67: Not Started
A68: Sprint 12 | B68: Mandate | C68: FAS 8151 Mandate Fund NAV Inquiry 全委基金淨值查詢 | D68: Development | E68: Mandate Fund NAV Inquiry - Development 2 | F68: Kent | G68: 3 | H68: =WORKDAY(I66,1) -> 46119 | I68: =WORKDAY(H68,J68) -> 46122 | J68: =IF(F68="New AP Lead", G68/$N$5, IF(F68="Kent", G68/$N$4, "")) -> 3 | K68: Not Started
A69: Sprint 12 | B69: Mandate | C69: FAS 8151 Mandate Fund NAV Inquiry 全委基金淨值查詢 | D69: QA | E69: Mandate Fund NAV Inquiry QA - unit-testing | F69: Kent | G69: 2 | H69: =WORKDAY(I68,1) -> 46125 | I69: =WORKDAY(H69,J69) -> 46127 | J69: =IF(F69="New AP Lead", G69/$N$5, IF(F69="Kent", G69/$N$4, "")) -> 2 | K69: Not Started
A70: Sprint 12 | B70: Mandate | C70: FAS 8152 Mandate Account Holdings Inquiry 全委帳戶庫存查詢 | D70: BA | E70: Mandate Fund NAV Inquiry Requirement Analysis | F70: New AP Lead | G70: 1 | H70: =WORKDAY(I64,1) -> 46112 | I70: =WORKDAY(H70,J70) -> 46113 | J70: =IF(F70="New AP Lead", G70/$N$5, IF(F70="Kent", G70/$N$4, "")) -> 1 | K70: Not Started
A71: Sprint 13 | B71: Mandate | C71: FAS 8152 Mandate Account Holdings Inquiry 全委帳戶庫存查詢 | D71: BA | E71: Mandate Fund NAV Inquiry Requirement Doc | F71: New AP Lead | G71: 2 | H71: =WORKDAY(I70,1) -> 46114 | I71: =WORKDAY(H71,J71) -> 46118 | J71: =IF(F71="New AP Lead", G71/$N$5, IF(F71="Kent", G71/$N$4, "")) -> 2 | K71: Not Started
A72: Sprint 13 | B72: Mandate | C72: FAS 8152 Mandate Account Holdings Inquiry 全委帳戶庫存查詢 | D72: Development | E72: Mandate Fund NAV Inquiry - Development 1 | F72: New AP Lead | G72: 2 | H72: =WORKDAY(I71,1) -> 46119 | I72: =WORKDAY(H72,J72) -> 46121 | J72: =G72/$N$6 -> 2 | K72: Not Started
A73: Sprint 13 | B73: Mandate | C73: FAS 8152 Mandate Account Holdings Inquiry 全委帳戶庫存查詢 | D73: Development | E73: Mandate Fund NAV Inquiry - Development 2 | F73: New AP Lead | G73: 2 | H73: =WORKDAY(I71,1) -> 46119 | I73: =WORKDAY(H73,J73) -> 46121 | J73: =IF(F73="New AP Lead", G73/$N$5, IF(F73="Kent", G73/$N$4, "")) -> 2 | K73: Not Started
A74: Sprint 13 | B74: Mandate | C74: FAS 8152 Mandate Account Holdings Inquiry 全委帳戶庫存查詢 | D74: QA | E74: Mandate Fund NAV Inquiry QA - unit-testing | F74: New AP Lead | G74: 2 | H74: =WORKDAY(I73,1) -> 46122 | I74: =WORKDAY(H74,J74) -> 46126 | J74: =IF(F74="New AP Lead", G74/$N$5, IF(F74="Kent", G74/$N$4, "")) -> 2 | K74: Not Started
A75: Sprint 5 | B75: Mandate | C75: FAS 81611 Subscription Details Report 申購資料明細表 | D75: BA | E75: Subscription Details Report Requirement Analysis | F75: Kent | G75: 1 | H75: =WORKDAY(I69,1) -> 46128 | I75: =WORKDAY(H75,J75) -> 46129 | J75: =IF(F75="New AP Lead", G75/$N$5, IF(F75="Kent", G75/$N$4, "")) -> 1 | K75: Not Started
A76: Sprint 6 | B76: Mandate | C76: FAS 81611 Subscription Details Report 申購資料明細表 | D76: BA | E76: Subscription Details Report Requirement | F76: Kent | G76: 1 | H76: =WORKDAY(I75,1) -> 46132 | I76: =WORKDAY(H76,J76) -> 46133 | J76: =IF(F76="New AP Lead", G76/$N$5, IF(F76="Kent", G76/$N$4, "")) -> 1 | K76: Not Started
A77: Sprint 6 | B77: Mandate | C77: FAS 81611 Subscription Details Report 申購資料明細表 | D77: Development | E77: Subscription Details Report - Development 1 | F77: FrontEnd | G77: 1 | H77: =WORKDAY(I76,1) -> 46134 | I77: =WORKDAY(H77,J77) -> 46135 | J77: =G77/$N$6 -> 1 | K77: Not Started
A78: Sprint 6 | B78: Mandate | C78: FAS 81611 Subscription Details Report 申購資料明細表 | D78: Development | E78: Subscription Details Report - Development 2 | F78: Kent | G78: 2 | H78: =WORKDAY(I76,1) -> 46134 | I78: =WORKDAY(H78,J78) -> 46136 | J78: =IF(F78="New AP Lead", G78/$N$5, IF(F78="Kent", G78/$N$4, "")) -> 2 | K78: Not Started
A79: Sprint 7 | B79: Mandate | C79: FAS 81611 Subscription Details Report 申購資料明細表 | D79: QA | E79: Subscription Details Report QA - unit-testing | F79: Kent | G79: 1 | H79: =WORKDAY(I78,1) -> 46139 | I79: =WORKDAY(H79,J79) -> 46140 | J79: =IF(F79="New AP Lead", G79/$N$5, IF(F79="Kent", G79/$N$4, "")) -> 1 | K79: Not Started
A80: Sprint 7 | B80: Mandate | C80: FAS 81621 Redemption Details Report 買回資料明細表 | D80: BA | E80: Redemption Details Report Requirement Analysis | F80: New AP Lead | G80: 1 | H80: =WORKDAY(I74,1) -> 46127 | I80: =WORKDAY(H80,J80) -> 46128 | J80: =IF(F80="New AP Lead", G80/$N$5, IF(F80="Kent", G80/$N$4, "")) -> 1 | K80: Not Started
A81: Sprint 8 | B81: Mandate | C81: FAS 81621 Redemption Details Report 買回資料明細表 | D81: BA | E81: Redemption Details Report Requirement | F81: New AP Lead | G81: 1 | H81: =WORKDAY(I80,1) -> 46129 | I81: =WORKDAY(H81,J81) -> 46132 | J81: =IF(F81="New AP Lead", G81/$N$5, IF(F81="Kent", G81/$N$4, "")) -> 1 | K81: Not Started
A82: Sprint 8 | B82: Mandate | C82: FAS 81621 Redemption Details Report 買回資料明細表 | D82: Development | E82: Redemption Details Report - Development 1 | F82: FrontEnd | G82: 1 | H82: =WORKDAY(I81,1) -> 46133 | I82: =WORKDAY(H82,J82) -> 46134 | J82: =G82/$N$6 -> 1 | K82: Not Started
A83: Sprint 8 | B83: Mandate | C83: FAS 81621 Redemption Details Report 買回資料明細表 | D83: Development | E83: Redemption Details Report - Development 2 | F83: New AP Lead | G83: 2 | H83: =WORKDAY(I81,1) -> 46133 | I83: =WORKDAY(H83,J83) -> 46135 | J83: =IF(F83="New AP Lead", G83/$N$5, IF(F83="Kent", G83/$N$4, "")) -> 2 | K83: Not Started
A84: Sprint 9 | B84: Mandate | C84: FAS 81621 Redemption Details Report 買回資料明細表 | D84: QA | E84: Redemption Details Report QA - unit-testing | F84: New AP Lead | G84: 1 | H84: =WORKDAY(I83,1) -> 46136 | I84: =WORKDAY(H84,J84) -> 46139 | J84: =IF(F84="New AP Lead", G84/$N$5, IF(F84="Kent", G84/$N$4, "")) -> 1 | K84: Not Started
A85: Sprint 9 | B85: Mandate | C85: FAS 8171 Mandate NAV Import Process (State Street) 全委淨值匯入作業(道富) | D85: BA | E85: Mandate NAV Import Process (State Street) Requirement Analysis | F85: Kent | G85: 2 | H85: =WORKDAY(I79,1) -> 46141 | I85: =WORKDAY(H85,J85) -> 46143 | J85: =IF(F85="New AP Lead", G85/$N$5, IF(F85="Kent", G85/$N$4, "")) -> 2 | K85: Not Started
A86: Sprint 10 | B86: Mandate | C86: FAS 8171 Mandate NAV Import Process (State Street) 全委淨值匯入作業(道富) | D86: BA | E86: Mandate NAV Import Process (State Street) Requirement | F86: Kent | G86: 2 | H86: =WORKDAY(I85,1) -> 46146 | I86: =WORKDAY(H86,J86) -> 46148 | J86: =IF(F86="New AP Lead", G86/$N$5, IF(F86="Kent", G86/$N$4, "")) -> 2 | K86: Not Started
A87: Sprint 10 | B87: Mandate | C87: FAS 8171 Mandate NAV Import Process (State Street) 全委淨值匯入作業(道富) | D87: Development | E87: Mandate NAV Import Process (State Street) - Development 1 | F87: FrontEnd | G87: 3 | H87: =WORKDAY(I86,1) -> 46149 | I87: =WORKDAY(H87,J87) -> 46154 | J87: =G87/$N$6 -> 3 | K87: Not Started
A88: Sprint 11 | B88: Mandate | C88: FAS 8171 Mandate NAV Import Process (State Street) 全委淨值匯入作業(道富) | D88: Development | E88: Mandate NAV Import Process (State Street) - Development 2 | F88: Kent | G88: 5 | H88: =WORKDAY(I86,1) -> 46149 | I88: =WORKDAY(H88,J88) -> 46156 | J88: =IF(F88="New AP Lead", G88/$N$5, IF(F88="Kent", G88/$N$4, "")) -> 5 | K88: Not Started
A89: Sprint 12 | B89: Mandate | C89: FAS 8171 Mandate NAV Import Process (State Street) 全委淨值匯入作業(道富) | D89: QA | E89: Mandate NAV Import Process (State Street) QA - unit-testing | F89: Kent | G89: 1 | H89: =WORKDAY(I88,1) -> 46157 | I89: =WORKDAY(H89,J89) -> 46160 | J89: =IF(F89="New AP Lead", G89/$N$5, IF(F89="Kent", G89/$N$4, "")) -> 1 | K89: Not Started
A90: Sprint 12 | B90: Mandate | C90: FAS 81811 Generate Mandate Subscription/Redemption Data 全委申贖資料產生 | D90: BA | E90: Generate Mandate Subscription/Redemption Data Requirement Analysis | F90: New AP Lead | G90: 1 | H90: =WORKDAY(I84,1) -> 46140 | I90: =WORKDAY(H90,J90) -> 46141 | J90: =IF(F90="New AP Lead", G90/$N$5, IF(F90="Kent", G90/$N$4, "")) -> 1 | K90: Not Started
A91: Sprint 12 | B91: Mandate | C91: FAS 81811 Generate Mandate Subscription/Redemption Data 全委申贖資料產生 | D91: BA | E91: Generate Mandate Subscription/Redemption Data Requirement | F91: New AP Lead | G91: 2 | H91: =WORKDAY(I90,1) -> 46142 | I91: =WORKDAY(H91,J91) -> 46146 | J91: =IF(F91="New AP Lead", G91/$N$5, IF(F91="Kent", G91/$N$4, "")) -> 2 | K91: Not Started
A92: Sprint 13 | B92: Mandate | C92: FAS 81811 Generate Mandate Subscription/Redemption Data 全委申贖資料產生 | D92: Development | E92: Generate Mandate Subscription/Redemption Data - Development 1 | F92: FrontEnd | G92: 2 | H92: =WORKDAY(I91,1) -> 46147 | I92: =WORKDAY(H92,J92) -> 46149 | J92: =G92/$N$6 -> 2 | K92: Not Started
A93: Sprint 13 | B93: Mandate | C93: FAS 81811 Generate Mandate Subscription/Redemption Data 全委申贖資料產生 | D93: Development | E93: Generate Mandate Subscription/Redemption Data - Development 2 | F93: New AP Lead | G93: 4 | H93: =WORKDAY(I92,1) -> 46150 | I93: =WORKDAY(H93,J93) -> 46156 | J93: =IF(F93="New AP Lead", G93/$N$5, IF(F93="Kent", G93/$N$4, "")) -> 4 | K93: Not Started
A94: Sprint 14 | B94: Mandate | C94: FAS 81811 Generate Mandate Subscription/Redemption Data 全委申贖資料產生 | D94: QA | E94: Generate Mandate Subscription/Redemption Data QA - unit-testing | F94: New AP Lead | G94: 2 | H94: =WORKDAY(I93,1) -> 46157 | I94: =WORKDAY(H94,J94) -> 46161 | J94: =IF(F94="New AP Lead", G94/$N$5, IF(F94="Kent", G94/$N$4, "")) -> 2 | K94: Not Started
A95: Sprint 15 | B95: Mandate | C95: FAS 81812 Export Mandate Subscription/Redemption Data 全委申贖資料匯出 | D95: BA | E95: Export Mandate Subscription/Redemption Data Requirement Analysis | F95: Kent | G95: 0.5 | H95: =WORKDAY(I89,1) -> 46161 | I95: =WORKDAY(H95,J95) -> 46161 | J95: =IF(F95="New AP Lead", G95/$N$5, IF(F95="Kent", G95/$N$4, "")) -> 0.5 | K95: Not Started
A96: Sprint 15 | B96: Mandate | C96: FAS 81812 Export Mandate Subscription/Redemption Data 全委申贖資料匯出 | D96: BA | E96: Export Mandate Subscription/Redemption Data Requirement | F96: Kent | G96: 0.5 | H96: =WORKDAY(I95,1) -> 46162 | I96: =WORKDAY(H96,J96) -> 46162 | J96: =IF(F96="New AP Lead", G96/$N$5, IF(F96="Kent", G96/$N$4, "")) -> 0.5 | K96: Not Started
A97: Sprint 15 | B97: Mandate | C97: FAS 81812 Export Mandate Subscription/Redemption Data 全委申贖資料匯出 | D97: Development | E97: Export Mandate Subscription/Redemption Data - Development 1 | F97: FrontEnd | G97: 1.5 | H97: =WORKDAY(I96,1) -> 46163 | I97: =WORKDAY(H97,J97) -> 46164 | J97: =G97/$N$6 -> 1.5 | K97: Not Started
A98: Sprint 16 | B98: Mandate | C98: FAS 81812 Export Mandate Subscription/Redemption Data 全委申贖資料匯出 | D98: Development | E98: Export Mandate Subscription/Redemption Data - Development 2 | F98: Kent | G98: 2.5 | H98: =WORKDAY(I96,1) -> 46163 | I98: =WORKDAY(H98,J98) -> 46167 | J98: =IF(F98="New AP Lead", G98/$N$5, IF(F98="Kent", G98/$N$4, "")) -> 2.5 | K98: Not Started
A99: Sprint 16 | B99: Mandate | C99: FAS 81812 Export Mandate Subscription/Redemption Data 全委申贖資料匯出 | D99: QA | E99: Export Mandate Subscription/Redemption Data QA - unit-testing | F99: Kent | G99: 1 | H99: =WORKDAY(I98,1) -> 46168 | I99: =WORKDAY(H99,J99) -> 46169 | J99: =IF(F99="New AP Lead", G99/$N$5, IF(F99="Kent", G99/$N$4, "")) -> 1 | K99: Not Started
A100: Sprint 17 | B100: Mandate | C100: FAS 81831 Generate SSB Mandate Subscription/Redemption Data 產生SSB全委申贖資料 | D100: BA | E100: Generate SSB Mandate Subscription/Redemption Data Requirement Analysis | F100: New AP Lead | G100: 2 | H100: =WORKDAY(I94,1) -> 46162 | I100: =WORKDAY(H100,J100) -> 46164 | J100: =IF(F100="New AP Lead", G100/$N$5, IF(F100="Kent", G100/$N$4, "")) -> 2 | K100: Not Started
A101: Sprint 17 | B101: Mandate | C101: FAS 81831 Generate SSB Mandate Subscription/Redemption Data 產生SSB全委申贖資料 | D101: BA | E101: Generate SSB Mandate Subscription/Redemption Data Requirement | F101: New AP Lead | G101: 2 | H101: =WORKDAY(I100,1) -> 46167 | I101: =WORKDAY(H101,J101) -> 46169 | J101: =IF(F101="New AP Lead", G101/$N$5, IF(F101="Kent", G101/$N$4, "")) -> 2 | K101: Not Started
A102: Sprint 17 | B102: Mandate | C102: FAS 81831 Generate SSB Mandate Subscription/Redemption Data 產生SSB全委申贖資料 | D102: Development | E102: Generate SSB Mandate Subscription/Redemption Data - Development 1 | F102: FrontEnd | G102: 2 | H102: =I101 -> 46169 | I102: =WORKDAY(H102,J102) -> 46171 | J102: =G102/$N$6 -> 2 | K102: Not Started
A103: Sprint 18 | B103: Mandate | C103: FAS 81831 Generate SSB Mandate Subscription/Redemption Data 產生SSB全委申贖資料 | D103: Development | E103: Generate SSB Mandate Subscription/Redemption Data - Development 2 | F103: New AP Lead | G103: 5 | H103: =I102 -> 46171 | I103: =WORKDAY(H103,J103) -> 46178 | J103: =IF(F103="New AP Lead", G103/$N$5, IF(F103="Kent", G103/$N$4, "")) -> 5 | K103: Not Started
A104: Sprint 19 | B104: Mandate | C104: FAS 81831 Generate SSB Mandate Subscription/Redemption Data 產生SSB全委申贖資料 | D104: QA | E104: Generate SSB Mandate Subscription/Redemption Data QA - unit-testing | F104: New AP Lead | G104: 2 | H104: =I103 -> 46178 | I104: =WORKDAY(H104,J104) -> 46182 | J104: =IF(F104="New AP Lead", G104/$N$5, IF(F104="Kent", G104/$N$4, "")) -> 2 | K104: Not Started
...

Sheet Shareholders' Meeting & Managem
C1: Shareholders' Meeting & Managem
B3: TOTAL TASKS | C3: =COUNTA(E17:E1048576) -> 23 | G3: DURATION | H3: =H5-H4+1 -> 61 | J3: Overall Progress
B4: Completed | C4: =COUNTIF(L17:L1048576,B4) -> 0 | G4: START | H4: =MIN(I11:I1048576) -> 46447 | L4: =SUM(H11:H16) -> 12 | N4: Team Member | O4: FTE | P4: Cost / Monthly | T4: Difficulty Level | U4: MD
B5: In progress | C5: =COUNTIF(L17:L1048576,B5) -> 0 | G5: FINISH | H5: =MAX(J11:J1048576) -> 46507 | L5: =SUM(H11:H215) -> 52 | N5: Kent | O5: 1 | Q5: 1 year | T5: Low | U5: 1-2
B6: Not Started | C6: =COUNTIF(L17:L1048576,B6) -> 24 | N6: BA/Testing | O6: 1 | P6: =145000*1.05 -> 152250 | Q6: =P6*12 -> 1827000 | T6: Mid | U6: 3-5
D7: New SA and Engineer training | H7: 1/5/2026 - 1/9/2026 | J7: =1-J5 -> 1 | N7: AP Lead | O7: 1 | Q7: Onboard after Chinese New Year | T7: High | U7: 6-8
N8: FrontEnd1 | O8: 1 | P8: =145000*1.05 -> 152250 | Q8: =P8*12 -> 1827000
A9: SPRINT | B9: EPIC | C9: FEATURE | D9: TASKS | E9: STORIES | F9: Difficulty Level | G9: RESPONSIBLE | H9: Man Day Required | I9: START | J9: FINISH | K9: DURATION | L9: STATUS
A10: Sprint 24 | B10: Shareholders' Meeting & Management | C10: Generate Shareholder Meeting Data | D10: BA | E10: Generate Shareholder Meeting Data Requirement Analysis | F10: Low | G10: BA/Testing | H10: 1 | I10: 46447 | J10: 46447 | K10: 1 | L10: Not Started
A11: Sprint 24 | B11: Shareholders' Meeting & Management | C11: Generate Shareholder Meeting Data | D11: BA | E11: Generate Shareholder Meeting Data Requirement | F11: Low | G11: BA/Testing | H11: 1 | I11: 46448 | J11: 46448 | K11: 1 | L11: Not Started
A12: Sprint 25 | B12: Shareholders' Meeting & Management | C12: Generate Shareholder Meeting Data | D12: Development | E12: Generate Shareholder Meeting Data - Development 1 | F12: Mid | G12: FrontEnd | H12: 3 | I12: 46449 | J12: 46451 | K12: 3 | L12: Not Started
A13: Sprint 25 | B13: Shareholders' Meeting & Management | C13: Generate Shareholder Meeting Data | D13: Development | E13: Generate Shareholder Meeting Data - Development 2 | F13: Mid | G13: Kent | H13: 4 | I13: 46449 | J13: 46454 | K13: 4 | L13: Not Started
A14: Sprint 25 | B14: Shareholders' Meeting & Management | C14: Generate Shareholder Meeting Data | D14: Testing | E14: Generate Shareholder Meeting Data QA - unit-testing | F14: Low | G14: BA/Testing | H14: 2 | I14: 46455 | J14: 46456 | K14: 2 | L14: Not Started
A15: Sprint 26 | B15: Shareholders' Meeting & Management | C15: Generate Memo for Assigned Personnel/Function | D15: BA | E15: Generate Memo for Assigned Personnel/Function Requirement Analysis | F15: Low | G15: BA/Testing | H15: 1 | I15: 46447 | J15: 46447 | K15: 1 | L15: Not Started
A16: Sprint 26 | B16: Shareholders' Meeting & Management | C16: Generate Memo for Assigned Personnel/Function | D16: BA | E16: Generate Memo for Assigned Personnel/Function Requirement | F16: Low | G16: BA/Testing | H16: 1 | I16: 46448 | J16: 46448 | K16: 1 | L16: Not Started
A17: Sprint 26 | B17: Shareholders' Meeting & Management | C17: Generate Memo for Assigned Personnel/Function | D17: Development | E17: Generate Memo for Assigned Personnel/Function - Development 1 | F17: Low | G17: FrontEnd | H17: 2 | I17: 46449 | J17: 46450 | K17: 2 | L17: Not Started
A18: Sprint 26 | B18: Shareholders' Meeting & Management | C18: Generate Memo for Assigned Personnel/Function | D18: Development | E18: Generate Memo for Assigned Personnel/Function - Development 2 | F18: Mid | G18: New AP Lead | H18: 5 | I18: 46449 | J18: 46455 | K18: 5 | L18: Not Started
A19: Sprint 27 | B19: Shareholders' Meeting & Management | C19: Generate Memo for Assigned Personnel/Function | D19: Testing | E19: Generate Memo for Assigned Personnel/Function QA - unit-testing | F19: Low | G19: BA/Testing | H19: 1 | I19: 46456 | J19: 46456 | K19: 1 | L19: Not Started
A20: Sprint 27 | B20: Shareholders' Meeting & Management | C20: Director/Supervisor Election Report/Function | D20: BA | E20: Director/Supervisor Election Report/Function Requirement Analysis | F20: Low | G20: BA/Testing | H20: 1 | I20: 46451 | J20: 46451 | K20: 1 | L20: Not Started
A21: Sprint 27 | B21: Shareholders' Meeting & Management | C21: Director/Supervisor Election Report/Function | D21: BA | E21: Director/Supervisor Election Report/Function Requirement | F21: Low | G21: BA/Testing | H21: 1 | I21: 46454 | J21: 46454 | K21: 1 | L21: Not Started
... A39: Sprint 30 | B39: Shareholders' Meeting & Management | C39: Stock Basic Data Maintenance | D39: Testing | E39: Stock Basic Data Maintenance QA - unit-testing | F39: Low | G39: BA/Testing | H39: 1 | I39: 46472 | J39: 46472 | K39: 1 | L39: Not Started
A40: Sprint30 | B40: Shareholders' Meeting & Management | C40: Pararell Run | D40: All | G40: New AP Lead | I40: 46475 | J40: 46507 | L40: Not Started

Sheet Project Planning - C
C1: DMS Development
B3: TOTAL TASKS | C3: =COUNTA(E16:E1048576) -> 199 | F3: DURATION | G3: =G5-G4+1 -> 479 | I3: Overall Progress | M3: Team Member | N3: FTE
B4: Completed | C4: =COUNTIF(K16:K1048576,B4) -> 0 | F4: START | G4: =MIN(H10:H1048576) -> 45915 | K4: =SUM(G10:G15) -> 24 | M4: Patrick | N4: 0.5
B5: In progress | C5: =COUNTIF(K16:K1048576,B5) -> 9 | F5: FINISH | G5: =MAX(I10:I1048576) -> 46393 | K5: =SUM(G10:G214) -> 408 | M5: Kent | N5: 1
B6: Not Started | C6: =COUNTIF(K16:K1048576,B6) -> 190 | M6: Richard | N6: 0.5
I7: =1-I5 -> 1 | K7: =K4/K5 -> 0.058823529 | M7: AP Lead | N7: 1
M8: FrontEnd1 | N8: 1
A9: SPRINT | B9: EPIC | C9: FEATURE | D9: TASKS | E9: STORIES | F9: RESPONSIBLE | G9: Man Day Required | H9: START | I9: FINISH | J9: DURATION | K9: STATUS
A10: Sprint 0 | B10: Shareholders' Meeting & Management | C10: Data Mapping, Data Migration & Create Tables in DB | D10: BA | E10: Data Mapping, Data Migration & Create Tables in DB Requirement Analysis | F10: Kent | G10: 3 | H10: 45915 | I10: =WORKDAY(H10,J10) -> 45918 | J10: =G10/$N$5 -> 3 | K10: Completed
A11: Sprint 0 | B11: Shareholders' Meeting & Management | C11: Data Mapping, Data Migration & Create Tables in DB | D11: BA | E11: Data Mapping, Data Migration & Create Tables in DB Requirement | F11: Kent | G11: 3 | H11: =WORKDAY(I10,1) -> 45919 | I11: =WORKDAY(H11,J11) -> 45924 | J11: =G11/$N$5 -> 3 | K11: Completed
A12: Sprint 0 | B12: Shareholders' Meeting & Management | C12: Data Mapping, Data Migration & Create Tables in DB | D12: Development | E12: Data Mapping - Development | F12: Kent | G12: 5 | H12: =WORKDAY(I11,1) -> 45925 | I12: =WORKDAY(H12,J12) -> 45932 | J12: =G12/$N$5 -> 5 | K12: Completed
A13: Sprint 0 | B13: Shareholders' Meeting & Management | C13: Data Mapping, Data Migration & Create Tables in DB | D13: Development | E13: Data Migration - Development | F13: Kent | G13: 5 | H13: =WORKDAY(I12,1) -> 45933 | I13: =WORKDAY(H13,J13) -> 45940 | J13: =G13/$N$5 -> 5 | K13: Completed
A14: Sprint 0 | B14: Shareholders' Meeting & Management | C14: Data Mapping, Data Migration & Create Tables in DB | D14: Development | E14: Create Tables in DB - Development | F14: Kent | G14: 5 | H14: =WORKDAY(I13,1) -> 45943 | I14: =WORKDAY(H14,J14) -> 45950 | J14: =G14/$N$5 -> 5 | K14: Completed
A15: Sprint 0 | B15: Shareholders' Meeting & Management | C15: Data Mapping, Data Migration & Create Tables in DB | D15: QA | E15: Data Related QA - unit testing | F15: Kent | G15: 3 | H15: =WORKDAY(I14,1) -> 45951 | I15: =WORKDAY(H15,J15) -> 45954 | J15: =G15/$N$5 -> 3 | K15: Completed
A16: {=INDEX('Sprint Calendar'!$A:$A, MATCH(1, ('Project Planning - C'!I16 >= 'Sprint Calendar'!$B:$B) * ('Project Planning - C'!H16 <= 'Sprint Calendar'!$C:$C), 0))} -> Sprint 1 | B16: Dividend Distribution | C16: Data Mapping, Data Migration & Create Tables in DB | D16: BA | E16: Data Related Detail Requirement Analysis | F16: Patrick | G16: 3 | H16: 45985 | I16: =WORKDAY(H16,J16) -> 45993 | J16: =G16/N4 -> 6 | K16: In progress
A17: {=INDEX('Sprint Calendar'!$A:$A, MATCH(1, ('Project Planning - C'!I17 >= 'Sprint Calendar'!$B:$B) * ('Project Planning - C'!H17 <= 'Sprint Calendar'!$C:$C), 0))} -> Sprint 1 | B17: Dividend Distribution | C17: Data Mapping, Data Migration & Create Tables in DB | D17: BA | E17: Data Related Document Detail Requirement | F17: Patrick | G17: 3 | H17: =WORKDAY(I16,1) -> 45994 | I17: =WORKDAY(H17,J17) -> 46002 | J17: =G17/N4 -> 6 | K17: In progress
A18: {=INDEX('Sprint Calendar'!$A:$A, MATCH(1, ('Project Planning - C'!I18 >= 'Sprint Calendar'!$B:$B) * ('Project Planning - C'!H18 <= 'Sprint Calendar'!$C:$C), 0))} -> Sprint 1 | B18: Dividend Distribution | C18: Data Mapping, Data Migration & Create Tables in DB | D18: Development | E18: Data Mapping - Development | F18: Kent | G18: 3 | H18: 45985 | I18: =WORKDAY(H18,J18) -> 45988 | J18: =G18/$N$5 -> 3 | K18: In progress
A19: {=INDEX('Sprint Calendar'!$A:$A, MATCH(1, ('Project Planning - C'!I19 >= 'Sprint Calendar'!$B:$B) * ('Project Planning - C'!H19 <= 'Sprint Calendar'!$C:$C), 0))} -> Sprint 1 | B19: Dividend Distribution | C19: Data Mapping, Data Migration & Create Tables in DB | D19: Development | E19: Data Migration - Development | F19: Kent | G19: 5 | H19: =WORKDAY(I18,1) -> 45989 | I19: =WORKDAY(H19,J19) -> 45996 | J19: =G19/$N$5 -> 5 | K19: Not Started
A20: {=INDEX('Sprint Calendar'!$A:$A, MATCH(1, ('Project Planning - C'!I20 >= 'Sprint Calendar'!$B:$B) * ('Project Planning - C'!H20 <= 'Sprint Calendar'!$C:$C), 0))} -> Sprint 2 | B20: Dividend Distribution | C20: Data Mapping, Data Migration & Create Tables in DB | D20: Development | E20: Create Tables in DB - Development | F20: Kent | G20: 2 | H20: =WORKDAY(I19,1) -> 45999 | I20: =WORKDAY(H20,J20) -> 46001 | J20: =G20/$N$5 -> 2 | K20: Not Started
A21: {=INDEX('Sprint Calendar'!$A:$A, MATCH(1, ('Project Planning - C'!I21 >= 'Sprint Calendar'!$B:$B) * ('Project Planning - C'!H21 <= 'Sprint Calendar'!$C:$C), 0))} -> Sprint 2 | B21: Dividend Distribution | C21: Data Mapping, Data Migration & Create Tables in DB | D21: QA | E21: Data Related QA - unit testing | F21: Kent | G21: 3 | H21: =WORKDAY(I20,1) -> 46002 | I21: =WORKDAY(H21,J21) -> 46007 | J21: =G21/N5 -> 3 | K21: Not Started
A22: {=INDEX('Sprint Calendar'!$A:$A, MATCH(1, ('Project Planning - C'!I22 >= 'Sprint Calendar'!$B:$B) * ('Project Planning - C'!H22 <= 'Sprint Calendar'!$C:$C), 0))} -> Sprint 2 | B22: Dividend Distribution | C22: Maintain Distributable Balance 可分配餘額維護作業 | D22: BA | E22: Maintain Distributable Balance Detail Requirement Analysis | F22: Patrick | G22: 1.5 | H22: =WORKDAY(I17,1) -> 46003 | I22: =WORKDAY(H22,J22) -> 46008 | J22: =G22/$N$6 -> 3 | K22: In progress
A23: {=INDEX('Sprint Calendar'!$A:$A, MATCH(1, ('Project Planning - C'!I23 >= 'Sprint Calendar'!$B:$B) * ('Project Planning - C'!H23 <= 'Sprint Calendar'!$C:$C), 0))} -> Sprint 2 | B23: Dividend Distribution | C23: Maintain Distributable Balance 可分配餘額維護作業 | D23: BA | E23: Maintain Distributable Document Detail Requirement | F23: Patrick | G23: 1.5 | H23: =WORKDAY(I22,1) -> 46009 | I23: =WORKDAY(H23,J23) -> 46014 | J23: =G23/$N$6 -> 3 | K23: In progress
A24: {=INDEX('Sprint Calendar'!$A:$A, MATCH(1, ('Project Planning - C'!I24 >= 'Sprint Calendar'!$B:$B) * ('Project Planning - C'!H24 <= 'Sprint Calendar'!$C:$C), 0))} -> Sprint 2 | B24: Dividend Distribution | C24: Maintain Distributable Balance 可分配餘額維護作業 | D24: Development | E24: Maintain Distributable Balance - Development 1 | F24: Kent | G24: 4 | H24: =WORKDAY(I21,1) -> 46008 | I24: =WORKDAY(H24,J24) -> 46014 | J24: =G24/$N$5 -> 4 | K24: Not Started
A25: {=INDEX('Sprint Calendar'!$A:$A, MATCH(1, ('Project Planning - C'!I25 >= 'Sprint Calendar'!$B:$B) * ('Project Planning - C'!H25 <= 'Sprint Calendar'!$C:$C), 0))} -> Sprint 3 | B25: Dividend Distribution | C25: Maintain Distributable Balance 可分配餘額維護作業 | D25: Development | E25: Maintain Distributable Balance - Development 2 | F25: Kent | G25: 4 | H25: =WORKDAY(I24,1) -> 46015 | I25: =WORKDAY(H25,J25) -> 46021 | J25: =G25/$N$5 -> 4 | K25: Not Started
A26: {=INDEX('Sprint Calendar'!$A:$A, MATCH(1, ('Project Planning - C'!I26 >= 'Sprint Calendar'!$B:$B) * ('Project Planning - C'!H26 <= 'Sprint Calendar'!$C:$C), 0))} -> Sprint 3 | B26: Dividend Distribution | C26: Maintain Distributable Balance 可分配餘額維護作業 | D26: QA | E26: Maintain Distributable Balance QA - unit testing | F26: Kent | G26: 3 | H26: =WORKDAY(I25,1) -> 46022 | I26: =WORKDAY(H26,J26) -> 46027 | J26: =G26/$N$5 -> 3 | K26: Not Started
A27: {=INDEX('Sprint Calendar'!$A:$A, MATCH(1, ('Project Planning - C'!I27 >= 'Sprint Calendar'!$B:$B) * ('Project Planning - C'!H27 <= 'Sprint Calendar'!$C:$C), 0))} -> Sprint 3 | B27: Dividend Distribution | C27: Domestic Dividend Information Inquiry 境內配息資訊查詢作業 | D27: BA | E27: Domestic Dividend Information Inquiry Detail Requirement Analysis | F27: Patrick | G27: 1.5 | H27: =WORKDAY(I23,1) -> 46015 | I27: =WORKDAY(H27,J27) -> 46020 | J27: =G27/$N$4 -> 3 | K27: In progress
A28: {=INDEX('Sprint Calendar'!$A:$A, MATCH(1, ('Project Planning - C'!I28 >= 'Sprint Calendar'!$B:$B) * ('Project Planning - C'!H28 <= 'Sprint Calendar'!$C:$C), 0))} -> Sprint 3 | B28: Dividend Distribution | C28: Domestic Dividend Information Inquiry 境內配息資訊查詢作業 | D28: BA | E28: Domestic Dividend Information Inquiry Document Detail Requirement | F28: Patrick | G28: 1.5 | H28: =WORKDAY(I27,1) -> 46021 | I28: =WORKDAY(H28,J28) -> 46024 | J28: =G28/$N$4 -> 3 | K28: In progress
A29: {=INDEX('Sprint Calendar'!$A:$A, MATCH(1, ('Project Planning - C'!I29 >= 'Sprint Calendar'!$B:$B) * ('Project Planning - C'!H29 <= 'Sprint Calendar'!$C:$C), 0))} -> Sprint 4 | B29: Dividend Distribution | C29: Domestic Dividend Information Inquiry 境內配息資訊查詢作業 | D29: Development | E29: Domestic Dividend Information Inquiry - Development 1 | F29: Kent | G29: 4 | H29: =WORKDAY(I26,1) -> 46028 | I29: =WORKDAY(H29,J29) -> 46034 | J29: =G29/$N$5 -> 4 | K29: Not Started
A30: {=INDEX('Sprint Calendar'!$A:$A, MATCH(1, ('Project Planning - C'!I30 >= 'Sprint Calendar'!$B:$B) * ('Project Planning - C'!H30 <= 'Sprint Calendar'!$C:$C), 0))} -> Sprint 4 | B30: Dividend Distribution | C30: Domestic Dividend Information Inquiry 境內配息資訊查詢作業 | D30: Development | E30: Domestic Dividend Information Inquiry - Development 2 | F30: Kent | G30: 4 | H30: =WORKDAY(I29,1) -> 46035 | I30: =WORKDAY(H30,J30) -> 46041 | J30: =G30/$N$5 -> 4 | K30: Not Started
A31: {=INDEX('Sprint Calendar'!$A:$A, MATCH(1, ('Project Planning - C'!I31 >= 'Sprint Calendar'!$B:$B) * ('Project Planning - C'!H31 <= 'Sprint Calendar'!$C:$C), 0))} -> Sprint 5 | B31: Dividend Distribution | C31: Domestic Dividend Information Inquiry 境內配息資訊查詢作業 | D31: QA | E31: Domestic Dividend Information Inquiry QA - unit testing | F31: Kent | G31: 2 | H31: =WORKDAY(I30,1) -> 46042 | I31: =WORKDAY(H31,J31) -> 46044 | J31: =G31/$N$5 -> 2 | K31: Not Started
A32: {=INDEX('Sprint Calendar'!$A:$A, MATCH(1, ('Project Planning - C'!I32 >= 'Sprint Calendar'!$B:$B) * ('Project Planning - C'!H32 <= 'Sprint Calendar'!$C:$C), 0))} -> Sprint 3 | B32: Dividend Distribution | C32: Upload Domestic Dividend Composition Info to EC 境內配息組成資訊上傳EC | D32: BA | E32: Upload Domestic Dividend Composition Info to EC - Detail Requirement Analysis | F32: Patrick | G32: 1.5 | H32: =WORKDAY(I23,1) -> 46015 | I32: =WORKDAY(H32,J32) -> 46020 | J32: =G32/$N$4 -> 3 | K32: In progress
A33: {=INDEX('Sprint Calendar'!$A:$A, MATCH(1, ('Project Planning - C'!I33 >= 'Sprint Calendar'!$B:$B) * ('Project Planning - C'!H33 <= 'Sprint Calendar'!$C:$C), 0))} -> Sprint 3 | B33: Dividend Distribution | C33: Upload Domestic Dividend Composition Info to EC 境內配息組成資訊上傳EC | D33: BA | E33: Upload Domestic Dividend Composition Info to EC - Document Detail Requirement | F33: Patrick | G33: 1.5 | H33: =WORKDAY(I32,1) -> 46021 | I33: =WORKDAY(H33,J33) -> 46024 | J33: =G33/$N$4 -> 3 | K33: In progress
A34: {=INDEX('Sprint Calendar'!$A:$A, MATCH(1, ('Project Planning - C'!I34 >= 'Sprint Calendar'!$B:$B) * ('Project Planning - C'!H34 <= 'Sprint Calendar'!$C:$C), 0))} -> Sprint 5 | B34: Dividend Distribution | C34: Upload Domestic Dividend Composition Info to EC 境內配息組成資訊上傳EC | D34: Development | E34: Upload Domestic Dividend Composition Info to EC - Development 1 | F34: Kent | G34: 4 | H34: =WORKDAY(I31,1) -> 46045 | I34: =WORKDAY(H34,J34) -> 46051 | J34: =G34/$N$5 -> 4 | K34: Not Started
A35: {=INDEX('Sprint Calendar'!$A:$A, MATCH(1, ('Project Planning - C'!I35 >= 'Sprint Calendar'!$B:$B) * ('Project Planning - C'!H35 <= 'Sprint Calendar'!$C:$C), 0))} -> Sprint 5 | B35: Dividend Distribution | C35: Upload Domestic Dividend Composition Info to EC 境內配息組成資訊上傳EC | D35: Development | E35: Upload Domestic Dividend Composition Info to EC - Development 2 | F35: Kent | G35: 4 | H35: =WORKDAY(I34,1) -> 46052 | I35: =WORKDAY(H35,J35) -> 46058 | J35: =G35/$N$5 -> 4 | K35: Not Started
A36: {=INDEX('Sprint Calendar'!$A:$A, MATCH(1, ('Project Planning - C'!I36 >= 'Sprint Calendar'!$B:$B) * ('Project Planning - C'!H36 <= 'Sprint Calendar'!$C:$C), 0))} -> Sprint 6 | B36: Dividend Distribution | C36: Upload Domestic Dividend Composition Info to EC 境內配息組成資訊上傳EC | D36: QA | E36: Upload Domestic Dividend Composition Info to EC QA - unit testing | F36: Kent | G36: 2 | H36: =WORKDAY(I35,1) -> 46059 | I36: =WORKDAY(H36,J36) -> 46063 | J36: =G36/$N$5 -> 2 | K36: Not Started
A37: {=INDEX('Sprint Calendar'!$A:$A, MATCH(1, ('Project Planning - C'!I37 >= 'Sprint Calendar'!$B:$B) * ('Project Planning - C'!H37 <= 'Sprint Calendar'!$C:$C), 0))} -> Sprint 1 | B37: Mandate | C37: Data Mapping, Data Migration & Create Tables in DB | D37: BA | E37: Data Mapping, Data Migration & Create Tables in DB Requirement Analysis | F37: Richard | G37: 3 | H37: 45992 | I37: =WORKDAY(H37,J37) -> 46000 | J37: =G37/$N$6 -> 6 | K37: Not Started
A38: {=INDEX('Sprint Calendar'!$A:$A, MATCH(1, ('Project Planning - C'!I38 >= 'Sprint Calendar'!$B:$B) * ('Project Planning - C'!H38 <= 'Sprint Calendar'!$C:$C), 0))} -> Sprint 2 | B38: Mandate | C38: Data Mapping, Data Migration & Create Tables in DB | D38: BA | E38: Data Mapping, Data Migration & Create Tables in DB Requirement | F38: Richard | G38: 3 | H38: =WORKDAY(I37,1) -> 46001 | I38: =WORKDAY(H38,J38) -> 46009 | J38: =G38/$N$6 -> 6 | K38: Not Started
A39: {=INDEX('Sprint Calendar'!$A:$A, MATCH(1, ('Project Planning - C'!I39 >= 'Sprint Calendar'!$B:$B) * ('Project Planning - C'!H39 <= 'Sprint Calendar'!$C:$C), 0))} -> Sprint 2 | B39: Mandate | C39: Data Mapping, Data Migration & Create Tables in DB | D39: Development | E39: Data Mapping - Development | F39: Richard | G39: 4 | H39: =WORKDAY(I38,1) -> 46010 | I39: =WORKDAY(H39,J39) -> 46022 | J39: =G39/$N$6 -> 8 | K39: Not Started
A40: {=INDEX('Sprint Calendar'!$A:$A, MATCH(1, ('Project Planning - C'!I40 >= 'Sprint Calendar'!$B:$B) * ('Project Planning - C'!H40 <= 'Sprint Calendar'!$C:$C), 0))} -> Sprint 3 | B40: Mandate | C40: Data Mapping, Data Migration & Create Tables in DB | D40: Development | E40: Data Migration - Development | F40: Richard | G40: 4 | H40: =WORKDAY(I39,1) -> 46023 | I40: =WORKDAY(H40,J40) -> 46035 | J40: =G40/$N$6 -> 8 | K40: Not Started
A41: {=INDEX('Sprint Calendar'!$A:$A, MATCH(1, ('Project Planning - C'!I41 >= 'Sprint Calendar'!$B:$B) * ('Project Planning - C'!H41 <= 'Sprint Calendar'!$C:$C), 0))} -> Sprint 4 | B41: Mandate | C41: Data Mapping, Data Migration & Create Tables in DB | D41: Development | E41: Create Tables in DB - Development | F41: Richard | G41: 2 | H41: =WORKDAY(I40,1) -> 46036 | I41: =WORKDAY(H41,J41) -> 46042 | J41: =G41/$N$6 -> 4 | K41: Not Started
A42: {=INDEX('Sprint Calendar'!$A:$A, MATCH(1, ('Project Planning - C'!I42 >= 'Sprint Calendar'!$B:$B) * ('Project Planning - C'!H42 <= 'Sprint Calendar'!$C:$C), 0))} -> Sprint 5 | B42: Mandate | C42: Data Mapping, Data Migration & Create Tables in DB | D42: QA | E42: Data Related QA - unit testing | F42: Richard | G42: 3 | H42: =WORKDAY(I41,1) -> 46043 | I42: =WORKDAY(H42,J42) -> 46051 | J42: =G42/$N$6 -> 6 | K42: Not Started
A43: {=INDEX('Sprint Calendar'!$A:$A, MATCH(1, ('Project Planning - C'!I43 >= 'Sprint Calendar'!$B:$B) * ('Project Planning - C'!H43 <= 'Sprint Calendar'!$C:$C), 0))} -> Sprint 4 | B43: Mandate | C43: FAS 8111 Mandate Client Information Maintenance 全委委託人資料維護 | D43: BA | E43: Mandate Client Information Maintenance Requirement Analysis | F43: New AP Lead | G43: 2 | H43: 46027 | I43: =WORKDAY(H43,J43) -> 46029 | J43: =G43/$N$7 -> 2 | K43: Not Started
A44: {=INDEX('Sprint Calendar'!$A:$A, MATCH(1, ('Project Planning - C'!I44 >= 'Sprint Calendar'!$B:$B) * ('Project Planning - C'!H44 <= 'Sprint Calendar'!$C:$C), 0))} -> Sprint 4 | B44: Mandate | C44: FAS 8111 Mandate Client Information Maintenance 全委委託人資料維護 | D44: BA | E44: Mandate Client Information Maintenance Requirement | F44: New AP Lead | G44: 2 | H44: =WORKDAY(I43,1) -> 46030 | I44: =WORKDAY(H44,J44) -> 46034 | J44: =G44/$N$7 -> 2 | K44: Not Started
A45: {=INDEX('Sprint Calendar'!$A:$A, MATCH(1, ('Project Planning - C'!I45 >= 'Sprint Calendar'!$B:$B) * ('Project Planning - C'!H45 <= 'Sprint Calendar'!$C:$C), 0))} -> Sprint 4 | B45: Mandate | C45: FAS 8111 Mandate Client Information Maintenance 全委委託人資料維護 | D45: Development | E45: Mandate Client Information Maintenance - Development 1 | F45: New AP Lead | G45: 5 | H45: =WORKDAY(I44,1) -> 46035 | I45: =WORKDAY(H45,J45) -> 46042 | J45: =G45/$N$7 -> 5 | K45: Not Started
A46: {=INDEX('Sprint Calendar'!$A:$A, MATCH(1, ('Project Planning - C'!I46 >= 'Sprint Calendar'!$B:$B) * ('Project Planning - C'!H46 <= 'Sprint Calendar'!$C:$C), 0))} -> Sprint 5 | B46: Mandate | C46: FAS 8111 Mandate Client Information Maintenance 全委委託人資料維護 | D46: Development | E46: Mandate Client Information Maintenance - Development 2 | F46: New AP Lead | G46: 5 | H46: =WORKDAY(I45,1) -> 46043 | I46: =WORKDAY(H46,J46) -> 46050 | J46: =G46/$N$7 -> 5 | K46: Not Started
A47: {=INDEX('Sprint Calendar'!$A:$A, MATCH(1, ('Project Planning - C'!I47 >= 'Sprint Calendar'!$B:$B) * ('Project Planning - C'!H47 <= 'Sprint Calendar'!$C:$C), 0))} -> Sprint 5 | B47: Mandate | C47: FAS 8111 Mandate Client Information Maintenance 全委委託人資料維護 | D47: QA | E47: Mandate Client Information Maintenance QA - unit-testing | F47: New AP Lead | G47: 2 | H47: =WORKDAY(I46,1) -> 46051 | I47: =WORKDAY(H47,J47) -> 46055 | J47: =G47/$N$7 -> 2 | K47: Not Started
A48: {=INDEX('Sprint Calendar'!$A:$A, MATCH(1, ('Project Planning - C'!I48 >= 'Sprint Calendar'!$B:$B) * ('Project Planning - C'!H48 <= 'Sprint Calendar'!$C:$C), 0))} -> Sprint 6 | B48: Mandate | C48: FAS 8112 Mandate Contract Information Maintenance 全委契約資料維護 | D48: BA | E48: Mandate Contract Information Maintenance Requirement Analysis | F48: New AP Lead | G48: 2 | H48: =WORKDAY(I47,1) -> 46056 | I48: =WORKDAY(H48,J48) -> 46058 | J48: =G48/$N$7 -> 2 | K48: Not Started
A49: {=INDEX('Sprint Calendar'!$A:$A, MATCH(1, ('Project Planning - C'!I49 >= 'Sprint Calendar'!$B:$B) * ('Project Planning - C'!H49 <= 'Sprint Calendar'!$C:$C), 0))} -> Sprint 6 | B49: Mandate | C49: FAS 8112 Mandate Contract Information Maintenance 全委契約資料維護 | D49: BA | E49: Mandate Contract Information Maintenance Requirement | F49: New AP Lead | G49: 2 | H49: =WORKDAY(I48,1) -> 46059 | I49: =WORKDAY(H49,J49) -> 46063 | J49: =G49/$N$7 -> 2 | K49: Not Started
A50: {=INDEX('Sprint Calendar'!$A:$A, MATCH(1, ('Project Planning - C'!I50 >= 'Sprint Calendar'!$B:$B) * ('Project Planning - C'!H50 <= 'Sprint Calendar'!$C:$C), 0))} -> Sprint 6 | B50: Mandate | C50: FAS 8112 Mandate Contract Information Maintenance 全委契約資料維護 | D50: Development | E50: Mandate Contract Information Maintenance - Development 1 | F50: New AP Lead | G50: 5 | H50: =WORKDAY(I49,1) -> 46064 | I50: =WORKDAY(H50,J50) -> 46071 | J50: =G50/$N$7 -> 5 | K50: Not Started
A51: {=INDEX('Sprint Calendar'!$A:$A, MATCH(1, ('Project Planning - C'!I51 >= 'Sprint Calendar'!$B:$B) * ('Project Planning - C'!H51 <= 'Sprint Calendar'!$C:$C), 0))} -> Sprint 7 | B51: Mandate | C51: FAS 8112 Mandate Contract Information Maintenance 全委契約資料維護 | D51: Development | E51: Mandate Contract Information Maintenance - Development 2 | F51: New AP Lead | G51: 5 | H51: 46076 | I51: =WORKDAY(H51,J51) -> 46083 | J51: =G51/$N$7 -> 5 | K51: Not Started
A52: {=INDEX('Sprint Calendar'!$A:$A, MATCH(1, ('Project Planning - C'!I52 >= 'Sprint Calendar'!$B:$B) * ('Project Planning - C'!H52 <= 'Sprint Calendar'!$C:$C), 0))} -> Sprint 8 | B52: Mandate | C52: FAS 8112 Mandate Contract Information Maintenance 全委契約資料維護 | D52: QA | E52: Mandate Contract Information Maintenance QA - unit-testing | F52: New AP Lead | G52: 2 | H52: =WORKDAY(I51,1) -> 46084 | I52: =WORKDAY(H52,J52) -> 46086 | J52: =G52/$N$7 -> 2 | K52: Not Started
A53: {=INDEX('Sprint Calendar'!$A:$A, MATCH(1, ('Project Planning - C'!I53 >= 'Sprint Calendar'!$B:$B) * ('Project Planning - C'!H53 <= 'Sprint Calendar'!$C:$C), 0))} -> Sprint 6 | B53: Mandate | C53: FAS 8121 Mandate Subscription Data Entry 全委申購資料登錄 | D53: BA | E53: Mandate Subscription Data Entry Requirement Analysis | F53: Kent | G53: 2 | H53: =WORKDAY(I36,1) -> 46064 | I53: =WORKDAY(H53,J53) -> 46066 | J53: =G53/$N$5 -> 2 | K53: Not Started
A54: {=INDEX('Sprint Calendar'!$A:$A, MATCH(1, ('Project Planning - C'!I54 >= 'Sprint Calendar'!$B:$B) * ('Project Planning - C'!H54 <= 'Sprint Calendar'!$C:$C), 0))} -> Sprint 7 | B54: Mandate | C54: FAS 8121 Mandate Subscription Data Entry 全委申購資料登錄 | D54: BA | E54: Mandate Subscription Data Entry Requirement Doc | F54: Kent | G54: 2 | H54: 46076 | I54: =WORKDAY(H54,J54) -> 46078 | J54: =G54/$N$5 -> 2 | K54: Not Started
A55: {=INDEX('Sprint Calendar'!$A:$A, MATCH(1, ('Project Planning - C'!I55 >= 'Sprint Calendar'!$B:$B) * ('Project Planning - C'!H55 <= 'Sprint Calendar'!$C:$C), 0))} -> Sprint 7 | B55: Mandate | C55: FAS 8121 Mandate Subscription Data Entry 全委申購資料登錄 | D55: Development | E55: Mandate Subscription Data Entry - Development 1 | F55: Kent | G55: 5 | H55: =WORKDAY(I54,1) -> 46079 | I55: =WORKDAY(H55,J55) -> 46086 | J55: =G55/$N$5 -> 5 | K55: Not Started
A56: {=INDEX('Sprint Calendar'!$A:$A, MATCH(1, ('Project Planning - C'!I56 >= 'Sprint Calendar'!$B:$B) * ('Project Planning - C'!H56 <= 'Sprint Calendar'!$C:$C), 0))} -> Sprint 8 | B56: Mandate | C56: FAS 8121 Mandate Subscription Data Entry 全委申購資料登錄 | D56: Development | E56: Mandate Subscription Data Entry - Development 2 | F56: Kent | G56: 5 | H56: =WORKDAY(I55,1) -> 46087 | I56: =WORKDAY(H56,J56) -> 46094 | J56: =G56/$N$5 -> 5 | K56: Not Started
A57: {=INDEX('Sprint Calendar'!$A:$A, MATCH(1, ('Project Planning - C'!I57 >= 'Sprint Calendar'!$B:$B) * ('Project Planning - C'!H57 <= 'Sprint Calendar'!$C:$C), 0))} -> Sprint 9 | B57: Mandate | C57: FAS 8121 Mandate Subscription Data Entry 全委申購資料登錄 | D57: QA | E57: Mandate Subscription Data Entry QA - unit-testing | F57: Kent | G57: 2 | H57: =WORKDAY(I56,1) -> 46097 | I57: =WORKDAY(H57,J57) -> 46099 | J57: =G57/$N$5 -> 2 | K57: Not Started
A58: {=INDEX('Sprint Calendar'!$A:$A, MATCH(1, ('Project Planning - C'!I58 >= 'Sprint Calendar'!$B:$B) * ('Project Planning - C'!H58 <= 'Sprint Calendar'!$C:$C), 0))} -> Sprint 9 | B58: Mandate | C58: FAS 8122 Mandate Redemption Data Entry 全委買回資料登錄 | D58: BA | E58: Mandate Redemption Data Entry Requirement Analysis | F58: Kent | G58: 2 | H58: =WORKDAY(I57,1) -> 46100 | I58: =WORKDAY(H58,J58) -> 46104 | J58: =G58/$N$5 -> 2 | K58: Not Started
A59: {=INDEX('Sprint Calendar'!$A:$A, MATCH(1, ('Project Planning - C'!I59 >= 'Sprint Calendar'!$B:$B) * ('Project Planning - C'!H59 <= 'Sprint Calendar'!$C:$C), 0))} -> Sprint 9 | B59: Mandate | C59: FAS 8122 Mandate Redemption Data Entry 全委買回資料登錄 | D59: BA | E59: Mandate Redemption Data Entry Requirement Doc | F59: Kent | G59: 2 | H59: =WORKDAY(I58,1) -> 46105 | I59: =WORKDAY(H59,J59) -> 46107 | J59: =G59/$N$5 -> 2 | K59: Not Started
A60: {=INDEX('Sprint Calendar'!$A:$A, MATCH(1, ('Project Planning - C'!I60 >= 'Sprint Calendar'!$B:$B) * ('Project Planning - C'!H60 <= 'Sprint Calendar'!$C:$C), 0))} -> Sprint 9 | B60: Mandate | C60: FAS 8122 Mandate Redemption Data Entry 全委買回資料登錄 | D60: Development | E60: Mandate Redemption Data Entry - Development 1 | F60: Kent | G60: 5 | H60: =WORKDAY(I59,1) -> 46108 | I60: =WORKDAY(H60,J60) -> 46115 | J60: =G60/$N$5 -> 5 | K60: Not Started
A61: {=INDEX('Sprint Calendar'!$A:$A, MATCH(1, ('Project Planning - C'!I61 >= 'Sprint Calendar'!$B:$B) * ('Project Planning - C'!H61 <= 'Sprint Calendar'!$C:$C), 0))} -> Sprint 10 | B61: Mandate | C61: FAS 8122 Mandate Redemption Data Entry 全委買回資料登錄 | D61: Development | E61: Mandate Redemption Data Entry - Development 2 | F61: Kent | G61: 5 | H61: =WORKDAY(I60,1) -> 46118 | I61: =WORKDAY(H61,J61) -> 46125 | J61: =G61/$N$5 -> 5 | K61: Not Started
A62: {=INDEX('Sprint Calendar'!$A:$A, MATCH(1, ('Project Planning - C'!I62 >= 'Sprint Calendar'!$B:$B) * ('Project Planning - C'!H62 <= 'Sprint Calendar'!$C:$C), 0))} -> Sprint 11 | B62: Mandate | C62: FAS 8122 Mandate Redemption Data Entry 全委買回資料登錄 | D62: QA | E62: Mandate Redemption Data Entry QA - unit-testing | F62: Kent | G62: 2 | H62: =WORKDAY(I61,1) -> 46126 | I62: =WORKDAY(H62,J62) -> 46128 | J62: =G62/$N$5 -> 2 | K62: Not Started
A63: {=INDEX('Sprint Calendar'!$A:$A, MATCH(1, ('Project Planning - C'!I63 >= 'Sprint Calendar'!$B:$B) * ('Project Planning - C'!H63 <= 'Sprint Calendar'!$C:$C), 0))} -> Sprint 11 | B63: Mandate | C63: FAS 8151 Mandate Fund NAV Inquiry 全委基金淨值查詢 | D63: BA | E63: Mandate Fund NAV Inquiry Requirement Analysis | F63: Kent | G63: 1 | H63: =WORKDAY(I62,1) -> 46129 | I63: =WORKDAY(H63,J63) -> 46132 | J63: =G63/$N$5 -> 1 | K63: Not Started
A64: {=INDEX('Sprint Calendar'!$A:$A, MATCH(1, ('Project Planning - C'!I64 >= 'Sprint Calendar'!$B:$B) * ('Project Planning - C'!H64 <= 'Sprint Calendar'!$C:$C), 0))} -> Sprint 11 | B64: Mandate | C64: FAS 8151 Mandate Fund NAV Inquiry 全委基金淨值查詢 | D64: BA | E64: Mandate Fund NAV Inquiry Requirement Doc | F64: Kent | G64: 2 | H64: =WORKDAY(I63,1) -> 46133 | I64: =WORKDAY(H64,J64) -> 46135 | J64: =G64/$N$5 -> 2 | K64: Not Started
A65: {=INDEX('Sprint Calendar'!$A:$A, MATCH(1, ('Project Planning - C'!I65 >= 'Sprint Calendar'!$B:$B) * ('Project Planning - C'!H65 <= 'Sprint Calendar'!$C:$C), 0))} -> Sprint 11 | B65: Mandate | C65: FAS 8151 Mandate Fund NAV Inquiry 全委基金淨值查詢 | D65: Development | E65: Mandate Fund NAV Inquiry - Development 1 | F65: Kent | G65: 2 | H65: =WORKDAY(I64,1) -> 46136 | I65: =WORKDAY(H65,J65) -> 46140 | J65: =G65/$N$5 -> 2 | K65: Not Started
A66: {=INDEX('Sprint Calendar'!$A:$A, MATCH(1, ('Project Planning - C'!I66 >= 'Sprint Calendar'!$B:$B) * ('Project Planning - C'!H66 <= 'Sprint Calendar'!$C:$C), 0))} -> Sprint 12 | B66: Mandate | C66: FAS 8151 Mandate Fund NAV Inquiry 全委基金淨值查詢 | D66: Development | E66: Mandate Fund NAV Inquiry - Development 2 | F66: Kent | G66: 2 | H66: =WORKDAY(I65,1) -> 46141 | I66: =WORKDAY(H66,J66) -> 46143 | J66: =G66/$N$5 -> 2 | K66: Not Started
... A72: {=INDEX('Sprint Calendar'!$A:$A, MATCH(1, ('Project Planning - C'!I72 >= 'Sprint Calendar'!$B:$B) * ('Project Planning - C'!H72 <= 'Sprint Calendar'!$C:$C), 0))} -> Sprint 13 | B72: Mandate | C72: FAS 8152 Mandate Account Holdings Inquiry 全委帳戶庫存查詢 | D72: QA | E72: Mandate Fund NAV Inquiry QA - unit-testing | F72: Kent | G72: 2 | H72: =WORKDAY(I71,1) -> 46164 | I72: =WORKDAY(H72,J72) -> 46168 | J72: =G72/$N$5 -> 2 | K72: Not Started
A73: {=INDEX('Sprint Calendar'!$A:$A, MATCH(1, ('Project Planning - C'!I73 >= 'Sprint Calendar'!$B:$B) * ('Project Planning - C'!H73 <= 'Sprint Calendar'!$C:$C), 0))} -> Sprint 5 | B73: Mandate | C73: FAS 81611 Subscription Details Report 申購資料明細表 | D73: BA | E73: Subscription Details Report Requirement Analysis | F73: Richard | G73: 1 | H73: =WORKDAY(I42,1) -> 46052 | I73: =WORKDAY(H73,J73) -> 46056 | J73: =G73/$N$6 -> 2 | K73: Not Started
A74: {=INDEX('Sprint Calendar'!$A:$A, MATCH(1, ('Project Planning - C'!I74 >= 'Sprint Calendar'!$B:$B) * ('Project Planning - C'!H74 <= 'Sprint Calendar'!$C:$C), 0))} -> Sprint 6 | B74: Mandate | C74: FAS 81611 Subscription Details Report 申購資料明細表 | D74: BA | E74: Subscription Details Report Requirement | F74: Richard | G74: 1 | H74: =WORKDAY(I73,1) -> 46057 | I74: =WORKDAY(H74,J74) -> 46059 | J74: =G74/$N$6 -> 2 | K74: Not Started
A75: {=INDEX('Sprint Calendar'!$A:$A, MATCH(1, ('Project Planning - C'!I75 >= 'Sprint Calendar'!$B:$B) * ('Project Planning - C'!H75 <= 'Sprint Calendar'!$C:$C), 0))} -> Sprint 6 | B75: Mandate | C75: FAS 81611 Subscription Details Report 申購資料明細表 | D75: Development | E75: Subscription Details Report - Development 1 | F75: Richard | G75: 1 | H75: =WORKDAY(I74,1) -> 46062 | I75: =WORKDAY(H75,J75) -> 46064 | J75: =G75/$N$6 -> 2 | K75: Not Started
A76: {=INDEX('Sprint Calendar'!$A:$A, MATCH(1, ('Project Planning - C'!I76 >= 'Sprint Calendar'!$B:$B) * ('Project Planning - C'!H76 <= 'Sprint Calendar'!$C:$C), 0))} -> Sprint 6 | B76: Mandate | C76: FAS 81611 Subscription Details Report 申購資料明細表 | D76: Development | E76: Subscription Details Report - Development 2 | F76: Richard | G76: 2 | H76: =WORKDAY(I75,1) -> 46065 | I76: =WORKDAY(H76,J76) -> 46071 | J76: =G76/$N$6 -> 4 | K76: Not Started
A77: {=INDEX('Sprint Calendar'!$A:$A, MATCH(1, ('Project Planning - C'!I77 >= 'Sprint Calendar'!$B:$B) * ('Project Planning - C'!H77 <= 'Sprint Calendar'!$C:$C), 0))} -> Sprint 7 | B77: Mandate | C77: FAS 81611 Subscription Details Report 申購資料明細表 | D77: QA | E77: Subscription Details Report QA - unit-testing | F77: Richard | G77: 1 | H77: 46076 | I77: =WORKDAY(H77,J77) -> 46078 | J77: =G77/$N$6 -> 2 | K77: Not Started
A78: {=INDEX('Sprint Calendar'!$A:$A, MATCH(1, ('Project Planning - C'!I78 >= 'Sprint Calendar'!$B:$B) * ('Project Planning - C'!H78 <= 'Sprint Calendar'!$C:$C), 0))} -> Sprint 7 | B78: Mandate | C78: FAS 81621 Redemption Details Report 買回資料明細表 | D78: BA | E78: Redemption Details Report Requirement Analysis | F78: Richard | G78: 1 | H78: =WORKDAY(I77,1) -> 46079 | I78: =WORKDAY(H78,J78) -> 46083 | J78: =G78/$N$6 -> 2 | K78: Not Started
A79: {=INDEX('Sprint Calendar'!$A:$A, MATCH(1, ('Project Planning - C'!I79 >= 'Sprint Calendar'!$B:$B) * ('Project Planning - C'!H79 <= 'Sprint Calendar'!$C:$C), 0))} -> Sprint 8 | B79: Mandate | C79: FAS 81621 Redemption Details Report 買回資料明細表 | D79: BA | E79: Redemption Details Report Requirement | F79: Richard | G79: 1 | H79: =WORKDAY(I78,1) -> 46084 | I79: =WORKDAY(H79,J79) -> 46086 | J79: =G79/$N$6 -> 2 | K79: Not Started
A80: {=INDEX('Sprint Calendar'!$A:$A, MATCH(1, ('Project Planning - C'!I80 >= 'Sprint Calendar'!$B:$B) * ('Project Planning - C'!H80 <= 'Sprint Calendar'!$C:$C), 0))} -> Sprint 8 | B80: Mandate | C80: FAS 81621 Redemption Details Report 買回資料明細表 | D80: Development | E80: Redemption Details Report - Development 1 | F80: Richard | G80: 1 | H80: =WORKDAY(I79,1) -> 46087 | I80: =WORKDAY(H80,J80) -> 46091 | J80: =G80/$N$6 -> 2 | K80: Not Started
A81: {=INDEX('Sprint Calendar'!$A:$A, MATCH(1, ('Project Planning - C'!I81 >= 'Sprint Calendar'!$B:$B) * ('Project Planning - C'!H81 <= 'Sprint Calendar'!$C:$C), 0))} -> Sprint 8 | B81: Mandate | C81: FAS 81621 Redemption Details Report 買回資料明細表 | D81: Development | E81: Redemption Details Report - Development 2 | F81: Richard | G81: 2 | H81: =WORKDAY(I80,1) -> 46092 | I81: =WORKDAY(H81,J81) -> 46098 | J81: =G81/$N$6 -> 4 | K81: Not Started
A82: {=INDEX('Sprint Calendar'!$A:$A, MATCH(1, ('Project Planning - C'!I82 >= 'Sprint Calendar'!$B:$B) * ('Project Planning - C'!H82 <= 'Sprint Calendar'!$C:$C), 0))} -> Sprint 9 | B82: Mandate | C82: FAS 81621 Redemption Details Report 買回資料明細表 | D82: QA | E82: Redemption Details Report QA - unit-testing | F82: Richard | G82: 1 | H82: =WORKDAY(I81,1) -> 46099 | I82: =WORKDAY(H82,J82) -> 46101 | J82: =G82/$N$6 -> 2 | K82: Not Started
A83: {=INDEX('Sprint Calendar'!$A:$A, MATCH(1, ('Project Planning - C'!I83 >= 'Sprint Calendar'!$B:$B) * ('Project Planning - C'!H83 <= 'Sprint Calendar'!$C:$C), 0))} -> Sprint 9 | B83: Mandate | C83: FAS 8171 Mandate NAV Import Process (State Street) 全委淨值匯入作業(道富) | D83: BA | E83: Mandate NAV Import Process (State Street) Requirement Analysis | F83: Richard | G83: 2 | H83: =WORKDAY(I82,1) -> 46104 | I83: =WORKDAY(H83,J83) -> 46108 | J83: =G83/$N$6 -> 4 | K83: Not Started
A84: {=INDEX('Sprint Calendar'!$A:$A, MATCH(1, ('Project Planning - C'!I84 >= 'Sprint Calendar'!$B:$B) * ('Project Planning - C'!H84 <= 'Sprint Calendar'!$C:$C), 0))} -> Sprint 10 | B84: Mandate | C84: FAS 8171 Mandate NAV Import Process (State Street) 全委淨值匯入作業(道富) | D84: BA | E84: Mandate NAV Import Process (State Street) Requirement | F84: Richard | G84: 2 | H84: =WORKDAY(I83,1) -> 46111 | I84: =WORKDAY(H84,J84) -> 46115 | J84: =G84/$N$6 -> 4 | K84: Not Started
A85: {=INDEX('Sprint Calendar'!$A:$A, MATCH(1, ('Project Planning - C'!I85 >= 'Sprint Calendar'!$B:$B) * ('Project Planning - C'!H85 <= 'Sprint Calendar'!$C:$C), 0))} -> Sprint 10 | B85: Mandate | C85: FAS 8171 Mandate NAV Import Process (State Street) 全委淨值匯入作業(道富) | D85: Development | E85: Mandate NAV Import Process (State Street) - Development 1 | F85: Richard | G85: 3 | H85: =WORKDAY(I84,1) -> 46118 | I85: =WORKDAY(H85,J85) -> 46126 | J85: =G85/$N$6 -> 6 | K85: Not Started
A86: {=INDEX('Sprint Calendar'!$A:$A, MATCH(1, ('Project Planning - C'!I86 >= 'Sprint Calendar'!$B:$B) * ('Project Planning - C'!H86 <= 'Sprint Calendar'!$C:$C), 0))} -> Sprint 11 | B86: Mandate | C86: FAS 8171 Mandate NAV Import Process (State Street) 全委淨值匯入作業(道富) | D86: Development | E86: Mandate NAV Import Process (State Street) - Development 2 | F86: Richard | G86: 5 | H86: =WORKDAY(I85,1) -> 46127 | I86: =WORKDAY(H86,J86) -> 46141 | J86: =G86/$N$6 -> 10 | K86: Not Started
A87: {=INDEX('Sprint Calendar'!$A:$A, MATCH(1, ('Project Planning - C'!I87 >= 'Sprint Calendar'!$B:$B) * ('Project Planning - C'!H87 <= 'Sprint Calendar'!$C:$C), 0))} -> Sprint 12 | B87: Mandate | C87: FAS 8171 Mandate NAV Import Process (State Street) 全委淨值匯入作業(道富) | D87: QA | E87: Mandate NAV Import Process (State Street) QA - unit-testing | F87: Richard | G87: 1 | H87: =WORKDAY(I86,1) -> 46142 | I87: =WORKDAY(H87,J87) -> 46146 | J87: =G87/$N$6 -> 2 | K87: Not Started
A88: {=INDEX('Sprint Calendar'!$A:$A, MATCH(1, ('Project Planning - C'!I88 >= 'Sprint Calendar'!$B:$B) * ('Project Planning - C'!H88 <= 'Sprint Calendar'!$C:$C), 0))} -> Sprint 12 | B88: Mandate | C88: FAS 81811 Generate Mandate Subscription/Redemption Data 全委申贖資料產生 | D88: BA | E88: Generate Mandate Subscription/Redemption Data Requirement Analysis | F88: Richard | G88: 1 | H88: =WORKDAY(I87,1) -> 46147 | I88: =WORKDAY(H88,J88) -> 46149 | J88: =G88/$N$6 -> 2 | K88: Not Started
A89: {=INDEX('Sprint Calendar'!$A:$A, MATCH(1, ('Project Planning - C'!I89 >= 'Sprint Calendar'!$B:$B) * ('Project Planning - C'!H89 <= 'Sprint Calendar'!$C:$C), 0))} -> Sprint 12 | B89: Mandate | C89: FAS 81811 Generate Mandate Subscription/Redemption Data 全委申贖資料產生 | D89: BA | E89: Generate Mandate Subscription/Redemption Data Requirement | F89: Richard | G89: 2 | H89: =WORKDAY(I88,1) -> 46150 | I89: =WORKDAY(H89,J89) -> 46156 | J89: =G89/$N$6 -> 4 | K89: Not Started
... A98: {=INDEX('Sprint Calendar'!$A:$A, MATCH(1, ('Project Planning - C'!I98 >= 'Sprint Calendar'!$B:$B) * ('Project Planning - C'!H98 <= 'Sprint Calendar'!$C:$C), 0))} -> Sprint 17 | B98: Mandate | C98: FAS 81831 Generate SSB Mandate Subscription/Redemption Data 產生SSB全委申贖資料 | D98: BA | E98: Generate SSB Mandate Subscription/Redemption Data Requirement Analysis | F98: Richard | G98: 2 | H98: =WORKDAY(I97,1) -> 46209 | I98: =WORKDAY(H98,J98) -> 46213 | J98: =G98/$N$6 -> 4 | K98: Not Started
A99: {=INDEX('Sprint Calendar'!$A:$A, MATCH(1, ('Project Planning - C'!I99 >= 'Sprint Calendar'!$B:$B) * ('Project Planning - C'!H99 <= 'Sprint Calendar'!$C:$C), 0))} -> Sprint 17 | B99: Mandate | C99: FAS 81831 Generate SSB Mandate Subscription/Redemption Data 產生SSB全委申贖資料 | D99: BA | E99: Generate SSB Mandate Subscription/Redemption Data Requirement | F99: Richard | G99: 2 | H99: =I98 -> 46213 | I99: =WORKDAY(H99,J99) -> 46219 | J99: =G99/$N$6 -> 4 | K99: Not Started
A100: {=INDEX('Sprint Calendar'!$A:$A, MATCH(1, ('Project Planning - C'!I100 >= 'Sprint Calendar'!$B:$B) * ('Project Planning - C'!H100 <= 'Sprint Calendar'!$C:$C), 0))} -> Sprint 17 | B100: Mandate | C100: FAS 81831 Generate SSB Mandate Subscription/Redemption Data 產生SSB全委申贖資料 | D100: Development | E100: Generate SSB Mandate Subscription/Redemption Data - Development 1 | F100: Richard | G100: 2 | H100: =I99 -> 46219 | I100: =WORKDAY(H100,J100) -> 46225 | J100: =G100/$N$6 -> 4 | K100: Not Started
A101: {=INDEX('Sprint Calendar'!$A:$A, MATCH(1, ('Project Planning - C'!I101 >= 'Sprint Calendar'!$B:$B) * ('Project Planning - C'!H101 <= 'Sprint Calendar'!$C:$C), 0))} -> Sprint 18 | B101: Mandate | C101: FAS 81831 Generate SSB Mandate Subscription/Redemption Data 產生SSB全委申贖資料 | D101: Development | E101: Generate SSB Mandate Subscription/Redemption Data - Development 2 | F101: Richard | G101: 5 | H101: =I100 -> 46225 | I101: =WORKDAY(H101,J101) -> 46239 | J101: =G101/$N$6 -> 10 | K101: Not Started
A102: {=INDEX('Sprint Calendar'!$A:$A, MATCH(1, ('Project Planning - C'!I102 >= 'Sprint Calendar'!$B:$B) * ('Project Planning - C'!H102 <= 'Sprint Calendar'!$C:$C), 0))} -> Sprint 19 | B102: Mandate | C102: FAS 81831 Generate SSB Mandate Subscription/Redemption Data 產生SSB全委申贖資料 | D102: QA | E102: Generate SSB Mandate Subscription/Redemption Data QA - unit-testing | F102: Richard | G102: 2 | H102: =I101 -> 46239 | I102: =WORKDAY(H102,J102) -> 46245 | J102: =G102/$N$6 -> 4 | K102: Not Started
A103: {=INDEX('Sprint Calendar'!$A:$A, MATCH(1, ('Project Planning - C'!I103 >= 'Sprint Calendar'!$B:$B) * ('Project Planning - C'!H103 <= 'Sprint Calendar'!$C:$C), 0))} -> Sprint 19 | B103: Mandate | C103: FAS 81832 Export SSB Mandate Subscription/Redemption Data 匯出SSB全委申贖資料 | D103: BA | E103: Export SSB Mandate Subscription/Redemption Data Requirement Analysis | F103: Richard | G103: 0.5 | H103: =I102 -> 46245 | I103: =WORKDAY(H103,J103) -> 46246 | J103: =G103/$N$6 -> 1 | K103: Not Started
A104: {=INDEX('Sprint Calendar'!$A:$A, MATCH(1, ('Project Planning - C'!I104 >= 'Sprint Calendar'!$B:$B) * ('Project Planning - C'!H104 <= 'Sprint Calendar'!$C:$C), 0))} -> Sprint 19 | B104: Mandate | C104: FAS 81832 Export SSB Mandate Subscription/Redemption Data 匯出SSB全委申贖資料 | D104: BA | E104: Export SSB Mandate Subscription/Redemption Data Requirement | F104: Richard | G104: 0.5 | H104: =I103 -> 46246 | I104: =WORKDAY(H104,J104) -> 46247 | J104: =G104/$N$6 -> 1 | K104: Not Started
A105: {=INDEX('Sprint Calendar'!$A:$A, MATCH(1, ('Project Planning - C'!I105 >= 'Sprint Calendar'!$B:$B) * ('Project Planning - C'!H105 <= 'Sprint Calendar'!$C:$C), 0))} -> Sprint 19 | B105: Mandate | C105: FAS 81832 Export SSB Mandate Subscription/Redemption Data 匯出SSB全委申贖資料 | D105: Development | E105: Export SSB Mandate Subscription/Redemption Data - Development 1 | F105: Richard | G105: 2 | H105: =I104 -> 46247 | I105: =WORKDAY(H105,J105) -> 46253 | J105: =G105/$N$6 -> 4 | K105: Not Started
A106: {=INDEX('Sprint Calendar'!$A:$A, MATCH(1, ('Project Planning - C'!I106 >= 'Sprint Calendar'!$B:$B) * ('Project Planning - C'!H106 <= 'Sprint Calendar'!$C:$C), 0))} -> Sprint 20 | B106: Mandate | C106: FAS 81832 Export SSB Mandate Subscription/Redemption Data 匯出SSB全委申贖資料 | D106: Development | E106: Export SSB Mandate Subscription/Redemption Data - Development 2 | F106: Richard | G106: 3 | H106: =I105 -> 46253 | I106: =WORKDAY(H106,J106) -> 46261 | J106: =G106/$N$6 -> 6 | K106: Not Started
A107: {=INDEX('Sprint Calendar'!$A:$A, MATCH(1, ('Project Planning - C'!I107 >= 'Sprint Calendar'!$B:$B) * ('Project Planning - C'!H107 <= 'Sprint Calendar'!$C:$C), 0))} -> Sprint 20 | B107: Mandate | C107: FAS 81832 Export SSB Mandate Subscription/Redemption Data 匯出SSB全委申贖資料 | D107: QA | E107: Export SSB Mandate Subscription/Redemption Data QA - unit-testing | F107: Richard | G107: 1 | H107: =I106 -> 46261 | I107: =WORKDAY(H107,J107) -> 46265 | J107: =G107/$N$6 -> 2 | K107: Not Started
A108: {=INDEX('Sprint Calendar'!$A:$A, MATCH(1, ('Project Planning - C'!I108 >= 'Sprint Calendar'!$B:$B) * ('Project Planning - C'!H108 <= 'Sprint Calendar'!$C:$C), 0))} -> Sprint 14 | B108: Mandate | C108: FAS 883 Fund NAV Auto Import Process 基金淨值自動匯入作業 | D108: BA | E108: Fund NAV Auto Import Process Requirement Analysis | F108: Kent | G108: 2 | H108: =WORKDAY(I72,1) -> 46169 | I108: =WORKDAY(H108,J108) -> 46171 | J108: =G108/$N$5 -> 2 | K108: Not Started
A109: {=INDEX('Sprint Calendar'!$A:$A, MATCH(1, ('Project Planning - C'!I109 >= 'Sprint Calendar'!$B:$B) * ('Project Planning - C'!H109 <= 'Sprint Calendar'!$C:$C), 0))} -> Sprint 14 | B109: Mandate | C109: FAS 883 Fund NAV Auto Import Process 基金淨值自動匯入作業 | D109: BA | E109: Fund NAV Auto Import Process Data Requirement | F109: Kent | G109: 2 | H109: =WORKDAY(I108,1) -> 46174 | I109: =WORKDAY(H109,J109) -> 46176 | J109: =G109/$N$5 -> 2 | K109: Not Started
A110: {=INDEX('Sprint Calendar'!$A:$A, MATCH(1, ('Project Planning - C'!I110 >= 'Sprint Calendar'!$B:$B) * ('Project Planning - C'!H110 <= 'Sprint Calendar'!$C:$C), 0))} -> Sprint 14 | B110: Mandate | C110: FAS 883 Fund NAV Auto Import Process 基金淨值自動匯入作業 | D110: Development | E110: Fund NAV Auto Import Process Data - Development 1 | F110: Kent | G110: 3 | H110: =WORKDAY(I109,1) -> 46177 | I110: =WORKDAY(H110,J110) -> 46182 | J110: =G110/$N$5 -> 3 | K110: Not Started
A111: {=INDEX('Sprint Calendar'!$A:$A, MATCH(1, ('Project Planning - C'!I111 >= 'Sprint Calendar'!$B:$B) * ('Project Planning - C'!H111 <= 'Sprint Calendar'!$C:$C), 0))} -> Sprint 15 | B111: Mandate | C111: FAS 883 Fund NAV Auto Import Process 基金淨值自動匯入作業 | D111: Development | E111: Fund NAV Auto Import Process Data - Development 2 | F111: Kent | G111: 5 | H111: =WORKDAY(I110,1) -> 46183 | I111: =WORKDAY(H111,J111) -> 46190 | J111: =G111/$N$5 -> 5 | K111: Not Started
A112: {=INDEX('Sprint Calendar'!$A:$A, MATCH(1, ('Project Planning - C'!I112 >= 'Sprint Calendar'!$B:$B) * ('Project Planning - C'!H112 <= 'Sprint Calendar'!$C:$C), 0))} -> Sprint 15 | B112: Mandate | C112: FAS 883 Fund NAV Auto Import Process 基金淨值自動匯入作業 | D112: QA | E112: Fund NAV Auto Import Process QA - unit-testing | F112: Kent | G112: 1 | H112: =WORKDAY(I111,1) -> 46191 | I112: =WORKDAY(H112,J112) -> 46192 | J112: =G112/$N$5 -> 1 | K112: Not Started
A113: {=INDEX('Sprint Calendar'!$A:$A, MATCH(1, ('Project Planning - C'!I113 >= 'Sprint Calendar'!$B:$B) * ('Project Planning - C'!H113 <= 'Sprint Calendar'!$C:$C), 0))} -> Sprint 16 | B113: Mandate | C113: FAS 884 Fund NAV Import Status Inquiry 基金淨值匯入狀況查詢 | D113: BA | E113: Fund NAV Import Status Inquiry Requirement Analysis | F113: Kent | G113: 1 | H113: =WORKDAY(I112,1) -> 46195 | I113: =WORKDAY(H113,J113) -> 46196 | J113: =G113/$N$5 -> 1 | K113: Not Started
A114: {=INDEX('Sprint Calendar'!$A:$A, MATCH(1, ('Project Planning - C'!I114 >= 'Sprint Calendar'!$B:$B) * ('Project Planning - C'!H114 <= 'Sprint Calendar'!$C:$C), 0))} -> Sprint 16 | B114: Mandate | C114: FAS 884 Fund NAV Import Status Inquiry 基金淨值匯入狀況查詢 | D114: BA | E114: Fund NAV Import Status Inquiry Data Requirement | F114: Kent | G114: 2 | H114: =WORKDAY(I113,1) -> 46197 | I114: =WORKDAY(H114,J114) -> 46199 | J114: =G114/$N$5 -> 2 | K114: Not Started
...

Sheet Project Planning (3)
C1: DMS Development
B3: TOTAL TASKS | C3: =COUNTA(E16:E1048576) -> 199 | F3: DURATION | G3: =G5-G4+1 -> 325 | I3: Overall Progress | M3: Team Member | N3: FTE
B4: Completed | C4: =COUNTIF(K16:K1048576,B4) -> 0 | F4: START | G4: =MIN(H10:H1048576) -> 45915 | K4: =SUM(G10:G15) -> 24 | M4: BA | N4: 1
B5: In progress | C5: =COUNTIF(K16:K1048576,B5) -> 9 | F5: FINISH | G5: =MAX(I10:I1048576) -> 46239 | K5: =SUM(G10:G214) -> 408 | M5: Kent | N5: 1
B6: Not Started | C6: =COUNTIF(K16:K1048576,B6) -> 190 | M6: QA | N6: 1
I7: =1-I5 -> 1 | K7: =K4/K5 -> 0.058823529 | M7: AP Lead | N7: 1
M8: FrontEnd | N8: 1
A9: SPRINT | B9: EPIC | C9: FEATURE | D9: TASKS | E9: STORIES | F9: RESPONSIBLE | G9: Man Day Required | H9: START | I9: FINISH | J9: DURATION | K9: STATUS
A10: Sprint 0 | B10: Shareholders' Meeting & Management | C10: Data Mapping, Data Migration & Create Tables in DB | D10: BA | E10: Data Mapping, Data Migration & Create Tables in DB Requirement Analysis | F10: BA | G10: 3 | H10: 45915 | I10: =WORKDAY(H10,J10) -> 45918 | J10: =G10/$N$5 -> 3 | K10: Completed
A11: Sprint 0 | B11: Shareholders' Meeting & Management | C11: Data Mapping, Data Migration & Create Tables in DB | D11: BA | E11: Data Mapping, Data Migration & Create Tables in DB Requirement | F11: BA | G11: 3 | H11: =WORKDAY(I10,1) -> 45919 | I11: =WORKDAY(H11,J11) -> 45924 | J11: =G11/$N$5 -> 3 | K11: Completed
A12: Sprint 0 | B12: Shareholders' Meeting & Management | C12: Data Mapping, Data Migration & Create Tables in DB | D12: Development | E12: Data Mapping - Development | F12: Kent | G12: 5 | H12: =WORKDAY(I11,1) -> 45925 | I12: =WORKDAY(H12,J12) -> 45932 | J12: =G12/$N$5 -> 5 | K12: Completed
A13: Sprint 0 | B13: Shareholders' Meeting & Management | C13: Data Mapping, Data Migration & Create Tables in DB | D13: Development | E13: Data Migration - Development | F13: Kent | G13: 5 | H13: =WORKDAY(I12,1) -> 45933 | I13: =WORKDAY(H13,J13) -> 45940 | J13: =G13/$N$5 -> 5 | K13: Completed
A14: Sprint 0 | B14: Shareholders' Meeting & Management | C14: Data Mapping, Data Migration & Create Tables in DB | D14: Development | E14: Create Tables in DB - Development | F14: Kent | G14: 5 | H14: =WORKDAY(I13,1) -> 45943 | I14: =WORKDAY(H14,J14) -> 45950 | J14: =G14/$N$5 -> 5 | K14: Completed
A15: Sprint 0 | B15: Shareholders' Meeting & Management | C15: Data Mapping, Data Migration & Create Tables in DB | D15: QA | E15: Data Related QA - unit testing | F15: QA | G15: 3 | H15: =WORKDAY(I14,1) -> 45951 | I15: =WORKDAY(H15,J15) -> 45954 | J15: =G15/$N$5 -> 3 | K15: Completed
A16: Sprint 1 | B16: Dividend Distribution | C16: Data Mapping, Data Migration & Create Tables in DB | D16: BA | E16: Data Related Detail Requirement Analysis | F16: BA | G16: 3 | H16: 45985 | I16: =WORKDAY(H16,J16) -> 45988 | J16: =G16/N4 -> 3 | K16: In progress
A17: Sprint 1 | B17: Dividend Distribution | C17: Data Mapping, Data Migration & Create Tables in DB | D17: BA | E17: Data Related Document Detail Requirement | F17: BA | G17: 3 | H17: =WORKDAY(I16,1) -> 45989 | I17: =WORKDAY(H17,J17) -> 45994 | J17: =G17/N4 -> 3 | K17: In progress
A18: Sprint 1 | B18: Dividend Distribution | C18: Data Mapping, Data Migration & Create Tables in DB | D18: Development | E18: Data Mapping - Development | F18: Kent | G18: 3 | H18: =WORKDAY(I17,1) -> 45995 | I18: =WORKDAY(H18,J18) -> 46000 | J18: =G18/$N$5 -> 3 | K18: In progress
A19: Sprint 1 | B19: Dividend Distribution | C19: Data Mapping, Data Migration & Create Tables in DB | D19: Development | E19: Data Migration - Development | F19: Kent | G19: 5 | H19: =WORKDAY(I18,1) -> 46001 | I19: =WORKDAY(H19,J19) -> 46008 | J19: =G19/$N$5 -> 5 | K19: Not Started
A20: Sprint 2 | B20: Dividend Distribution | C20: Data Mapping, Data Migration & Create Tables in DB | D20: Development | E20: Create Tables in DB - Development | F20: Kent | G20: 2 | H20: =WORKDAY(I19,1) -> 46009 | I20: =WORKDAY(H20,J20) -> 46013 | J20: =G20/$N$5 -> 2 | K20: Not Started
A21: Sprint 2 | B21: Dividend Distribution | C21: Data Mapping, Data Migration & Create Tables in DB | D21: QA | E21: Data Related QA - unit testing | F21: QA | G21: 3 | H21: =WORKDAY(I20,1) -> 46014 | I21: =WORKDAY(H21,J21) -> 46017 | J21: =G21/$N$5 -> 3 | K21: Not Started
A22: Sprint 2 | B22: Dividend Distribution | C22: Maintain Distributable Balance 可分配餘額維護作業 | D22: BA | E22: Maintain Distributable Balance Detail Requirement Analysis | F22: BA | G22: 1.5 | H22: =WORKDAY(I17,1) -> 45995 | I22: =WORKDAY(H22,J22) -> 45996 | J22: =G22/$N$6 -> 1.5 | K22: In progress
A23: Sprint 2 | B23: Dividend Distribution | C23: Maintain Distributable Balance 可分配餘額維護作業 | D23: BA | E23: Maintain Distributable Document Detail Requirement | F23: BA | G23: 1.5 | H23: =WORKDAY(I22,1) -> 45999 | I23: =WORKDAY(H23,J23) -> 46000 | J23: =G23/$N$6 -> 1.5 | K23: In progress
A24: Sprint 2 | B24: Dividend Distribution | C24: Maintain Distributable Balance 可分配餘額維護作業 | D24: Development | E24: Maintain Distributable Balance - Development 1 | F24: FrontEnd | G24: 4 | H24: =WORKDAY(I23,1) -> 46001 | I24: =WORKDAY(H24,J24) -> 46007 | J24: =G24/$N$5 -> 4 | K24: Not Started
A25: Sprint 3 | B25: Dividend Distribution | C25: Maintain Distributable Balance 可分配餘額維護作業 | D25: Development | E25: Maintain Distributable Balance - Development 2 | F25: Kent | G25: 4 | H25: =WORKDAY(I23,1) -> 46001 | I25: =WORKDAY(H25,J25) -> 46007 | J25: =G25/$N$5 -> 4 | K25: Not Started
A26: Sprint 3 | B26: Dividend Distribution | C26: Maintain Distributable Balance 可分配餘額維護作業 | D26: QA | E26: Maintain Distributable Balance QA - unit testing | F26: QA | G26: 3 | H26: =WORKDAY(I25,1) -> 46008 | I26: =WORKDAY(H26,J26) -> 46013 | J26: =G26/$N$5 -> 3 | K26: Not Started
A27: Sprint 3 | B27: Dividend Distribution | C27: Domestic Dividend Information Inquiry 境內配息資訊查詢作業 | D27: BA | E27: Domestic Dividend Information Inquiry Detail Requirement Analysis | F27: BA | G27: 1.5 | H27: =WORKDAY(I23,1) -> 46001 | I27: =WORKDAY(H27,J27) -> 46002 | J27: =G27/$N$4 -> 1.5 | K27: In progress
A28: Sprint 3 | B28: Dividend Distribution | C28: Domestic Dividend Information Inquiry 境內配息資訊查詢作業 | D28: BA | E28: Domestic Dividend Information Inquiry Document Detail Requirement | F28: BA | G28: 1.5 | H28: =WORKDAY(I27,1) -> 46003 | I28: =WORKDAY(H28,J28) -> 46006 | J28: =G28/$N$4 -> 1.5 | K28: In progress
A29: Sprint 4 | B29: Dividend Distribution | C29: Domestic Dividend Information Inquiry 境內配息資訊查詢作業 | D29: Development | E29: Domestic Dividend Information Inquiry - Development 1 | F29: FrontEnd | G29: 4 | H29: =WORKDAY(I28,1) -> 46007 | I29: =WORKDAY(H29,J29) -> 46013 | J29: =G29/$N$5 -> 4 | K29: Not Started
A30: Sprint 4 | B30: Dividend Distribution | C30: Domestic Dividend Information Inquiry 境內配息資訊查詢作業 | D30: Development | E30: Domestic Dividend Information Inquiry - Development 2 | F30: Kent | G30: 4 | H30: =WORKDAY(I28,1) -> 46007 | I30: =WORKDAY(H30,J30) -> 46013 | J30: =G30/$N$5 -> 4 | K30: Not Started
A31: Sprint 5 | B31: Dividend Distribution | C31: Domestic Dividend Information Inquiry 境內配息資訊查詢作業 | D31: QA | E31: Domestic Dividend Information Inquiry QA - unit testing | F31: QA | G31: 2 | H31: =WORKDAY(I30,1) -> 46014 | I31: =WORKDAY(H31,J31) -> 46016 | J31: =G31/$N$5 -> 2 | K31: Not Started
A32: Sprint 3 | B32: Dividend Distribution | C32: Upload Domestic Dividend Composition Info to EC 境內配息組成資訊上傳EC | D32: BA | E32: Upload Domestic Dividend Composition Info to EC - Detail Requirement Analysis | F32: BA | G32: 1.5 | H32: =WORKDAY(I28,1) -> 46007 | I32: =WORKDAY(H32,J32) -> 46008 | J32: =G32/$N$4 -> 1.5 | K32: In progress
A33: Sprint 3 | B33: Dividend Distribution | C33: Upload Domestic Dividend Composition Info to EC 境內配息組成資訊上傳EC | D33: BA | E33: Upload Domestic Dividend Composition Info to EC - Document Detail Requirement | F33: BA | G33: 1.5 | H33: =WORKDAY(I32,1) -> 46009 | I33: =WORKDAY(H33,J33) -> 46010 | J33: =G33/$N$4 -> 1.5 | K33: In progress
A34: Sprint 5 | B34: Dividend Distribution | C34: Upload Domestic Dividend Composition Info to EC 境內配息組成資訊上傳EC | D34: Development | E34: Upload Domestic Dividend Composition Info to EC - Development 1 | F34: FrontEnd | G34: 4 | H34: 46014 | I34: =WORKDAY(H34,J34) -> 46020 | J34: =G34/$N$5 -> 4 | K34: Not Started
A35: Sprint 5 | B35: Dividend Distribution | C35: Upload Domestic Dividend Composition Info to EC 境內配息組成資訊上傳EC | D35: Development | E35: Upload Domestic Dividend Composition Info to EC - Development 2 | F35: Kent | G35: 4 | H35: 46014 | I35: =WORKDAY(H35,J35) -> 46020 | J35: =G35/$N$5 -> 4 | K35: Not Started
A36: Sprint 6 | B36: Dividend Distribution | C36: Upload Domestic Dividend Composition Info to EC 境內配息組成資訊上傳EC | D36: QA | E36: Upload Domestic Dividend Composition Info to EC QA - unit testing | F36: QA | G36: 2 | H36: =WORKDAY(I35,1) -> 46021 | I36: =WORKDAY(H36,J36) -> 46023 | J36: =G36/$N$5 -> 2 | K36: Not Started
A37: Sprint 1 | B37: Mandate | C37: Data Mapping, Data Migration & Create Tables in DB | D37: BA | E37: Data Mapping, Data Migration & Create Tables in DB Requirement Analysis | F37: BA | G37: 3 | H37: =WORKDAY(I33,1) -> 46013 | I37: =WORKDAY(H37,J37) -> 46016 | J37: =G37/$N$6 -> 3 | K37: Not Started
A38: Sprint 2 | B38: Mandate | C38: Data Mapping, Data Migration & Create Tables in DB | D38: BA | E38: Data Mapping, Data Migration & Create Tables in DB Requirement | F38: BA | G38: 3 | H38: =WORKDAY(I37,1) -> 46017 | I38: =WORKDAY(H38,J38) -> 46022 | J38: =G38/$N$6 -> 3 | K38: Not Started
A39: Sprint 2 | B39: Mandate | C39: Data Mapping, Data Migration & Create Tables in DB | D39: Development | E39: Data Mapping - Development | F39: New AP Lead | G39: 4 | H39: 46024 | I39: =WORKDAY(H39,J39) -> 46030 | J39: =G39/$N$7 -> 4 | K39: Not Started
A40: Sprint 3 | B40: Mandate | C40: Data Mapping, Data Migration & Create Tables in DB | D40: Development | E40: Data Migration - Development | F40: New AP Lead | G40: 4 | H40: =WORKDAY(I39,1) -> 46031 | I40: =WORKDAY(H40,J40) -> 46037 | J40: =G40/$N$7 -> 4 | K40: Not Started
A41: Sprint 4 | B41: Mandate | C41: Data Mapping, Data Migration & Create Tables in DB | D41: Development | E41: Create Tables in DB - Development | F41: New AP Lead | G41: 2 | H41: =WORKDAY(I40,1) -> 46038 | I41: =WORKDAY(H41,J41) -> 46042 | J41: =G41/$N$7 -> 2 | K41: Not Started
A42: Sprint 5 | B42: Mandate | C42: Data Mapping, Data Migration & Create Tables in DB | D42: QA | E42: Data Related QA - unit testing | F42: QA | G42: 3 | H42: =WORKDAY(I41,1) -> 46043 | I42: =WORKDAY(H42,J42) -> 46048 | J42: =G42/$N$5 -> 3 | K42: Not Started
A43: Sprint 4 | B43: Mandate | C43: FAS 8111 Mandate Client Information Maintenance 全委委託人資料維護 | D43: BA | E43: Mandate Client Information Maintenance Requirement Analysis | F43: BA | G43: 2 | H43: 46024 | I43: =WORKDAY(H43,J43) -> 46028 | J43: =G43/$N$7 -> 2 | K43: Not Started
A44: Sprint 4 | B44: Mandate | C44: FAS 8111 Mandate Client Information Maintenance 全委委託人資料維護 | D44: BA | E44: Mandate Client Information Maintenance Requirement | F44: BA | G44: 2 | H44: =WORKDAY(I43,1) -> 46029 | I44: =WORKDAY(H44,J44) -> 46031 | J44: =G44/$N$7 -> 2 | K44: Not Started
A45: Sprint 4 | B45: Mandate | C45: FAS 8111 Mandate Client Information Maintenance 全委委託人資料維護 | D45: Development | E45: Mandate Client Information Maintenance - Development 1 | F45: FrontEnd | G45: 5 | H45: =WORKDAY(I44,1) -> 46034 | I45: =WORKDAY(H45,J45) -> 46041 | J45: =G45/$N$8 -> 5 | K45: Not Started
A46: Sprint 5 | B46: Mandate | C46: FAS 8111 Mandate Client Information Maintenance 全委委託人資料維護 | D46: Development | E46: Mandate Client Information Maintenance - Development 2 | F46: New AP Lead | G46: 5 | H46: =WORKDAY(I44,1) -> 46034 | I46: =WORKDAY(H46,J46) -> 46041 | J46: =G46/$N$7 -> 5 | K46: Not Started
A47: Sprint 5 | B47: Mandate | C47: FAS 8111 Mandate Client Information Maintenance 全委委託人資料維護 | D47: QA | E47: Mandate Client Information Maintenance QA - unit-testing | F47: QA | G47: 2 | H47: =WORKDAY(I46,1) -> 46042 | I47: =WORKDAY(H47,J47) -> 46044 | J47: =G47/$N$5 -> 2 | K47: Not Started
A48: Sprint 6 | B48: Mandate | C48: FAS 8112 Mandate Contract Information Maintenance 全委契約資料維護 | D48: BA | E48: Mandate Contract Information Maintenance Requirement Analysis | F48: BA | G48: 2 | H48: =WORKDAY(I44,1) -> 46034 | I48: =WORKDAY(H48,J48) -> 46036 | J48: =G48/$N$7 -> 2 | K48: Not Started
A49: Sprint 6 | B49: Mandate | C49: FAS 8112 Mandate Contract Information Maintenance 全委契約資料維護 | D49: BA | E49: Mandate Contract Information Maintenance Requirement | F49: BA | G49: 2 | H49: =WORKDAY(I48,1) -> 46037 | I49: =WORKDAY(H49,J49) -> 46041 | J49: =G49/$N$7 -> 2 | K49: Not Started
A50: Sprint 6 | B50: Mandate | C50: FAS 8112 Mandate Contract Information Maintenance 全委契約資料維護 | D50: Development | E50: Mandate Contract Information Maintenance - Development 1 | F50: FrontEnd | G50: 5 | H50: =WORKDAY(I49,1) -> 46042 | I50: =WORKDAY(H50,J50) -> 46049 | J50: =G50/$N$8 -> 5 | K50: Not Started
A51: Sprint 7 | B51: Mandate | C51: FAS 8112 Mandate Contract Information Maintenance 全委契約資料維護 | D51: Development | E51: Mandate Contract Information Maintenance - Development 2 | F51: New AP Lead | G51: 5 | H51: =WORKDAY(I49,1) -> 46042 | I51: =WORKDAY(H51,J51) -> 46049 | J51: =G51/$N$7 -> 5 | K51: Not Started
A52: Sprint 8 | B52: Mandate | C52: FAS 8112 Mandate Contract Information Maintenance 全委契約資料維護 | D52: QA | E52: Mandate Contract Information Maintenance QA - unit-testing | F52: QA | G52: 2 | H52: =WORKDAY(I51,1) -> 46050 | I52: =WORKDAY(H52,J52) -> 46052 | J52: =G52/$N$5 -> 2 | K52: Not Started
A53: Sprint 6 | B53: Mandate | C53: FAS 8121 Mandate Subscription Data Entry 全委申購資料登錄 | D53: BA | E53: Mandate Subscription Data Entry Requirement Analysis | F53: BA | G53: 2 | H53: =WORKDAY(I49,1) -> 46042 | I53: =WORKDAY(H53,J53) -> 46044 | J53: =G53/$N$5 -> 2 | K53: Not Started
A54: Sprint 7 | B54: Mandate | C54: FAS 8121 Mandate Subscription Data Entry 全委申購資料登錄 | D54: BA | E54: Mandate Subscription Data Entry Requirement Doc | F54: BA | G54: 2 | H54: =WORKDAY(I53,1) -> 46045 | I54: =WORKDAY(H54,J54) -> 46049 | J54: =G54/$N$5 -> 2 | K54: Not Started
A55: Sprint 7 | B55: Mandate | C55: FAS 8121 Mandate Subscription Data Entry 全委申購資料登錄 | D55: Development | E55: Mandate Subscription Data Entry - Development 1 | F55: FrontEnd | G55: 5 | H55: =WORKDAY(I54,1) -> 46050 | I55: =WORKDAY(H55,J55) -> 46057 | J55: =G55/$N$8 -> 5 | K55: Not Started
A56: Sprint 8 | B56: Mandate | C56: FAS 8121 Mandate Subscription Data Entry 全委申購資料登錄 | D56: Development | E56: Mandate Subscription Data Entry - Development 2 | F56: Kent | G56: 5 | H56: =WORKDAY(I54,1) -> 46050 | I56: =WORKDAY(H56,J56) -> 46057 | J56: =G56/$N$5 -> 5 | K56: Not Started
A57: Sprint 9 | B57: Mandate | C57: FAS 8121 Mandate Subscription Data Entry 全委申購資料登錄 | D57: QA | E57: Mandate Subscription Data Entry QA - unit-testing | F57: QA | G57: 2 | H57: =WORKDAY(I56,1) -> 46058 | I57: =WORKDAY(H57,J57) -> 46062 | J57: =G57/$N$5 -> 2 | K57: Not Started
A58: Sprint 9 | B58: Mandate | C58: FAS 8122 Mandate Redemption Data Entry 全委買回資料登錄 | D58: BA | E58: Mandate Redemption Data Entry Requirement Analysis | F58: BA | G58: 2 | H58: =WORKDAY(I54,1) -> 46050 | I58: =WORKDAY(H58,J58) -> 46052 | J58: =G58/$N$5 -> 2 | K58: Not Started
A59: Sprint 9 | B59: Mandate | C59: FAS 8122 Mandate Redemption Data Entry 全委買回資料登錄 | D59: BA | E59: Mandate Redemption Data Entry Requirement Doc | F59: BA | G59: 2 | H59: =WORKDAY(I58,1) -> 46055 | I59: =WORKDAY(H59,J59) -> 46057 | J59: =G59/$N$5 -> 2 | K59: Not Started
A60: Sprint 9 | B60: Mandate | C60: FAS 8122 Mandate Redemption Data Entry 全委買回資料登錄 | D60: Development | E60: Mandate Redemption Data Entry - Development 1 | F60: FrontEnd | G60: 5 | H60: =WORKDAY(I59,1) -> 46058 | I60: =WORKDAY(H60,J60) -> 46065 | J60: =G60/$N$8 -> 5 | K60: Not Started
A61: Sprint 10 | B61: Mandate | C61: FAS 8122 Mandate Redemption Data Entry 全委買回資料登錄 | D61: Development | E61: Mandate Redemption Data Entry - Development 2 | F61: Kent | G61: 5 | H61: =WORKDAY(I59,1) -> 46058 | I61: =WORKDAY(H61,J61) -> 46065 | J61: =G61/$N$5 -> 5 | K61: Not Started
A62: Sprint 11 | B62: Mandate | C62: FAS 8122 Mandate Redemption Data Entry 全委買回資料登錄 | D62: QA | E62: Mandate Redemption Data Entry QA - unit-testing | F62: QA | G62: 2 | H62: =WORKDAY(I61,1) -> 46066 | I62: =WORKDAY(H62,J62) -> 46070 | J62: =G62/$N$5 -> 2 | K62: Not Started
A63: Sprint 11 | B63: Mandate | C63: FAS 8151 Mandate Fund NAV Inquiry 全委基金淨值查詢 | D63: BA | E63: Mandate Fund NAV Inquiry Requirement Analysis | F63: BA | G63: 1 | H63: =WORKDAY(I59,1) -> 46058 | I63: =WORKDAY(H63,J63) -> 46059 | J63: =G63/$N$5 -> 1 | K63: Not Started
A64: Sprint 11 | B64: Mandate | C64: FAS 8151 Mandate Fund NAV Inquiry 全委基金淨值查詢 | D64: BA | E64: Mandate Fund NAV Inquiry Requirement Doc | F64: BA | G64: 2 | H64: =WORKDAY(I63,1) -> 46062 | I64: =WORKDAY(H64,J64) -> 46064 | J64: =G64/$N$5 -> 2 | K64: Not Started
A65: Sprint 11 | B65: Mandate | C65: FAS 8151 Mandate Fund NAV Inquiry 全委基金淨值查詢 | D65: Development | E65: Mandate Fund NAV Inquiry - Development 1 | F65: FrontEnd | G65: 2 | H65: =WORKDAY(I64,1) -> 46065 | I65: =WORKDAY(H65,J65) -> 46069 | J65: =G65/$N$8 -> 2 | K65: Not Started
A66: Sprint 12 | B66: Mandate | C66: FAS 8151 Mandate Fund NAV Inquiry 全委基金淨值查詢 | D66: Development | E66: Mandate Fund NAV Inquiry - Development 2 | F66: Kent | G66: 2 | H66: =WORKDAY(I64,1) -> 46065 | I66: =WORKDAY(H66,J66) -> 46069 | J66: =G66/$N$5 -> 2 | K66: Not Started
A67: Sprint 12 | B67: Mandate | C67: FAS 8151 Mandate Fund NAV Inquiry 全委基金淨值查詢 | D67: QA | E67: Mandate Fund NAV Inquiry QA - unit-testing | F67: QA | G67: 2 | H67: =WORKDAY(I66,1) -> 46070 | I67: =WORKDAY(H67,J67) -> 46072 | J67: =G67/$N$5 -> 2 | K67: Not Started
A68: Sprint 12 | B68: Mandate | C68: FAS 8152 Mandate Account Holdings Inquiry 全委帳戶庫存查詢 | D68: BA | E68: Mandate Fund NAV Inquiry Requirement Analysis | F68: BA | G68: 1 | H68: =WORKDAY(I64,1) -> 46065 | I68: =WORKDAY(H68,J68) -> 46066 | J68: =G68/$N$5 -> 1 | K68: Not Started
A69: Sprint 13 | B69: Mandate | C69: FAS 8152 Mandate Account Holdings Inquiry 全委帳戶庫存查詢 | D69: BA | E69: Mandate Fund NAV Inquiry Requirement Doc | F69: BA | G69: 2 | H69: =WORKDAY(I68,1) -> 46069 | I69: =WORKDAY(H69,J69) -> 46071 | J69: =G69/$N$5 -> 2 | K69: Not Started
A70: Sprint 13 | B70: Mandate | C70: FAS 8152 Mandate Account Holdings Inquiry 全委帳戶庫存查詢 | D70: Development | E70: Mandate Fund NAV Inquiry - Development 1 | F70: FrontEnd | G70: 2 | H70: =WORKDAY(I69,1) -> 46072 | I70: =WORKDAY(H70,J70) -> 46076 | J70: =G70/$N$8 -> 2 | K70: Not Started
A71: Sprint 13 | B71: Mandate | C71: FAS 8152 Mandate Account Holdings Inquiry 全委帳戶庫存查詢 | D71: Development | E71: Mandate Fund NAV Inquiry - Development 2 | F71: Kent | G71: 2 | H71: =WORKDAY(I69,1) -> 46072 | I71: =WORKDAY(H71,J71) -> 46076 | J71: =G71/$N$5 -> 2 | K71: Not Started
A72: Sprint 13 | B72: Mandate | C72: FAS 8152 Mandate Account Holdings Inquiry 全委帳戶庫存查詢 | D72: QA | E72: Mandate Fund NAV Inquiry QA - unit-testing | F72: QA | G72: 2 | H72: =WORKDAY(I71,1) -> 46077 | I72: =WORKDAY(H72,J72) -> 46079 | J72: =G72/$N$5 -> 2 | K72: Not Started
A73: Sprint 5 | B73: Mandate | C73: FAS 81611 Subscription Details Report 申購資料明細表 | D73: BA | E73: Subscription Details Report Requirement Analysis | F73: BA | G73: 1 | H73: =WORKDAY(I69,1) -> 46072 | I73: =WORKDAY(H73,J73) -> 46073 | J73: =G73/$N$6 -> 1 | K73: Not Started
A74: Sprint 6 | B74: Mandate | C74: FAS 81611 Subscription Details Report 申購資料明細表 | D74: BA | E74: Subscription Details Report Requirement | F74: BA | G74: 1 | H74: =WORKDAY(I73,1) -> 46076 | I74: =WORKDAY(H74,J74) -> 46077 | J74: =G74/$N$6 -> 1 | K74: Not Started
A75: Sprint 6 | B75: Mandate | C75: FAS 81611 Subscription Details Report 申購資料明細表 | D75: Development | E75: Subscription Details Report - Development 1 | F75: FrontEnd | G75: 1 | H75: =WORKDAY(I74,1) -> 46078 | I75: =WORKDAY(H75,J75) -> 46079 | J75: =G75/$N$8 -> 1 | K75: Not Started
A76: Sprint 6 | B76: Mandate | C76: FAS 81611 Subscription Details Report 申購資料明細表 | D76: Development | E76: Subscription Details Report - Development 2 | F76: New AP Lead | G76: 2 | H76: =WORKDAY(I74,1) -> 46078 | I76: =WORKDAY(H76,J76) -> 46080 | J76: =G76/$N$7 -> 2 | K76: Not Started
A77: Sprint 7 | B77: Mandate | C77: FAS 81611 Subscription Details Report 申購資料明細表 | D77: QA | E77: Subscription Details Report QA - unit-testing | F77: QA | G77: 1 | H77: 46076 | I77: =WORKDAY(H77,J77) -> 46077 | J77: =G77/$N$5 -> 1 | K77: Not Started
A78: Sprint 7 | B78: Mandate | C78: FAS 81621 Redemption Details Report 買回資料明細表 | D78: BA | E78: Redemption Details Report Requirement Analysis | F78: BA | G78: 1 | H78: =WORKDAY(I74,1) -> 46078 | I78: =WORKDAY(H78,J78) -> 46079 | J78: =G78/$N$6 -> 1 | K78: Not Started
A79: Sprint 8 | B79: Mandate | C79: FAS 81621 Redemption Details Report 買回資料明細表 | D79: BA | E79: Redemption Details Report Requirement | F79: BA | G79: 1 | H79: =WORKDAY(I78,1) -> 46080 | I79: =WORKDAY(H79,J79) -> 46083 | J79: =G79/$N$6 -> 1 | K79: Not Started
A80: Sprint 8 | B80: Mandate | C80: FAS 81621 Redemption Details Report 買回資料明細表 | D80: Development | E80: Redemption Details Report - Development 1 | F80: FrontEnd | G80: 1 | H80: =WORKDAY(I79,1) -> 46084 | I80: =WORKDAY(H80,J80) -> 46085 | J80: =G80/$N$8 -> 1 | K80: Not Started
A81: Sprint 8 | B81: Mandate | C81: FAS 81621 Redemption Details Report 買回資料明細表 | D81: Development | E81: Redemption Details Report - Development 2 | F81: New AP Lead | G81: 2 | H81: =WORKDAY(I79,1) -> 46084 | I81: =WORKDAY(H81,J81) -> 46086 | J81: =G81/$N$7 -> 2 | K81: Not Started
A82: Sprint 9 | B82: Mandate | C82: FAS 81621 Redemption Details Report 買回資料明細表 | D82: QA | E82: Redemption Details Report QA - unit-testing | F82: QA | G82: 1 | H82: =WORKDAY(I81,1) -> 46087 | I82: =WORKDAY(H82,J82) -> 46090 | J82: =G82/$N$5 -> 1 | K82: Not Started
A83: Sprint 9 | B83: Mandate | C83: FAS 8171 Mandate NAV Import Process (State Street) 全委淨值匯入作業(道富) | D83: BA | E83: Mandate NAV Import Process (State Street) Requirement Analysis | F83: BA | G83: 2 | H83: =WORKDAY(I79,1) -> 46084 | I83: =WORKDAY(H83,J83) -> 46086 | J83: =G83/$N$6 -> 2 | K83: Not Started
A84: Sprint 10 | B84: Mandate | C84: FAS 8171 Mandate NAV Import Process (State Street) 全委淨值匯入作業(道富) | D84: BA | E84: Mandate NAV Import Process (State Street) Requirement | F84: BA | G84: 2 | H84: =WORKDAY(I83,1) -> 46087 | I84: =WORKDAY(H84,J84) -> 46091 | J84: =G84/$N$6 -> 2 | K84: Not Started
A85: Sprint 10 | B85: Mandate | C85: FAS 8171 Mandate NAV Import Process (State Street) 全委淨值匯入作業(道富) | D85: Development | E85: Mandate NAV Import Process (State Street) - Development 1 | F85: FrontEnd | G85: 3 | H85: =WORKDAY(I84,1) -> 46092 | I85: =WORKDAY(H85,J85) -> 46097 | J85: =G85/$N$8 -> 3 | K85: Not Started
A86: Sprint 11 | B86: Mandate | C86: FAS 8171 Mandate NAV Import Process (State Street) 全委淨值匯入作業(道富) | D86: Development | E86: Mandate NAV Import Process (State Street) - Development 2 | F86: New AP Lead | G86: 5 | H86: =WORKDAY(I84,1) -> 46092 | I86: =WORKDAY(H86,J86) -> 46099 | J86: =G86/$N$7 -> 5 | K86: Not Started
A87: Sprint 12 | B87: Mandate | C87: FAS 8171 Mandate NAV Import Process (State Street) 全委淨值匯入作業(道富) | D87: QA | E87: Mandate NAV Import Process (State Street) QA - unit-testing | F87: QA | G87: 1 | H87: =WORKDAY(I86,1) -> 46100 | I87: =WORKDAY(H87,J87) -> 46101 | J87: =G87/$N$5 -> 1 | K87: Not Started
A88: Sprint 12 | B88: Mandate | C88: FAS 81811 Generate Mandate Subscription/Redemption Data 全委申贖資料產生 | D88: BA | E88: Generate Mandate Subscription/Redemption Data Requirement Analysis | F88: BA | G88: 1 | H88: =WORKDAY(I84,1) -> 46092 | I88: =WORKDAY(H88,J88) -> 46093 | J88: =G88/$N$6 -> 1 | K88: Not Started
A89: Sprint 12 | B89: Mandate | C89: FAS 81811 Generate Mandate Subscription/Redemption Data 全委申贖資料產生 | D89: BA | E89: Generate Mandate Subscription/Redemption Data Requirement | F89: BA | G89: 2 | H89: =WORKDAY(I88,1) -> 46094 | I89: =WORKDAY(H89,J89) -> 46098 | J89: =G89/$N$6 -> 2 | K89: Not Started
A90: Sprint 13 | B90: Mandate | C90: FAS 81811 Generate Mandate Subscription/Redemption Data 全委申贖資料產生 | D90: Development | E90: Generate Mandate Subscription/Redemption Data - Development 1 | F90: FrontEnd | G90: 2 | H90: =WORKDAY(I89,1) -> 46099 | I90: =WORKDAY(H90,J90) -> 46101 | J90: =G90/$N$8 -> 2 | K90: Not Started
A91: Sprint 13 | B91: Mandate | C91: FAS 81811 Generate Mandate Subscription/Redemption Data 全委申贖資料產生 | D91: Development | E91: Generate Mandate Subscription/Redemption Data - Development 2 | F91: New AP Lead | G91: 4 | H91: 46100 | I91: =WORKDAY(H91,J91) -> 46106 | J91: =G91/$N$7 -> 4 | K91: Not Started
A92: Sprint 14 | B92: Mandate | C92: FAS 81811 Generate Mandate Subscription/Redemption Data 全委申贖資料產生 | D92: QA | E92: Generate Mandate Subscription/Redemption Data QA - unit-testing | F92: QA | G92: 2 | H92: =WORKDAY(I91,1) -> 46107 | I92: =WORKDAY(H92,J92) -> 46111 | J92: =G92/$N$5 -> 2 | K92: Not Started
A93: Sprint 15 | B93: Mandate | C93: FAS 81812 Export Mandate Subscription/Redemption Data 全委申贖資料匯出 | D93: BA | E93: Export Mandate Subscription/Redemption Data Requirement Analysis | F93: BA | G93: 0.5 | H93: =WORKDAY(I89,1) -> 46099 | I93: =WORKDAY(H93,J93) -> 46099 | J93: =G93/$N$6 -> 0.5 | K93: Not Started
A94: Sprint 15 | B94: Mandate | C94: FAS 81812 Export Mandate Subscription/Redemption Data 全委申贖資料匯出 | D94: BA | E94: Export Mandate Subscription/Redemption Data Requirement | F94: BA | G94: 0.5 | H94: =WORKDAY(I93,1) -> 46100 | I94: =WORKDAY(H94,J94) -> 46100 | J94: =G94/$N$6 -> 0.5 | K94: Not Started
A95: Sprint 15 | B95: Mandate | C95: FAS 81812 Export Mandate Subscription/Redemption Data 全委申贖資料匯出 | D95: Development | E95: Export Mandate Subscription/Redemption Data - Development 1 | F95: FrontEnd | G95: 1.5 | H95: 46102 | I95: =WORKDAY(H95,J95) -> 46104 | J95: =G95/$N$8 -> 1.5 | K95: Not Started
A96: Sprint 16 | B96: Mandate | C96: FAS 81812 Export Mandate Subscription/Redemption Data 全委申贖資料匯出 | D96: Development | E96: Export Mandate Subscription/Redemption Data - Development 2 | F96: New AP Lead | G96: 2.5 | H96: 46107 | I96: =WORKDAY(H96,J96) -> 46111 | J96: =G96/$N$7 -> 2.5 | K96: Not Started
A97: Sprint 16 | B97: Mandate | C97: FAS 81812 Export Mandate Subscription/Redemption Data 全委申贖資料匯出 | D97: QA | E97: Export Mandate Subscription/Redemption Data QA - unit-testing | F97: QA | G97: 1 | H97: =WORKDAY(I96,1) -> 46112 | I97: =WORKDAY(H97,J97) -> 46113 | J97: =G97/$N$5 -> 1 | K97: Not Started
A98: Sprint 17 | B98: Mandate | C98: FAS 81831 Generate SSB Mandate Subscription/Redemption Data 產生SSB全委申贖資料 | D98: BA | E98: Generate SSB Mandate Subscription/Redemption Data Requirement Analysis | F98: BA | G98: 2 | H98: =WORKDAY(I94,1) -> 46101 | I98: =WORKDAY(H98,J98) -> 46105 | J98: =G98/$N$6 -> 2 | K98: Not Started
A99: Sprint 17 | B99: Mandate | C99: FAS 81831 Generate SSB Mandate Subscription/Redemption Data 產生SSB全委申贖資料 | D99: BA | E99: Generate SSB Mandate Subscription/Redemption Data Requirement | F99: BA | G99: 2 | H99: =WORKDAY(I98,1) -> 46106 | I99: =WORKDAY(H99,J99) -> 46108 | J99: =G99/$N$6 -> 2 | K99: Not Started
A100: Sprint 17 | B100: Mandate | C100: FAS 81831 Generate SSB Mandate Subscription/Redemption Data 產生SSB全委申贖資料 | D100: Development | E100: Generate SSB Mandate Subscription/Redemption Data - Development 1 | F100: FrontEnd | G100: 2 | H100: =I99 -> 46108 | I100: =WORKDAY(H100,J100) -> 46112 | J100: =G100/$N$8 -> 2 | K100: Not Started
A101: Sprint 18 | B101: Mandate | C101: FAS 81831 Generate SSB Mandate Subscription/Redemption Data 產生SSB全委申贖資料 | D101: Development | E101: Generate SSB Mandate Subscription/Redemption Data - Development 2 | F101: New AP Lead | G101: 5 | H101: =I100 -> 46112 | I101: =WORKDAY(H101,J101) -> 46119 | J101: =G101/$N$7 -> 5 | K101: Not Started
...

Sheet Sprint Calendar
A1: Sprint | B1: Start Date | C1: End Date
A2: Sprint 1 | B2: 45985 | C2: 45998
A3: Sprint 2 | B3: 45999 | C3: 46012
A4: Sprint 3 | B4: 46013 | C4: 46026
A5: Sprint 4 | B5: 46027 | C5: 46040
A6: Sprint 5 | B6: 46041 | C6: 46054
A7: Sprint 6 | B7: 46055 | C7: 46068
A8: Sprint 7 | B8: 46069 | C8: 46082
A9: Sprint 8 | B9: 46083 | C9: 46096
A10: Sprint 9 | B10: 46097 | C10: 46110
A11: Sprint 10 | B11: 46111 | C11: 46124
A12: Sprint 11 | B12: 46125 | C12: 46138
A13: Sprint 12 | B13: 46139 | C13: 46152
... A34: Sprint 33 | B34: 46440 | C34: 46451

Sheet Project Planning (2)
C1: DMS Development
B3: TOTAL TASKS | C3: =COUNTA(E15:E1048576) -> 199 | F3: DURATION | G3: =G5-G4+1 -> #DIV/0! | I3: Overall Progress | M3: Team Member | N3: FTE
B4: Completed | C4: =COUNTIF(K15:K1048576,B4) -> 4 | F4: START | G4: =MIN(H9:H1048576) -> #DIV/0! | K4: =SUM(G9:G14) -> 15 | M4: BA | N4: 1
B5: In progress | C5: =COUNTIF(K15:K1048576,B5) -> 5 | F5: FINISH | G5: =MAX(I9:I1048576) -> #DIV/0! | K5: =SUM(G9:G213) -> 408 | M5: Kent | N5: 1
B6: Not Started | C6: =COUNTIF(K15:K1048576,B6) -> 190 | M6: QA | N6: 1
I7: =1-I5 -> 1 | K7: =K4/K5 -> 0.036764706 | M7: AP Lead | N7: 1
A8: SPRINT | B8: EPIC | C8: FEATURE | D8: TASKS | E8: STORIES | F8: RESPONSIBLE | G8: Man Day Required | H8: START | I8: FINISH | J8: DURATION | K8: STATUS
A9: Sprint 0 | B9: Shareholders' Meeting & Management | C9: Data Mapping, Data Migration & Create Tables in DB | D9: BA | E9: Data Mapping, Data Migration & Create Tables in DB Requirement Analysis | F9: Kent | G9: 3 | H9: 45915 | I9: =WORKDAY(H9,J9) -> 45918 | J9: =G9/$N$4 -> 3 | K9: Completed
A10: Sprint 0 | B10: Shareholders' Meeting & Management | C10: Data Mapping, Data Migration & Create Tables in DB | D10: BA | E10: Data Mapping, Data Migration & Create Tables in DB Requirement | F10: Kent | G10: 3 | H10: =WORKDAY(I9,1) -> 45919 | I10: =WORKDAY(H10,J10) -> 45924 | J10: =G10/$N$4 -> 3 | K10: Completed
A11: {=INDEX('Sprint Calendar'!$A:$A, MATCH(1, ('Project Planning (2)'!I15 >= 'Sprint Calendar'!$B:$B) * ('Project Planning (2)'!H15 <= 'Sprint Calendar'!$C:$C), 0))} -> Sprint 5 | B11: Dividend Distribution | C11: Data Mapping, Data Migration & Create Tables in DB | D11: BA | E11: Data Related Detail Requirement Analysis | F11: BA | G11: 3 | H11: 46023 | I11: =WORKDAY(H11,J11) -> 46028 | J11: =G11/$N$4 -> 3 | K11: In progress
A12: {=INDEX('Sprint Calendar'!$A:$A, MATCH(1, ('Project Planning (2)'!I16 >= 'Sprint Calendar'!$B:$B) * ('Project Planning (2)'!H16 <= 'Sprint Calendar'!$C:$C), 0))} -> Sprint 5 | B12: Dividend Distribution | C12: Data Mapping, Data Migration & Create Tables in DB | D12: BA | E12: Data Related Document Detail Requirement | F12: BA | G12: 3 | H12: =WORKDAY(I11,1) -> 46029 | I12: =WORKDAY(H12,J12) -> 46034 | J12: =G12/$N$4 -> 3 | K12: In progress
A13: {=INDEX('Sprint Calendar'!$A:$A, MATCH(1, ('Project Planning (2)'!I21 >= 'Sprint Calendar'!$B:$B) * ('Project Planning (2)'!H21 <= 'Sprint Calendar'!$C:$C), 0))} -> Sprint 6 | B13: Dividend Distribution | C13: Maintain Distributable Balance 可分配餘額維護作業 | D13: BA | E13: Maintain Distributable Balance Detail Requirement Analysis | F13: BA | G13: 1.5 | H13: =WORKDAY(I12,1) -> 46035 | I13: =WORKDAY(H13,J13) -> 46036 | J13: =G13/$N$4 -> 1.5 | K13: In progress
A14: {=INDEX('Sprint Calendar'!$A:$A, MATCH(1, ('Project Planning (2)'!I22 >= 'Sprint Calendar'!$B:$B) * ('Project Planning (2)'!H22 <= 'Sprint Calendar'!$C:$C), 0))} -> Sprint 6 | B14: Dividend Distribution | C14: Maintain Distributable Balance 可分配餘額維護作業 | D14: BA | E14: Maintain Distributable Document Detail Requirement | F14: BA | G14: 1.5 | H14: =WORKDAY(I13,1) -> 46037 | I14: =WORKDAY(H14,J14) -> 46038 | J14: =G14/$N$4 -> 1.5 | K14: In progress
A15: {=INDEX('Sprint Calendar'!$A:$A, MATCH(1, ('Project Planning (2)'!I26 >= 'Sprint Calendar'!$B:$B) * ('Project Planning (2)'!H26 <= 'Sprint Calendar'!$C:$C), 0))} -> Sprint 8 | B15: Dividend Distribution | C15: Domestic Dividend Information Inquiry 境內配息資訊查詢作業 | D15: BA | E15: Domestic Dividend Information Inquiry Detail Requirement Analysis | F15: BA | G15: 1.5 | H15: =WORKDAY(I14,1) -> 46041 | I15: =WORKDAY(H15,J15) -> 46042 | J15: =G15/$N$4 -> 1.5 | K15: In progress
A16: {=INDEX('Sprint Calendar'!$A:$A, MATCH(1, ('Project Planning (2)'!I27 >= 'Sprint Calendar'!$B:$B) * ('Project Planning (2)'!H27 <= 'Sprint Calendar'!$C:$C), 0))} -> Sprint 8 | B16: Dividend Distribution | C16: Domestic Dividend Information Inquiry 境內配息資訊查詢作業 | D16: BA | E16: Domestic Dividend Information Inquiry Document Detail Requirement | F16: BA | G16: 1.5 | H16: =WORKDAY(I15,1) -> 46043 | I16: =WORKDAY(H16,J16) -> 46044 | J16: =G16/$N$4 -> 1.5 | K16: In progress
A17: {=INDEX('Sprint Calendar'!$A:$A, MATCH(1, ('Project Planning (2)'!I31 >= 'Sprint Calendar'!$B:$B) * ('Project Planning (2)'!H31 <= 'Sprint Calendar'!$C:$C), 0))} -> Sprint 9 | B17: Dividend Distribution | C17: Upload Domestic Dividend Composition Info to EC 境內配息組成資訊上傳EC | D17: BA | E17: Upload Domestic Dividend Composition Info to EC - Detail Requirement Analysis | F17: BA | G17: 1.5 | H17: =WORKDAY(I16,1) -> 46045 | I17: =WORKDAY(H17,J17) -> 46048 | J17: =G17/$N$4 -> 1.5 | K17: In progress
A18: {=INDEX('Sprint Calendar'!$A:$A, MATCH(1, ('Project Planning (2)'!I32 >= 'Sprint Calendar'!$B:$B) * ('Project Planning (2)'!H32 <= 'Sprint Calendar'!$C:$C), 0))} -> Sprint 9 | B18: Dividend Distribution | C18: Upload Domestic Dividend Composition Info to EC 境內配息組成資訊上傳EC | D18: BA | E18: Upload Domestic Dividend Composition Info to EC - Document Detail Requirement | F18: BA | G18: 1.5 | H18: =WORKDAY(I17,1) -> 46049 | I18: =WORKDAY(H18,J18) -> 46050 | J18: =G18/$N$4 -> 1.5 | K18: In progress
A19: {=INDEX('Sprint Calendar'!$A:$A, MATCH(1, ('Project Planning (2)'!I36 >= 'Sprint Calendar'!$B:$B) * ('Project Planning (2)'!H36 <= 'Sprint Calendar'!$C:$C), 0))} -> Sprint 10 | B19: Mandate | C19: Data Mapping, Data Migration & Create Tables in DB | D19: BA | E19: Data Mapping, Data Migration & Create Tables in DB Requirement Analysis | F19: BA | G19: 3 | H19: =WORKDAY(I18,1) -> 46051 | I19: =WORKDAY(H19,J19) -> 46056 | J19: =G19/$N$4 -> 3 | K19: Not Started
A20: {=INDEX('Sprint Calendar'!$A:$A, MATCH(1, ('Project Planning (2)'!I37 >= 'Sprint Calendar'!$B:$B) * ('Project Planning (2)'!H37 <= 'Sprint Calendar'!$C:$C), 0))} -> Sprint 10 | B20: Mandate | C20: Data Mapping, Data Migration & Create Tables in DB | D20: BA | E20: Data Mapping, Data Migration & Create Tables in DB Requirement | F20: BA | G20: 3 | H20: =WORKDAY(I19,1) -> 46057 | I20: =WORKDAY(H20,J20) -> 46062 | J20: =G20/$N$4 -> 3 | K20: Not Started
A21: {=INDEX('Sprint Calendar'!$A:$A, MATCH(1, ('Project Planning (2)'!I42 >= 'Sprint Calendar'!$B:$B) * ('Project Planning (2)'!H42 <= 'Sprint Calendar'!$C:$C), 0))} -> Sprint 12 | B21: Mandate | C21: FAS 8111 Mandate Client Information Maintenance 全委委託人資料維護 | D21: BA | E21: Mandate Client Information Maintenance Requirement Analysis | F21: BA | G21: 2 | H21: =WORKDAY(I20,1) -> 46063 | I21: =WORKDAY(H21,J21) -> 46065 | J21: =G21/$N$4 -> 2 | K21: Not Started
A22: {=INDEX('Sprint Calendar'!$A:$A, MATCH(1, ('Project Planning (2)'!I43 >= 'Sprint Calendar'!$B:$B) * ('Project Planning (2)'!H43 <= 'Sprint Calendar'!$C:$C), 0))} -> Sprint 12 | B22: Mandate | C22: FAS 8111 Mandate Client Information Maintenance 全委委託人資料維護 | D22: BA | E22: Mandate Client Information Maintenance Requirement | F22: BA | G22: 2 | H22: =WORKDAY(I21,1) -> 46066 | I22: =WORKDAY(H22,J22) -> 46070 | J22: =G22/$N$4 -> 2 | K22: Not Started
A23: {=INDEX('Sprint Calendar'!$A:$A, MATCH(1, ('Project Planning (2)'!I47 >= 'Sprint Calendar'!$B:$B) * ('Project Planning (2)'!H47 <= 'Sprint Calendar'!$C:$C), 0))} -> Sprint 12 | B23: Mandate | C23: FAS 8112 Mandate Contract Information Maintenance 全委契約資料維護 | D23: BA | E23: Mandate Contract Information Maintenance Requirement Analysis | F23: BA | G23: 2 | H23: =WORKDAY(I22,1) -> 46071 | I23: =WORKDAY(H23,J23) -> 46073 | J23: =G23/$N$4 -> 2 | K23: Not Started
A24: {=INDEX('Sprint Calendar'!$A:$A, MATCH(1, ('Project Planning (2)'!I48 >= 'Sprint Calendar'!$B:$B) * ('Project Planning (2)'!H48 <= 'Sprint Calendar'!$C:$C), 0))} -> Sprint 13 | B24: Mandate | C24: FAS 8112 Mandate Contract Information Maintenance 全委契約資料維護 | D24: BA | E24: Mandate Contract Information Maintenance Requirement | F24: BA | G24: 2 | H24: =WORKDAY(I23,1) -> 46076 | I24: =WORKDAY(H24,J24) -> 46078 | J24: =G24/$N$4 -> 2 | K24: Not Started
A25: {=INDEX('Sprint Calendar'!$A:$A, MATCH(1, ('Project Planning (2)'!I52 >= 'Sprint Calendar'!$B:$B) * ('Project Planning (2)'!H52 <= 'Sprint Calendar'!$C:$C), 0))} -> Sprint 14 | B25: Mandate | C25: FAS 8121 Mandate Subscription Data Entry 全委申購資料登錄 | D25: BA | E25: Mandate Subscription Data Entry Requirement Analysis | F25: BA | G25: 2 | H25: =WORKDAY(I24,1) -> 46079 | I25: =WORKDAY(H25,J25) -> 46083 | J25: =G25/$N$4 -> 2 | K25: Not Started
A26: {=INDEX('Sprint Calendar'!$A:$A, MATCH(1, ('Project Planning (2)'!I53 >= 'Sprint Calendar'!$B:$B) * ('Project Planning (2)'!H53 <= 'Sprint Calendar'!$C:$C), 0))} -> Sprint 14 | B26: Mandate | C26: FAS 8121 Mandate Subscription Data Entry 全委申購資料登錄 | D26: BA | E26: Mandate Subscription Data Entry Requirement Doc | F26: BA | G26: 2 | H26: =WORKDAY(I25,1) -> 46084 | I26: =WORKDAY(H26,J26) -> 46086 | J26: =G26/$N$4 -> 2 | K26: Not Started
A27: {=INDEX('Sprint Calendar'!$A:$A, MATCH(1, ('Project Planning (2)'!I57 >= 'Sprint Calendar'!$B:$B) * ('Project Planning (2)'!H57 <= 'Sprint Calendar'!$C:$C), 0))} -> Sprint 15 | B27: Mandate | C27: FAS 8122 Mandate Redemption Data Entry 全委買回資料登錄 | D27: BA | E27: Mandate Redemption Data Entry Requirement Analysis | F27: BA | G27: 2 | H27: =WORKDAY(I26,1) -> 46087 | I27: =WORKDAY(H27,J27) -> 46091 | J27: =G27/$N$4 -> 2 | K27: Not Started
A28: {=INDEX('Sprint Calendar'!$A:$A, MATCH(1, ('Project Planning (2)'!I58 >= 'Sprint Calendar'!$B:$B) * ('Project Planning (2)'!H58 <= 'Sprint Calendar'!$C:$C), 0))} -> Sprint 15 | B28: Mandate | C28: FAS 8122 Mandate Redemption Data Entry 全委買回資料登錄 | D28: BA | E28: Mandate Redemption Data Entry Requirement Doc | F28: BA | G28: 2 | H28: =WORKDAY(I27,1) -> 46092 | I28: =WORKDAY(H28,J28) -> 46094 | J28: =G28/$N$4 -> 2 | K28: Not Started
A29: {=INDEX('Sprint Calendar'!$A:$A, MATCH(1, ('Project Planning (2)'!I62 >= 'Sprint Calendar'!$B:$B) * ('Project Planning (2)'!H62 <= 'Sprint Calendar'!$C:$C), 0))} -> Sprint 16 | B29: Mandate | C29: FAS 8151 Mandate Fund NAV Inquiry 全委基金淨值查詢 | D29: BA | E29: Mandate Fund NAV Inquiry Requirement Analysis | F29: BA | G29: 1 | H29: =WORKDAY(I28,1) -> 46097 | I29: =WORKDAY(H29,J29) -> 46098 | J29: =G29/$N$4 -> 1 | K29: Not Started
A30: {=INDEX('Sprint Calendar'!$A:$A, MATCH(1, ('Project Planning (2)'!I63 >= 'Sprint Calendar'!$B:$B) * ('Project Planning (2)'!H63 <= 'Sprint Calendar'!$C:$C), 0))} -> Sprint 16 | B30: Mandate | C30: FAS 8151 Mandate Fund NAV Inquiry 全委基金淨值查詢 | D30: BA | E30: Mandate Fund NAV Inquiry Requirement Doc | F30: BA | G30: 2 | H30: =WORKDAY(I29,1) -> 46099 | I30: =WORKDAY(H30,J30) -> 46101 | J30: =G30/$N$4 -> 2 | K30: Not Started
A31: {=INDEX('Sprint Calendar'!$A:$A, MATCH(1, ('Project Planning (2)'!I67 >= 'Sprint Calendar'!$B:$B) * ('Project Planning (2)'!H67 <= 'Sprint Calendar'!$C:$C), 0))} -> Sprint 17 | B31: Mandate | C31: FAS 8152 Mandate Account Holdings Inquiry 全委帳戶庫存查詢 | D31: BA | E31: Mandate Fund NAV Inquiry Requirement Analysis | F31: BA | G31: 1 | H31: =WORKDAY(I30,1) -> 46104 | I31: =WORKDAY(H31,J31) -> 46105 | J31: =G31/$N$4 -> 1 | K31: Not Started
A32: {=INDEX('Sprint Calendar'!$A:$A, MATCH(1, ('Project Planning (2)'!I68 >= 'Sprint Calendar'!$B:$B) * ('Project Planning (2)'!H68 <= 'Sprint Calendar'!$C:$C), 0))} -> Sprint 17 | B32: Mandate | C32: FAS 8152 Mandate Account Holdings Inquiry 全委帳戶庫存查詢 | D32: BA | E32: Mandate Fund NAV Inquiry Requirement Doc | F32: BA | G32: 2 | H32: =WORKDAY(I31,1) -> 46106 | I32: =WORKDAY(H32,J32) -> 46108 | J32: =G32/$N$4 -> 2 | K32: Not Started
A33: {=INDEX('Sprint Calendar'!$A:$A, MATCH(1, ('Project Planning (2)'!I72 >= 'Sprint Calendar'!$B:$B) * ('Project Planning (2)'!H72 <= 'Sprint Calendar'!$C:$C), 0))} -> Sprint 18 | B33: Mandate | C33: FAS 81611 Subscription Details Report 申購資料明細表 | D33: BA | E33: Subscription Details Report Requirement Analysis | F33: BA | G33: 1 | H33: =WORKDAY(I32,1) -> 46111 | I33: =WORKDAY(H33,J33) -> 46112 | J33: =G33/$N$4 -> 1 | K33: Not Started
A34: {=INDEX('Sprint Calendar'!$A:$A, MATCH(1, ('Project Planning (2)'!I73 >= 'Sprint Calendar'!$B:$B) * ('Project Planning (2)'!H73 <= 'Sprint Calendar'!$C:$C), 0))} -> Sprint 18 | B34: Mandate | C34: FAS 81611 Subscription Details Report 申購資料明細表 | D34: BA | E34: Subscription Details Report Requirement | F34: BA | G34: 1 | H34: =WORKDAY(I33,1) -> 46113 | I34: =WORKDAY(H34,J34) -> 46114 | J34: =G34/$N$4 -> 1 | K34: Not Started
A35: {=INDEX('Sprint Calendar'!$A:$A, MATCH(1, ('Project Planning (2)'!I77 >= 'Sprint Calendar'!$B:$B) * ('Project Planning (2)'!H77 <= 'Sprint Calendar'!$C:$C), 0))} -> Sprint 19 | B35: Mandate | C35: FAS 81621 Redemption Details Report 買回資料明細表 | D35: BA | E35: Redemption Details Report Requirement Analysis | F35: BA | G35: 1 | H35: =WORKDAY(I34,1) -> 46115 | I35: =WORKDAY(H35,J35) -> 46118 | J35: =G35/$N$4 -> 1 | K35: Not Started
A36: {=INDEX('Sprint Calendar'!$A:$A, MATCH(1, ('Project Planning (2)'!I78 >= 'Sprint Calendar'!$B:$B) * ('Project Planning (2)'!H78 <= 'Sprint Calendar'!$C:$C), 0))} -> Sprint 19 | B36: Mandate | C36: FAS 81621 Redemption Details Report 買回資料明細表 | D36: BA | E36: Redemption Details Report Requirement | F36: BA | G36: 1 | H36: =WORKDAY(I35,1) -> 46119 | I36: =WORKDAY(H36,J36) -> 46120 | J36: =G36/$N$4 -> 1 | K36: Not Started
A37: {=INDEX('Sprint Calendar'!$A:$A, MATCH(1, ('Project Planning (2)'!I82 >= 'Sprint Calendar'!$B:$B) * ('Project Planning (2)'!H82 <= 'Sprint Calendar'!$C:$C), 0))} -> Sprint 20 | B37: Mandate | C37: FAS 8171 Mandate NAV Import Process (State Street) 全委淨值匯入作業(道富) | D37: BA | E37: Mandate NAV Import Process (State Street) Requirement Analysis | F37: BA | G37: 2 | H37: =WORKDAY(I36,1) -> 46121 | I37: =WORKDAY(H37,J37) -> 46125 | J37: =G37/$N$4 -> 2 | K37: Not Started
A38: {=INDEX('Sprint Calendar'!$A:$A, MATCH(1, ('Project Planning (2)'!I83 >= 'Sprint Calendar'!$B:$B) * ('Project Planning (2)'!H83 <= 'Sprint Calendar'!$C:$C), 0))} -> Sprint 20 | B38: Mandate | C38: FAS 8171 Mandate NAV Import Process (State Street) 全委淨值匯入作業(道富) | D38: BA | E38: Mandate NAV Import Process (State Street) Requirement | F38: BA | G38: 2 | H38: =WORKDAY(I37,1) -> 46126 | I38: =WORKDAY(H38,J38) -> 46128 | J38: =G38/$N$4 -> 2 | K38: Not Started
A39: {=INDEX('Sprint Calendar'!$A:$A, MATCH(1, ('Project Planning (2)'!I87 >= 'Sprint Calendar'!$B:$B) * ('Project Planning (2)'!H87 <= 'Sprint Calendar'!$C:$C), 0))} -> Sprint 20 | B39: Mandate | C39: FAS 81811 Generate Mandate Subscription/Redemption Data 全委申贖資料產生 | D39: BA | E39: Generate Mandate Subscription/Redemption Data Requirement Analysis | F39: BA | G39: 1 | H39: =WORKDAY(I38,1) -> 46129 | I39: =WORKDAY(H39,J39) -> 46132 | J39: =G39/$N$4 -> 1 | K39: Not Started
A40: {=INDEX('Sprint Calendar'!$A:$A, MATCH(1, ('Project Planning (2)'!I88 >= 'Sprint Calendar'!$B:$B) * ('Project Planning (2)'!H88 <= 'Sprint Calendar'!$C:$C), 0))} -> Sprint 21 | B40: Mandate | C40: FAS 81811 Generate Mandate Subscription/Redemption Data 全委申贖資料產生 | D40: BA | E40: Generate Mandate Subscription/Redemption Data Requirement | F40: BA | G40: 2 | H40: =WORKDAY(I39,1) -> 46133 | I40: =WORKDAY(H40,J40) -> 46135 | J40: =G40/$N$4 -> 2 | K40: Not Started
A41: {=INDEX('Sprint Calendar'!$A:$A, MATCH(1, ('Project Planning (2)'!I92 >= 'Sprint Calendar'!$B:$B) * ('Project Planning (2)'!H92 <= 'Sprint Calendar'!$C:$C), 0))} -> Sprint 22 | B41: Mandate | C41: FAS 81812 Export Mandate Subscription/Redemption Data 全委申贖資料匯出 | D41: BA | E41: Export Mandate Subscription/Redemption Data Requirement Analysis | F41: BA | G41: 0.5 | H41: =WORKDAY(I40,1) -> 46136 | I41: =WORKDAY(H41,J41) -> 46136 | J41: =G41/$N$4 -> 0.5 | K41: Not Started
A42: {=INDEX('Sprint Calendar'!$A:$A, MATCH(1, ('Project Planning (2)'!I93 >= 'Sprint Calendar'!$B:$B) * ('Project Planning (2)'!H93 <= 'Sprint Calendar'!$C:$C), 0))} -> Sprint 22 | B42: Mandate | C42: FAS 81812 Export Mandate Subscription/Redemption Data 全委申贖資料匯出 | D42: BA | E42: Export Mandate Subscription/Redemption Data Requirement | F42: BA | G42: 0.5 | H42: =WORKDAY(I41,1) -> 46139 | I42: =WORKDAY(H42,J42) -> 46139 | J42: =G42/$N$4 -> 0.5 | K42: Not Started
A43: {=INDEX('Sprint Calendar'!$A:$A, MATCH(1, ('Project Planning (2)'!I97 >= 'Sprint Calendar'!$B:$B) * ('Project Planning (2)'!H97 <= 'Sprint Calendar'!$C:$C), 0))} -> Sprint 1 | B43: Mandate | C43: FAS 81831 Generate SSB Mandate Subscription/Redemption Data 產生SSB全委申贖資料 | D43: BA | E43: Generate SSB Mandate Subscription/Redemption Data Requirement Analysis | F43: BA | G43: 2 | H43: =WORKDAY(I42,1) -> 46140 | I43: =WORKDAY(H43,J43) -> 46142 | J43: =G43/$N$4 -> 2 | K43: Not Started
A44: {=INDEX('Sprint Calendar'!$A:$A, MATCH(1, ('Project Planning (2)'!I98 >= 'Sprint Calendar'!$B:$B) * ('Project Planning (2)'!H98 <= 'Sprint Calendar'!$C:$C), 0))} -> Sprint 1 | B44: Mandate | C44: FAS 81831 Generate SSB Mandate Subscription/Redemption Data 產生SSB全委申贖資料 | D44: BA | E44: Generate SSB Mandate Subscription/Redemption Data Requirement | F44: BA | G44: 2 | H44: =WORKDAY(I43,1) -> 46143 | I44: =WORKDAY(H44,J44) -> 46147 | J44: =G44/$N$4 -> 2 | K44: Not Started
A45: {=INDEX('Sprint Calendar'!$A:$A, MATCH(1, ('Project Planning (2)'!I102 >= 'Sprint Calendar'!$B:$B) * ('Project Planning (2)'!H102 <= 'Sprint Calendar'!$C:$C), 0))} -> Sprint 2 | B45: Mandate | C45: FAS 81832 Export SSB Mandate Subscription/Redemption Data 匯出SSB全委申贖資料 | D45: BA | E45: Export SSB Mandate Subscription/Redemption Data Requirement Analysis | F45: BA | G45: 0.5 | H45: =WORKDAY(I44,1) -> 46148 | I45: =WORKDAY(H45,J45) -> 46148 | J45: =G45/$N$4 -> 0.5 | K45: Not Started
A46: {=INDEX('Sprint Calendar'!$A:$A, MATCH(1, ('Project Planning (2)'!I103 >= 'Sprint Calendar'!$B:$B) * ('Project Planning (2)'!H103 <= 'Sprint Calendar'!$C:$C), 0))} -> Sprint 3 | B46: Mandate | C46: FAS 81832 Export SSB Mandate Subscription/Redemption Data 匯出SSB全委申贖資料 | D46: BA | E46: Export SSB Mandate Subscription/Redemption Data Requirement | F46: BA | G46: 0.5 | H46: =WORKDAY(I45,1) -> 46149 | I46: =WORKDAY(H46,J46) -> 46149 | J46: =G46/$N$4 -> 0.5 | K46: Not Started
A47: {=INDEX('Sprint Calendar'!$A:$A, MATCH(1, ('Project Planning (2)'!I107 >= 'Sprint Calendar'!$B:$B) * ('Project Planning (2)'!H107 <= 'Sprint Calendar'!$C:$C), 0))} -> Sprint 5 | B47: Mandate | C47: FAS 883 Fund NAV Auto Import Process 基金淨值自動匯入作業 | D47: BA | E47: Fund NAV Auto Import Process Requirement Analysis | F47: BA | G47: 2 | H47: =WORKDAY(I46,1) -> 46150 | I47: =WORKDAY(H47,J47) -> 46154 | J47: =G47/$N$4 -> 2 | K47: Not Started
A48: {=INDEX('Sprint Calendar'!$A:$A, MATCH(1, ('Project Planning (2)'!I108 >= 'Sprint Calendar'!$B:$B) * ('Project Planning (2)'!H108 <= 'Sprint Calendar'!$C:$C), 0))} -> Sprint 6 | B48: Mandate | C48: FAS 883 Fund NAV Auto Import Process 基金淨值自動匯入作業 | D48: BA | E48: Fund NAV Auto Import Process Data Requirement | F48: BA | G48: 2 | H48: =WORKDAY(I47,1) -> 46155 | I48: =WORKDAY(H48,J48) -> 46157 | J48: =G48/$N$4 -> 2 | K48: Not Started
A49: {=INDEX('Sprint Calendar'!$A:$A, MATCH(1, ('Project Planning (2)'!I112 >= 'Sprint Calendar'!$B:$B) * ('Project Planning (2)'!H112 <= 'Sprint Calendar'!$C:$C), 0))} -> Sprint 7 | B49: Mandate | C49: FAS 884 Fund NAV Import Status Inquiry 基金淨值匯入狀況查詢 | D49: BA | E49: Fund NAV Import Status Inquiry Requirement Analysis | F49: BA | G49: 1 | H49: =WORKDAY(I48,1) -> 46160 | I49: =WORKDAY(H49,J49) -> 46161 | J49: =G49/$N$4 -> 1 | K49: Not Started
A50: {=INDEX('Sprint Calendar'!$A:$A, MATCH(1, ('Project Planning (2)'!I113 >= 'Sprint Calendar'!$B:$B) * ('Project Planning (2)'!H113 <= 'Sprint Calendar'!$C:$C), 0))} -> Sprint 8 | B50: Mandate | C50: FAS 884 Fund NAV Import Status Inquiry 基金淨值匯入狀況查詢 | D50: BA | E50: Fund NAV Import Status Inquiry Data Requirement | F50: BA | G50: 2 | H50: =WORKDAY(I49,1) -> 46162 | I50: =WORKDAY(H50,J50) -> 46164 | J50: =G50/$N$4 -> 2 | K50: Not Started
A51: {=INDEX('Sprint Calendar'!$A:$A, MATCH(1, ('Project Planning (2)'!I117 >= 'Sprint Calendar'!$B:$B) * ('Project Planning (2)'!H117 <= 'Sprint Calendar'!$C:$C), 0))} -> Sprint 8 | B51: Mandate | C51: FAS 893 Calendar File - Mandate 全委日曆檔 | D51: BA | E51: Calendar File Requirement Analysis | F51: BA | G51: 1 | H51: =WORKDAY(I50,1) -> 46167 | I51: =WORKDAY(H51,J51) -> 46168 | J51: =G51/$N$4 -> 1 | K51: Not Started
A52: {=INDEX('Sprint Calendar'!$A:$A, MATCH(1, ('Project Planning (2)'!I118 >= 'Sprint Calendar'!$B:$B) * ('Project Planning (2)'!H118 <= 'Sprint Calendar'!$C:$C), 0))} -> Sprint 9 | B52: Mandate | C52: FAS 893 Calendar File - Mandate 全委日曆檔 | D52: BA | E52: Calendar File Requirement | F52: BA | G52: 1 | H52: =WORKDAY(I51,1) -> 46169 | I52: =WORKDAY(H52,J52) -> 46170 | J52: =G52/$N$4 -> 1 | K52: Not Started
A53: {=INDEX('Sprint Calendar'!$A:$A, MATCH(1, ('Project Planning (2)'!I122 >= 'Sprint Calendar'!$B:$B) * ('Project Planning (2)'!H122 <= 'Sprint Calendar'!$C:$C), 0))} -> Sprint 10 | B53: Mandate | C53: FAS 893 Payment Notice – Management Fee, Custody Fee 付款通知書-經理費、保管費 | D53: BA | E53: Payment Notice – Management Fee, Custody Fee Requirement Analysis | F53: BA | G53: 1 | H53: =WORKDAY(I52,1) -> 46171 | I53: =WORKDAY(H53,J53) -> 46174 | J53: =G53/$N$4 -> 1 | K53: Not Started
A54: {=INDEX('Sprint Calendar'!$A:$A, MATCH(1, ('Project Planning (2)'!I123 >= 'Sprint Calendar'!$B:$B) * ('Project Planning (2)'!H123 <= 'Sprint Calendar'!$C:$C), 0))} -> Sprint 10 | B54: Mandate | C54: FAS 893 Payment Notice – Management Fee, Custody Fee 付款通知書-經理費、保管費 | D54: BA | E54: Payment Notice – Management Fee, Custody Fee Requirement | F54: BA | G54: 2 | H54: =WORKDAY(I53,1) -> 46175 | I54: =WORKDAY(H54,J54) -> 46177 | J54: =G54/$N$4 -> 2 | K54: Not Started
A55: {=INDEX('Sprint Calendar'!$A:$A, MATCH(1, ('Project Planning (2)'!I127 >= 'Sprint Calendar'!$B:$B) * ('Project Planning (2)'!H127 <= 'Sprint Calendar'!$C:$C), 0))} -> #N/A | B55: Mandate | C55: FAS 893 Validation – Dividend Data 檢核-配息資料 | D55: BA | E55: Validation – Dividend Data Requirement Analysis | F55: BA | G55: 1.5 | H55: =WORKDAY(I54,1) -> 46178 | I55: =WORKDAY(H55,J55) -> 46181 | J55: =G55/$N$4 -> 1.5 | K55: Not Started
A56: {=INDEX('Sprint Calendar'!$A:$A, MATCH(1, ('Project Planning (2)'!I128 >= 'Sprint Calendar'!$B:$B) * ('Project Planning (2)'!H128 <= 'Sprint Calendar'!$C:$C), 0))} -> #N/A | B56: Mandate | C56: FAS 893 Validation – Dividend Data 檢核-配息資料 | D56: BA | E56: Validation – Dividend Data Requirement | F56: BA | G56: 1.5 | H56: =WORKDAY(I55,1) -> 46182 | I56: =WORKDAY(H56,J56) -> 46183 | J56: =G56/$N$4 -> 1.5 | K56: Not Started
A57: {=INDEX('Sprint Calendar'!$A:$A, MATCH(1, ('Project Planning (2)'!I132 >= 'Sprint Calendar'!$B:$B) * ('Project Planning (2)'!H132 <= 'Sprint Calendar'!$C:$C), 0))} -> #N/A | B57: Mandate | C57: FAS 893 Payment Notice – Dividend Distribution | D57: BA | E57: Payment Notice – Dividend Distribution Requirement Analysis | F57: BA | G57: 1 | H57: =WORKDAY(I56,1) -> 46184 | I57: =WORKDAY(H57,J57) -> 46185 | J57: =G57/$N$4 -> 1 | K57: Not Started
A58: {=INDEX('Sprint Calendar'!$A:$A, MATCH(1, ('Project Planning (2)'!I133 >= 'Sprint Calendar'!$B:$B) * ('Project Planning (2)'!H133 <= 'Sprint Calendar'!$C:$C), 0))} -> #N/A | B58: Mandate | C58: FAS 893 Payment Notice – Dividend Distribution | D58: BA | E58: Payment Notice – Dividend Distribution Requirement | F58: BA | G58: 1 | H58: =WORKDAY(I57,1) -> 46188 | I58: =WORKDAY(H58,J58) -> 46189 | J58: =G58/$N$4 -> 1 | K58: Not Started
A59: {=INDEX('Sprint Calendar'!$A:$A, MATCH(1, ('Project Planning (2)'!I137 >= 'Sprint Calendar'!$B:$B) * ('Project Planning (2)'!H137 <= 'Sprint Calendar'!$C:$C), 0))} -> #N/A | B59: Mandate | C59: FAS 893 Payment Notice – Dividend Instruction Printing | D59: BA | E59: Payment Notice – Dividend Instruction Printing Requirement Analysis | F59: BA | G59: 1 | H59: =WORKDAY(I58,1) -> 46190 | I59: =WORKDAY(H59,J59) -> 46191 | J59: =G59/$N$4 -> 1 | K59: Not Started
A60: {=INDEX('Sprint Calendar'!$A:$A, MATCH(1, ('Project Planning (2)'!I138 >= 'Sprint Calendar'!$B:$B) * ('Project Planning (2)'!H138 <= 'Sprint Calendar'!$C:$C), 0))} -> #N/A | B60: Mandate | C60: FAS 893 Payment Notice – Dividend Instruction Printing | D60: BA | E60: Payment Notice – Dividend Instruction Printing Requirement | F60: BA | G60: 1 | H60: =WORKDAY(I59,1) -> 46192 | I60: =WORKDAY(H60,J60) -> 46195 | J60: =G60/$N$4 -> 1 | K60: Not Started
A61: {=INDEX('Sprint Calendar'!$A:$A, MATCH(1, ('Project Planning (2)'!I142 >= 'Sprint Calendar'!$B:$B) * ('Project Planning (2)'!H142 <= 'Sprint Calendar'!$C:$C), 0))} -> #N/A | B61: Mandate | C61: DMS 271 Mandate Data Generation Process 全委資料產生作業 | D61: BA | E61: Mandate Data Generation Process Requirement Analysis | F61: BA | G61: 2 | H61: =WORKDAY(I60,1) -> 46196 | I61: =WORKDAY(H61,J61) -> 46198 | J61: =G61/$N$4 -> 2 | K61: Not Started
A62: {=INDEX('Sprint Calendar'!$A:$A, MATCH(1, ('Project Planning (2)'!I143 >= 'Sprint Calendar'!$B:$B) * ('Project Planning (2)'!H143 <= 'Sprint Calendar'!$C:$C), 0))} -> #N/A | B62: Mandate | C62: DMS 271 Mandate Data Generation Process 全委資料產生作業 | D62: BA | E62: Mandate Data Generation Process Requirement Doc | F62: BA | G62: 2 | H62: =WORKDAY(I61,1) -> 46199 | I62: =WORKDAY(H62,J62) -> 46203 | J62: =G62/$N$4 -> 2 | K62: Not Started
A63: {=INDEX('Sprint Calendar'!$A:$A, MATCH(1, ('Project Planning (2)'!I147 >= 'Sprint Calendar'!$B:$B) * ('Project Planning (2)'!H147 <= 'Sprint Calendar'!$C:$C), 0))} -> Sprint 5 | B63: Mandate | C63: DMS 272 Mandate Data Maintenance Process 全委資料維護作業 | D63: BA | E63: Mandate Data Maintenance Process Requirement Analysis | F63: BA | G63: 2 | H63: =WORKDAY(I62,1) -> 46204 | I63: =WORKDAY(H63,J63) -> 46206 | J63: =G63/$N$4 -> 2 | K63: Not Started
A64: {=INDEX('Sprint Calendar'!$A:$A, MATCH(1, ('Project Planning (2)'!I148 >= 'Sprint Calendar'!$B:$B) * ('Project Planning (2)'!H148 <= 'Sprint Calendar'!$C:$C), 0))} -> Sprint 5 | B64: Mandate | C64: DMS 272 Mandate Data Maintenance Process 全委資料維護作業 | D64: BA | E64: Mandate Data Maintenance Process Requirement Doc | F64: BA | G64: 2 | H64: =WORKDAY(I63,1) -> 46209 | I64: =WORKDAY(H64,J64) -> 46211 | J64: =G64/$N$4 -> 2 | K64: Not Started
A65: {=INDEX('Sprint Calendar'!$A:$A, MATCH(1, ('Project Planning (2)'!I152 >= 'Sprint Calendar'!$B:$B) * ('Project Planning (2)'!H152 <= 'Sprint Calendar'!$C:$C), 0))} -> Sprint 7 | B65: Mandate | C65: DMS 593916 Subscription/Redemption Posting Details Report 申購贖回入帳明細表 | D65: BA | E65: Subscription/Redemption Posting Details Report Requirement Analysis | F65: BA | G65: 1 | H65: =WORKDAY(I64,1) -> 46212 | I65: =WORKDAY(H65,J65) -> 46213 | J65: =G65/$N$4 -> 1 | K65: Not Started
A66: {=INDEX('Sprint Calendar'!$A:$A, MATCH(1, ('Project Planning (2)'!I153 >= 'Sprint Calendar'!$B:$B) * ('Project Planning (2)'!H153 <= 'Sprint Calendar'!$C:$C), 0))} -> Sprint 8 | B66: Mandate | C66: DMS 593916 Subscription/Redemption Posting Details Report 申購贖回入帳明細表 | D66: BA | E66: Subscription/Redemption Posting Details Report Requirement Doc | F66: BA | G66: 1 | H66: =WORKDAY(I65,1) -> 46216 | I66: =WORKDAY(H66,J66) -> 46217 | J66: =G66/$N$4 -> 1 | K66: Not Started
A67: {=INDEX('Sprint Calendar'!$A:$A, MATCH(1, ('Project Planning (2)'!I157 >= 'Sprint Calendar'!$B:$B) * ('Project Planning (2)'!H157 <= 'Sprint Calendar'!$C:$C), 0))} -> Sprint 9 | B67: Mandate | C67: DMS 6571B Mandate Contract Asset Movement Report 全委契約資產動動表 | D67: BA | E67: Mandate Contract Asset Movement Report Requirement Analysis | F67: BA | G67: 1 | H67: =WORKDAY(I66,1) -> 46218 | I67: =WORKDAY(H67,J67) -> 46219 | J67: =G67/$N$4 -> 1 | K67: Not Started
A68: {=INDEX('Sprint Calendar'!$A:$A, MATCH(1, ('Project Planning (2)'!I158 >= 'Sprint Calendar'!$B:$B) * ('Project Planning (2)'!H158 <= 'Sprint Calendar'!$C:$C), 0))} -> Sprint 9 | B68: Mandate | C68: DMS 6571B Mandate Contract Asset Movement Report 全委契約資產動動表 | D68: BA | E68: Mandate Contract Asset Movement Report Requirement Doc | F68: BA | G68: 1 | H68: =WORKDAY(I67,1) -> 46220 | I68: =WORKDAY(H68,J68) -> 46223 | J68: =G68/$N$4 -> 1 | K68: Not Started
A69: {=INDEX('Sprint Calendar'!$A:$A, MATCH(1, ('Project Planning (2)'!I162 >= 'Sprint Calendar'!$B:$B) * ('Project Planning (2)'!H162 <= 'Sprint Calendar'!$C:$C), 0))} -> Sprint 11 | B69: Mandate | C69: DMS 65731 PAMS Inventory File Export PAMS 庫存檔轉出 | D69: BA | E69: PAMS Inventory File Export Requirement Analysis | F69: BA | G69: 1 | H69: =WORKDAY(I68,1) -> 46224 | I69: =WORKDAY(H69,J69) -> 46225 | J69: =G69/$N$4 -> 1 | K69: Not Started
A70: {=INDEX('Sprint Calendar'!$A:$A, MATCH(1, ('Project Planning (2)'!I163 >= 'Sprint Calendar'!$B:$B) * ('Project Planning (2)'!H163 <= 'Sprint Calendar'!$C:$C), 0))} -> Sprint 11 | B70: Mandate | C70: DMS 65731 PAMS Inventory File Export PAMS 庫存檔轉出 | D70: BA | E70: PAMS Inventory File Export Requirement Doc | F70: BA | G70: 1 | H70: =WORKDAY(I69,1) -> 46226 | I70: =WORKDAY(H70,J70) -> 46227 | J70: =G70/$N$4 -> 1 | K70: Not Started
A71: {=INDEX('Sprint Calendar'!$A:$A, MATCH(1, ('Project Planning (2)'!I167 >= 'Sprint Calendar'!$B:$B) * ('Project Planning (2)'!H167 <= 'Sprint Calendar'!$C:$C), 0))} -> Sprint 12 | B71: Mandate | C71: DMS 756 Mandate Stock Stop-Loss Control Table 全權委託股票停損控管表 | D71: BA | E71: Mandate Stock Stop-Loss Control Table Requirement Analysis | F71: BA | G71: 1 | H71: =WORKDAY(I70,1) -> 46230 | I71: =WORKDAY(H71,J71) -> 46231 | J71: =G71/$N$4 -> 1 | K71: Not Started
A72: {=INDEX('Sprint Calendar'!$A:$A, MATCH(1, ('Project Planning (2)'!I168 >= 'Sprint Calendar'!$B:$B) * ('Project Planning (2)'!H168 <= 'Sprint Calendar'!$C:$C), 0))} -> Sprint 13 | B72: Mandate | C72: DMS 756 Mandate Stock Stop-Loss Control Table 全權委託股票停損控管表 | D72: BA | E72: Mandate Stock Stop-Loss Control Table Requirement | F72: BA | G72: 1 | H72: =WORKDAY(I71,1) -> 46232 | I72: =WORKDAY(H72,J72) -> 46233 | J72: =G72/$N$4 -> 1 | K72: Not Started
A73: {=INDEX('Sprint Calendar'!$A:$A, MATCH(1, ('Project Planning (2)'!I172 >= 'Sprint Calendar'!$B:$B) * ('Project Planning (2)'!H172 <= 'Sprint Calendar'!$C:$C), 0))} -> Sprint 13 | B73: Mandate | C73: Report - 基金規模報表查詢 | D73: BA | E73: Report - 基金規模報表查詢 Requirement Analysis | F73: BA | G73: 1 | H73: =WORKDAY(I72,1) -> 46234 | I73: =WORKDAY(H73,J73) -> 46237 | J73: =G73/$N$4 -> 1 | K73: Not Started
A74: {=INDEX('Sprint Calendar'!$A:$A, MATCH(1, ('Project Planning (2)'!I173 >= 'Sprint Calendar'!$B:$B) * ('Project Planning (2)'!H173 <= 'Sprint Calendar'!$C:$C), 0))} -> Sprint 13 | B74: Mandate | C74: Report - 基金規模報表查詢 | D74: BA | E74: Report - 基金規模報表查詢 Requirement Doc | F74: BA | G74: 1 | H74: =WORKDAY(I73,1) -> 46238 | I74: =WORKDAY(H74,J74) -> 46239 | J74: =G74/$N$4 -> 1 | K74: Not Started
A75: {=INDEX('Sprint Calendar'!$A:$A, MATCH(1, ('Project Planning (2)'!I176 >= 'Sprint Calendar'!$B:$B) * ('Project Planning (2)'!H176 <= 'Sprint Calendar'!$C:$C), 0))} -> Sprint 15 | B75: Mandate | C75: DMS 744 Taiwan Ratings Reporting Data 中華信評申報資料 | D75: BA | E75: Taiwan Ratings Reporting Data Requirement Analysis | F75: BA | G75: 1 | H75: =WORKDAY(I74,1) -> 46240 | I75: =WORKDAY(H75,J75) -> 46241 | J75: =G75/$N$4 -> 1 | K75: Not Started
A76: {=INDEX('Sprint Calendar'!$A:$A, MATCH(1, ('Project Planning (2)'!I177 >= 'Sprint Calendar'!$B:$B) * ('Project Planning (2)'!H177 <= 'Sprint Calendar'!$C:$C), 0))} -> Sprint 15 | B76: Mandate | C76: DMS 744 Taiwan Ratings Reporting Data 中華信評申報資料 | D76: BA | E76: Taiwan Ratings Reporting Data Requirement Doc | F76: BA | G76: 1 | H76: =WORKDAY(I75,1) -> 46244 | I76: =WORKDAY(H76,J76) -> 46245 | J76: =G76/$N$4 -> 1 | K76: Not Started
A77: {=INDEX('Sprint Calendar'!$A:$A, MATCH(1, ('Project Planning (2)'!I180 >= 'Sprint Calendar'!$B:$B) * ('Project Planning (2)'!H180 <= 'Sprint Calendar'!$C:$C), 0))} -> Sprint 16 | B77: Mandate | C77: DMS 758 Mutual Fund Asset Size Export Process 共同基金資產規模轉出作業 | D77: BA | E77: Mutual Fund Asset Size Export Process Requirement Analysis | F77: BA | G77: 1 | H77: =WORKDAY(I76,1) -> 46246 | I77: =WORKDAY(H77,J77) -> 46247 | J77: =G77/$N$4 -> 1 | K77: Not Started
A78: {=INDEX('Sprint Calendar'!$A:$A, MATCH(1, ('Project Planning (2)'!I181 >= 'Sprint Calendar'!$B:$B) * ('Project Planning (2)'!H181 <= 'Sprint Calendar'!$C:$C), 0))} -> Sprint 17 | B78: Mandate | C78: DMS 758 Mutual Fund Asset Size Export Process 共同基金資產規模轉出作業 | D78: BA | E78: Mutual Fund Asset Size Export Process Requirement Doc | F78: BA | G78: 1 | H78: =WORKDAY(I77,1) -> 46248 | I78: =WORKDAY(H78,J78) -> 46251 | J78: =G78/$N$4 -> 1 | K78: Not Started
A79: {=INDEX('Sprint Calendar'!$A:$A, MATCH(1, ('Project Planning (2)'!I184 >= 'Sprint Calendar'!$B:$B) * ('Project Planning (2)'!H184 <= 'Sprint Calendar'!$C:$C), 0))} -> Sprint 18 | B79: Shareholders' Meeting & Management | C79: Generate Shareholder Meeting Data | D79: BA | E79: Generate Shareholder Meeting Data Requirement Analysis | F79: BA | G79: 0.5 | H79: =WORKDAY(I78,1) -> 46252 | I79: =WORKDAY(H79,J79) -> 46252 | J79: =G79/$N$5 -> 0.5 | K79: Not Started
A80: {=INDEX('Sprint Calendar'!$A:$A, MATCH(1, ('Project Planning (2)'!I185 >= 'Sprint Calendar'!$B:$B) * ('Project Planning (2)'!H185 <= 'Sprint Calendar'!$C:$C), 0))} -> Sprint 18 | B80: Shareholders' Meeting & Management | C80: Generate Shareholder Meeting Data | D80: BA | E80: Generate Shareholder Meeting Data Requirement | F80: BA | G80: 0.5 | H80: =WORKDAY(I79,1) -> 46253 | I80: =WORKDAY(H80,J80) -> 46253 | J80: =G80/$N$5 -> 0.5 | K80: Not Started
A81: {=INDEX('Sprint Calendar'!$A:$A, MATCH(1, ('Project Planning (2)'!I189 >= 'Sprint Calendar'!$B:$B) * ('Project Planning (2)'!H189 <= 'Sprint Calendar'!$C:$C), 0))} -> Sprint 19 | B81: Shareholders' Meeting & Management | C81: Generate Memo for Assigned Personnel/Function | D81: BA | E81: Generate Memo for Assigned Personnel/Function Requirement Analysis | F81: BA | G81: 0.5 | H81: =WORKDAY(I80,1) -> 46254 | I81: =WORKDAY(H81,J81) -> 46254 | J81: =G81/$N$5 -> 0.5 | K81: Not Started
A82: {=INDEX('Sprint Calendar'!$A:$A, MATCH(1, ('Project Planning (2)'!I190 >= 'Sprint Calendar'!$B:$B) * ('Project Planning (2)'!H190 <= 'Sprint Calendar'!$C:$C), 0))} -> Sprint 20 | B82: Shareholders' Meeting & Management | C82: Generate Memo for Assigned Personnel/Function | D82: BA | E82: Generate Memo for Assigned Personnel/Function Requirement | F82: BA | G82: 0.5 | H82: =WORKDAY(I81,1) -> 46255 | I82: =WORKDAY(H82,J82) -> 46255 | J82: =G82/$N$5 -> 0.5 | K82: Not Started
A83: {=INDEX('Sprint Calendar'!$A:$A, MATCH(1, ('Project Planning (2)'!I194 >= 'Sprint Calendar'!$B:$B) * ('Project Planning (2)'!H194 <= 'Sprint Calendar'!$C:$C), 0))} -> Sprint 21 | B83: Shareholders' Meeting & Management | C83: Director/Supervisor Election Report/Function | D83: BA | E83: Director/Supervisor Election Report/Function Requirement Analysis | F83: BA | G83: 0.5 | H83: =WORKDAY(I82,1) -> 46258 | I83: =WORKDAY(H83,J83) -> 46258 | J83: =G83/$N$5 -> 0.5 | K83: Not Started
A84: {=INDEX('Sprint Calendar'!$A:$A, MATCH(1, ('Project Planning (2)'!I195 >= 'Sprint Calendar'!$B:$B) * ('Project Planning (2)'!H195 <= 'Sprint Calendar'!$C:$C), 0))} -> Sprint 21 | B84: Shareholders' Meeting & Management | C84: Director/Supervisor Election Report/Function | D84: BA | E84: Director/Supervisor Election Report/Function Requirement | F84: BA | G84: 0.5 | H84: =WORKDAY(I83,1) -> 46259 | I84: =WORKDAY(H84,J84) -> 46259 | J84: =G84/$N$5 -> 0.5 | K84: Not Started
A85: {=INDEX('Sprint Calendar'!$A:$A, MATCH(1, ('Project Planning (2)'!I199 >= 'Sprint Calendar'!$B:$B) * ('Project Planning (2)'!H199 <= 'Sprint Calendar'!$C:$C), 0))} -> Sprint 22 | B85: Shareholders' Meeting & Management | C85: Shareholder Meeting Fund Attendance Details Report | D85: BA | E85: Shareholder Meeting Fund Attendance Details Report Requirement Analysis | F85: BA | G85: 0.2 | H85: =WORKDAY(I84,1) -> 46260 | I85: =WORKDAY(H85,J85) -> 46260 | J85: =G85/$N$5 -> 0.2 | K85: Not Started
A86: {=INDEX('Sprint Calendar'!$A:$A, MATCH(1, ('Project Planning (2)'!I200 >= 'Sprint Calendar'!$B:$B) * ('Project Planning (2)'!H200 <= 'Sprint Calendar'!$C:$C), 0))} -> Sprint 22 | B86: Shareholders' Meeting & Management | C86: Shareholder Meeting Fund Attendance Details Report | D86: BA | E86: Shareholder Meeting Fund Attendance Details Report Requirement | F86: BA | G86: 0.3 | H86: =WORKDAY(I85,1) -> 46261 | I86: =WORKDAY(H86,J86) -> 46261 | J86: =G86/$N$5 -> 0.3 | K86: Not Started
A87: {=INDEX('Sprint Calendar'!$A:$A, MATCH(1, ('Project Planning (2)'!I204 >= 'Sprint Calendar'!$B:$B) * ('Project Planning (2)'!H204 <= 'Sprint Calendar'!$C:$C), 0))} -> Sprint 23 | B87: Shareholders' Meeting & Management | C87: Shareholder Meeting Missing Election Report Details | D87: BA | E87: Shareholder Meeting Missing Election Report Details Requirement Analysis | F87: BA | G87: 0.2 | H87: =WORKDAY(I86,1) -> 46262 | I87: =WORKDAY(H87,J87) -> 46262 | J87: =G87/$N$5 -> 0.2 | K87: Not Started
A88: {=INDEX('Sprint Calendar'!$A:$A, MATCH(1, ('Project Planning (2)'!I205 >= 'Sprint Calendar'!$B:$B) * ('Project Planning (2)'!H205 <= 'Sprint Calendar'!$C:$C), 0))} -> Sprint 24 | B88: Shareholders' Meeting & Management | C88: Shareholder Meeting Missing Election Report Details | D88: BA | E88: Shareholder Meeting Missing Election Report Details Report Requirement | F88: BA | G88: 0.3 | H88: =WORKDAY(I87,1) -> 46265 | I88: =WORKDAY(H88,J88) -> 46265 | J88: =G88/$N$5 -> 0.3 | K88: Not Started
A89: {=INDEX('Sprint Calendar'!$A:$A, MATCH(1, ('Project Planning (2)'!I209 >= 'Sprint Calendar'!$B:$B) * ('Project Planning (2)'!H209 <= 'Sprint Calendar'!$C:$C), 0))} -> Sprint 25 | B89: Shareholders' Meeting & Management | C89: Stock Basic Data Maintenance | D89: BA | E89: Stock Basic Data Maintenance Requirement Analysis | F89: BA | G89: 1 | H89: =WORKDAY(I88,1) -> 46266 | I89: =WORKDAY(H89,J89) -> 46267 | J89: =G89/$N$5 -> 1 | K89: Not Started
A90: {=INDEX('Sprint Calendar'!$A:$A, MATCH(1, ('Project Planning (2)'!I210 >= 'Sprint Calendar'!$B:$B) * ('Project Planning (2)'!H210 <= 'Sprint Calendar'!$C:$C), 0))} -> Sprint 25 | B90: Shareholders' Meeting & Management | C90: Stock Basic Data Maintenance | D90: BA | E90: Stock Basic Data Maintenance Requirement | F90: BA | G90: 1 | H90: =WORKDAY(I89,1) -> 46268 | I90: =WORKDAY(H90,J90) -> 46269 | J90: =G90/$N$5 -> 1 | K90: Not Started
A91: Sprint 0 | B91: Shareholders' Meeting & Management | C91: Data Mapping, Data Migration & Create Tables in DB | D91: Development | E91: Data Mapping - Development | F91: Kent | G91: 5 | H91: =WORKDAY(I90,1) -> 46272 | I91: =WORKDAY(H91,J91) -> 46279 | J91: =G91/$N$5 -> 5 | K91: Completed
A92: Sprint 0 | B92: Shareholders' Meeting & Management | C92: Data Mapping, Data Migration & Create Tables in DB | D92: Development | E92: Data Migration - Development | F92: Kent | G92: 5 | H92: =WORKDAY(I91,1) -> 46280 | I92: =WORKDAY(H92,J92) -> 46287 | J92: =G92/$N$5 -> 5 | K92: Completed
A93: Sprint 0 | B93: Shareholders' Meeting & Management | C93: Data Mapping, Data Migration & Create Tables in DB | D93: Development | E93: Create Tables in DB - Development | F93: Kent | G93: 5 | H93: =WORKDAY(I92,1) -> 46288 | I93: =WORKDAY(H93,J93) -> 46295 | J93: =G93/$N$5 -> 5 | K93: Completed
A94: {=INDEX('Sprint Calendar'!$A:$A, MATCH(1, ('Project Planning (2)'!I17 >= 'Sprint Calendar'!$B:$B) * ('Project Planning (2)'!H17 <= 'Sprint Calendar'!$C:$C), 0))} -> Sprint 5 | B94: Dividend Distribution | C94: Data Mapping, Data Migration & Create Tables in DB | D94: Development | E94: Data Mapping - Development | F94: Kent | G94: 3 | H94: 45985 | I94: =WORKDAY(H94,J94) -> 45988 | J94: =G94/$N$5 -> 3 | K94: In progress
A95: {=INDEX('Sprint Calendar'!$A:$A, MATCH(1, ('Project Planning (2)'!I18 >= 'Sprint Calendar'!$B:$B) * ('Project Planning (2)'!H18 <= 'Sprint Calendar'!$C:$C), 0))} -> Sprint 5 | B95: Dividend Distribution | C95: Data Mapping, Data Migration & Create Tables in DB | D95: Development | E95: Data Migration - Development | F95: Kent | G95: 5 | H95: =WORKDAY(I94,1) -> 45989 | I95: =WORKDAY(H95,J95) -> 45996 | J95: =G95/$N$5 -> 5 | K95: Not Started
A96: {=INDEX('Sprint Calendar'!$A:$A, MATCH(1, ('Project Planning (2)'!I19 >= 'Sprint Calendar'!$B:$B) * ('Project Planning (2)'!H19 <= 'Sprint Calendar'!$C:$C), 0))} -> Sprint 5 | B96: Dividend Distribution | C96: Data Mapping, Data Migration & Create Tables in DB | D96: Development | E96: Create Tables in DB - Development | F96: Kent | G96: 2 | H96: =WORKDAY(I95,1) -> 45999 | I96: =WORKDAY(H96,J96) -> 46001 | J96: =G96/$N$5 -> 2 | K96: Not Started
A97: {=INDEX('Sprint Calendar'!$A:$A, MATCH(1, ('Project Planning (2)'!I23 >= 'Sprint Calendar'!$B:$B) * ('Project Planning (2)'!H23 <= 'Sprint Calendar'!$C:$C), 0))} -> Sprint 7 | B97: Dividend Distribution | C97: Maintain Distributable Balance 可分配餘額維護作業 | D97: Development | E97: Maintain Distributable Balance - Development 1 | F97: Kent | G97: 4 | H97: =WORKDAY(I94,1) -> 45989 | I97: =WORKDAY(H97,J97) -> 45995 | J97: =G97/$N$5 -> 4 | K97: Not Started
A98: {=INDEX('Sprint Calendar'!$A:$A, MATCH(1, ('Project Planning (2)'!I24 >= 'Sprint Calendar'!$B:$B) * ('Project Planning (2)'!H24 <= 'Sprint Calendar'!$C:$C), 0))} -> Sprint 7 | B98: Dividend Distribution | C98: Maintain Distributable Balance 可分配餘額維護作業 | D98: Development | E98: Maintain Distributable Balance - Development 2 | F98: Kent | G98: 4 | H98: =WORKDAY(I97,1) -> 45996 | I98: =WORKDAY(H98,J98) -> 46002 | J98: =G98/$N$5 -> 4 | K98: Not Started
A99: {=INDEX('Sprint Calendar'!$A:$A, MATCH(1, ('Project Planning (2)'!I28 >= 'Sprint Calendar'!$B:$B) * ('Project Planning (2)'!H28 <= 'Sprint Calendar'!$C:$C), 0))} -> Sprint 8 | B99: Dividend Distribution | C99: Domestic Dividend Information Inquiry 境內配息資訊查詢作業 | D99: Development | E99: Domestic Dividend Information Inquiry - Development 1 | F99: Kent | G99: 4 | H99: =WORKDAY(I96,1) -> 46002 | I99: =WORKDAY(H99,J99) -> 46008 | J99: =G99/$N$5 -> 4 | K99: Not Started
A100: {=INDEX('Sprint Calendar'!$A:$A, MATCH(1, ('Project Planning (2)'!I29 >= 'Sprint Calendar'!$B:$B) * ('Project Planning (2)'!H29 <= 'Sprint Calendar'!$C:$C), 0))} -> Sprint 9 | B100: Dividend Distribution | C100: Domestic Dividend Information Inquiry 境內配息資訊查詢作業 | D100: Development | E100: Domestic Dividend Information Inquiry - Development 2 | F100: Kent | G100: 4 | H100: =WORKDAY(I99,1) -> 46009 | I100: =WORKDAY(H100,J100) -> 46015 | J100: =G100/$N$5 -> 4 | K100: Not Started
A101: {=INDEX('Sprint Calendar'!$A:$A, MATCH(1, ('Project Planning (2)'!I33 >= 'Sprint Calendar'!$B:$B) * ('Project Planning (2)'!H33 <= 'Sprint Calendar'!$C:$C), 0))} -> Sprint 10 | B101: Dividend Distribution | C101: Upload Domestic Dividend Composition Info to EC 境內配息組成資訊上傳EC | D101: Development | E101: Upload Domestic Dividend Composition Info to EC - Development 1 | F101: Kent | G101: 4 | H101: =WORKDAY(I98,1) -> 46003 | I101: =WORKDAY(H101,J101) -> 46009 | J101: =G101/$N$5 -> 4 | K101: Not Started
...

Sheet TimeLine_Ver2
A1: App | B1: Module | C1: Code | D1: Chinese Name | E1: Features | F1: Detailed req est. | G1: Dev + Unit test est. | H1: Detailed req est. 2 | I1: Dev + Unit test est.3 | J1: Full Time Estimate(%) | K1: Status | L1: Req ETA | M1: DEV ETA | N1: UAT ETA
A2: DMS | B2: Shareholders' Meeting & Management | E2: Data mapping | F2: 3 | G2: 5 | H2: 45931 | I2: 45960 | J2: 0.7 | K2: In Unit Testing | L2: =WORKDAY("10/1/2025",表格1_32[[#This Row],[Detailed req est. ]]/表格1_32[[#This Row],[Full Time Estimate(%)]]) -> 45937 | M2: =WORKDAY(表格1_32[[#This Row],[Req ETA]],表格1_32[[#This Row],[Dev + Unit test est.]]/表格1_32[[#This Row],[Full Time Estimate(%)]]) -> 45946
A3: DMS | B3: Shareholders' Meeting & Management | E3: Data Migration | F3: 3 | G3: 5 | H3: 45931 | I3: 45960 | J3: 0.7 | K3: In Unit Testing | L3: =WORKDAY(M2,表格1_32[[#This Row],[Detailed req est. ]]/表格1_32[[#This Row],[Full Time Estimate(%)]]) -> 45952 | M3: =WORKDAY(表格1_32[[#This Row],[Req ETA]],表格1_32[[#This Row],[Dev + Unit test est.]]/表格1_32[[#This Row],[Full Time Estimate(%)]]) -> 45961
A4: DMS | B4: Shareholders' Meeting & Management | E4: Create Tables in DB | F4: 3 | G4: 5 | H4: 45931 | I4: 45960 | J4: 0.7 | K4: In Unit Testing | L4: =WORKDAY(M3,表格1_32[[#This Row],[Detailed req est. ]]/表格1_32[[#This Row],[Full Time Estimate(%)]]) -> 45967 | M4: =WORKDAY(表格1_32[[#This Row],[Req ETA]],表格1_32[[#This Row],[Dev + Unit test est.]]/表格1_32[[#This Row],[Full Time Estimate(%)]]) -> 45978
A5: DMS | B5: Shareholders' Meeting & Management | C5: 7911、79161 | D5: 股東會資料產生 | E5: Generate Shareholder Meeting Data | F5: 1 | G5: 9 | H5: =H4+#REF!+#REF!+#REF!+4 -> #REF! | I5: =WORKDAY(表格1_32[[#This Row],[Detailed req est. 2]],#REF!) -> #REF! | J5: 0.7 | K5: In Unit Testing | L5: =WORKDAY(M4,表格1_32[[#This Row],[Detailed req est. ]]/表格1_32[[#This Row],[Full Time Estimate(%)]]) -> 45979 | M5: =WORKDAY(表格1_32[[#This Row],[Req ETA]],表格1_32[[#This Row],[Dev + Unit test est.]]/表格1_32[[#This Row],[Full Time Estimate(%)]]) -> 45995
A6: DMS | B6: Shareholders' Meeting & Management | C6: 7931 | D6: 指派人員產生簽呈 | E6: Generate Memo for Assigned Personnel/Function | F6: 1 | G6: 5 | H6: =WORKDAY(I5,#REF!) -> #REF! | I6: =WORKDAY(表格1_32[[#This Row],[Detailed req est. 2]],#REF!) -> #REF! | J6: 1 | K6: In Development | L6: =WORKDAY(M5,表格1_32[[#This Row],[Detailed req est. ]]/表格1_32[[#This Row],[Full Time Estimate(%)]]) -> 45996 | M6: =WORKDAY(表格1_32[[#This Row],[Req ETA]],表格1_32[[#This Row],[Dev + Unit test est.]]/表格1_32[[#This Row],[Full Time Estimate(%)]]) -> 46003
A7: DMS | B7: Shareholders' Meeting & Management | C7: 7942 | D7: 董監改補選報告 | E7: Director/Supervisor Election Report/Function | F7: 1 | G7: 5 | H7: =WORKDAY(I6,#REF!) -> #REF! | I7: =WORKDAY(表格1_32[[#This Row],[Detailed req est. 2]],#REF!) -> #REF! | J7: 1 | L7: =WORKDAY(M6,表格1_32[[#This Row],[Detailed req est. ]]/表格1_32[[#This Row],[Full Time Estimate(%)]]) -> 46006 | M7: =WORKDAY(表格1_32[[#This Row],[Req ETA]],表格1_32[[#This Row],[Dev + Unit test est.]]/表格1_32[[#This Row],[Full Time Estimate(%)]]) -> 46013
A8: DMS | B8: Shareholders' Meeting & Management | C8: 7951 | D8: 股東會基金出席明細表 | E8: Shareholder Meeting Fund Attendance Details Report | F8: 0.5 | G8: 1 | H8: =WORKDAY(I7,#REF!) -> #REF! | I8: =WORKDAY(表格1_32[[#This Row],[Detailed req est. 2]],#REF!) -> #REF! | J8: 1 | L8: =WORKDAY(M7,表格1_32[[#This Row],[Detailed req est. ]]/表格1_32[[#This Row],[Full Time Estimate(%)]]) -> 46013 | M8: =WORKDAY(表格1_32[[#This Row],[Req ETA]],表格1_32[[#This Row],[Dev + Unit test est.]]/表格1_32[[#This Row],[Full Time Estimate(%)]]) -> 46014
A9: DMS | B9: Shareholders' Meeting & Management | C9: 7953 | D9: 股東會董監改選缺交報告明細表 | E9: Shareholder Meeting Missing Election Report Details | F9: 0.5 | G9: 1 | H9: =WORKDAY(I8,#REF!) -> #REF! | I9: =WORKDAY(表格1_32[[#This Row],[Detailed req est. 2]],#REF!) -> #REF! | J9: 1 | L9: =WORKDAY(M8,表格1_32[[#This Row],[Detailed req est. ]]/表格1_32[[#This Row],[Full Time Estimate(%)]]) -> 46014 | M9: =WORKDAY(表格1_32[[#This Row],[Req ETA]],表格1_32[[#This Row],[Dev + Unit test est.]]/表格1_32[[#This Row],[Full Time Estimate(%)]]) -> 46015
A10: DMS | B10: Shareholders' Meeting & Management | C10: 1111 | D10: 股票基本資料維護 | E10: Stock Basic Data Maintenance | F10: 2 | G10: 5 | H10: =WORKDAY(I9,#REF!) -> #REF! | I10: =WORKDAY(表格1_32[[#This Row],[Detailed req est. 2]],#REF!) -> #REF! | J10: 1 | L10: =WORKDAY(M9,表格1_32[[#This Row],[Detailed req est. ]]/表格1_32[[#This Row],[Full Time Estimate(%)]]) -> 46017 | M10: =WORKDAY(表格1_32[[#This Row],[Req ETA]],表格1_32[[#This Row],[Dev + Unit test est.]]/表格1_32[[#This Row],[Full Time Estimate(%)]]) -> 46024 | N10: =WORKDAY(表格1_32[[#This Row],[ DEV ETA]],10) -> 46038
A11: DMS | B11: Shareholders' Meeting & Management | C11: 3181 | D11: 轉入Stock_Pool List | E11: Import Stock_Pool List | F11: 0 | G11: 0 | H11: =WORKDAY(I10,#REF!) -> #REF! | I11: =WORKDAY(表格1_32[[#This Row],[Detailed req est. 2]],#REF!) -> #REF! | J11: 2 | L11: =WORKDAY(M10,表格1_32[[#This Row],[Detailed req est. ]]/表格1_32[[#This Row],[Full Time Estimate(%)]]) -> 46024 | M11: =WORKDAY(表格1_32[[#This Row],[Req ETA]],表格1_32[[#This Row],[Dev + Unit test est.]]/表格1_32[[#This Row],[Full Time Estimate(%)]]) -> 46024
A12: DMS | B12: Shareholders' Meeting & Management | C12: 3182 | D12: 維護Stock_Pool List | E12: Maintain Stock_Pool List | F12: 0 | G12: 0 | H12: =WORKDAY(I11,#REF!) -> #REF! | I12: =WORKDAY(表格1_32[[#This Row],[Detailed req est. 2]],#REF!) -> #REF! | J12: 2 | L12: =WORKDAY(M11,表格1_32[[#This Row],[Detailed req est. ]]/表格1_32[[#This Row],[Full Time Estimate(%)]]) -> 46024 | M12: =WORKDAY(表格1_32[[#This Row],[Req ETA]],表格1_32[[#This Row],[Dev + Unit test est.]]/表格1_32[[#This Row],[Full Time Estimate(%)]]) -> 46024 | N12: =WORKDAY(表格1_32[[#This Row],[ DEV ETA]],10) -> 46038
M13: =WORKDAY(表格1_32[[#This Row],[Req ETA]],表格1_32[[#This Row],[Dev + Unit test est.]]/表格1_32[[#This Row],[Full Time Estimate(%)]]) -> #DIV/0! | N13: =M13+14 -> #DIV/0!
A14: DMS | B14: Dividend | E14: Data mapping | F14: 2 | G14: 4 | H14: =WORKDAY(I12,#REF!) -> #REF! | I14: =WORKDAY(表格1_32[[#This Row],[Detailed req est. 2]],#REF!) -> #REF! | J14: 2 | L14: =WORKDAY(M12,表格1_32[[#This Row],[Detailed req est. ]]/表格1_32[[#This Row],[Full Time Estimate(%)]]) -> 46027 | M14: =WORKDAY(表格1_32[[#This Row],[Req ETA]],表格1_32[[#This Row],[Dev + Unit test est.]]/表格1_32[[#This Row],[Full Time Estimate(%)]]) -> 46029
A15: DMS | B15: Dividend | E15: Data Migration | F15: 2 | G15: 6 | H15: =WORKDAY(I14,#REF!) -> #REF! | I15: =WORKDAY(表格1_32[[#This Row],[Detailed req est. 2]],#REF!) -> #REF! | J15: 2 | L15: =WORKDAY(M14,表格1_32[[#This Row],[Detailed req est. ]]/表格1_32[[#This Row],[Full Time Estimate(%)]]) -> 46030 | M15: =WORKDAY(表格1_32[[#This Row],[Req ETA]],表格1_32[[#This Row],[Dev + Unit test est.]]/表格1_32[[#This Row],[Full Time Estimate(%)]]) -> 46035
A16: DMS | B16: Dividend | E16: Create Tables in DB | F16: 2 | G16: 3 | H16: =WORKDAY(I15,#REF!) -> #REF! | I16: =WORKDAY(表格1_32[[#This Row],[Detailed req est. 2]],#REF!) -> #REF! | J16: 2 | L16: =WORKDAY(M15,表格1_32[[#This Row],[Detailed req est. ]]/表格1_32[[#This Row],[Full Time Estimate(%)]]) -> 46036 | M16: =WORKDAY(表格1_32[[#This Row],[Req ETA]],表格1_32[[#This Row],[Dev + Unit test est.]]/表格1_32[[#This Row],[Full Time Estimate(%)]]) -> 46037
A17: DMS | B17: Dividend | E17: Maintain Distributable Balance | F17: 3 | G17: 11 | H17: =WORKDAY(I16,#REF!) -> #REF! | I17: =WORKDAY(表格1_32[[#This Row],[Detailed req est. 2]],#REF!) -> #REF! | J17: 2 | L17: =WORKDAY(M16,表格1_32[[#This Row],[Detailed req est. ]]/表格1_32[[#This Row],[Full Time Estimate(%)]]) -> 46038 | M17: =WORKDAY(表格1_32[[#This Row],[Req ETA]],表格1_32[[#This Row],[Dev + Unit test est.]]/表格1_32[[#This Row],[Full Time Estimate(%)]]) -> 46045
A18: DMS | B18: Dividend | E18: Domestic Dividend Information Inquiry | F18: 3 | G18: 10 | H18: =WORKDAY(I17,#REF!) -> #REF! | I18: =WORKDAY(表格1_32[[#This Row],[Detailed req est. 2]],#REF!) -> #REF! | J18: 2 | L18: =WORKDAY(M17,表格1_32[[#This Row],[Detailed req est. ]]/表格1_32[[#This Row],[Full Time Estimate(%)]]) -> 46048 | M18: =WORKDAY(表格1_32[[#This Row],[Req ETA]],表格1_32[[#This Row],[Dev + Unit test est.]]/表格1_32[[#This Row],[Full Time Estimate(%)]]) -> 46055
A19: DMS | B19: Dividend | E19: Upload Domestic Dividend Composition Info to EC | F19: 3 | G19: 10 | H19: =WORKDAY(I18,#REF!) -> #REF! | I19: =WORKDAY(表格1_32[[#This Row],[Detailed req est. 2]],#REF!) -> #REF! | J19: 2 | L19: =WORKDAY(M18,表格1_32[[#This Row],[Detailed req est. ]]/表格1_32[[#This Row],[Full Time Estimate(%)]]) -> 46056 | M19: =WORKDAY(表格1_32[[#This Row],[Req ETA]],表格1_32[[#This Row],[Dev + Unit test est.]]/表格1_32[[#This Row],[Full Time Estimate(%)]]) -> 46063 | N19: =WORKDAY(表格1_32[[#This Row],[ DEV ETA]],20) -> 46091
M20: =WORKDAY(表格1_32[[#This Row],[Req ETA]],表格1_32[[#This Row],[Dev + Unit test est.]]/表格1_32[[#This Row],[Full Time Estimate(%)]]) -> #DIV/0! | N20: =M20+14 -> #DIV/0!
A21: DMS | B21: Mandate | E21: Create Tables in DB | F21: 2 | G21: 5 | H21: =WORKDAY(I19,#REF!) -> #REF! | I21: =WORKDAY(表格1_32[[#This Row],[Detailed req est. 2]],#REF!) -> #REF! | J21: 2 | L21: =WORKDAY(M19,表格1_32[[#This Row],[Detailed req est. ]]/表格1_32[[#This Row],[Full Time Estimate(%)]]) -> 46064 | M21: =WORKDAY(表格1_32[[#This Row],[Req ETA]],表格1_32[[#This Row],[Dev + Unit test est.]]/表格1_32[[#This Row],[Full Time Estimate(%)]]) -> 46066
A22: DMS | B22: Mandate | E22: Data mapping | F22: 2 | G22: 7 | H22: =WORKDAY(I21,#REF!) -> #REF! | I22: =WORKDAY(表格1_32[[#This Row],[Detailed req est. 2]],#REF!) -> #REF! | J22: 2 | L22: =WORKDAY(M21,表格1_32[[#This Row],[Detailed req est. ]]/表格1_32[[#This Row],[Full Time Estimate(%)]]) -> 46069 | M22: =WORKDAY(表格1_32[[#This Row],[Req ETA]],表格1_32[[#This Row],[Dev + Unit test est.]]/表格1_32[[#This Row],[Full Time Estimate(%)]]) -> 46072
A23: DMS | B23: Mandate | E23: Data Migration | F23: 2 | G23: 4 | H23: =WORKDAY(I22,#REF!) -> #REF! | I23: =WORKDAY(表格1_32[[#This Row],[Detailed req est. 2]],#REF!) -> #REF! | J23: 2 | L23: =WORKDAY(M22,表格1_32[[#This Row],[Detailed req est. ]]/表格1_32[[#This Row],[Full Time Estimate(%)]]) -> 46073 | M23: =WORKDAY(表格1_32[[#This Row],[Req ETA]],表格1_32[[#This Row],[Dev + Unit test est.]]/表格1_32[[#This Row],[Full Time Estimate(%)]]) -> 46077
A24: FAS | B24: Mandate | E24: Subscription Details Report | F24: 2 | G24: 4 | H24: =WORKDAY(I23,#REF!) -> #REF! | I24: =WORKDAY(表格1_32[[#This Row],[Detailed req est. 2]],#REF!) -> #REF! | J24: 2 | L24: =WORKDAY(M23,表格1_32[[#This Row],[Detailed req est. ]]/表格1_32[[#This Row],[Full Time Estimate(%)]]) -> 46078 | M24: =WORKDAY(表格1_32[[#This Row],[Req ETA]],表格1_32[[#This Row],[Dev + Unit test est.]]/表格1_32[[#This Row],[Full Time Estimate(%)]]) -> 46080
A25: FAS | B25: Mandate | E25: Redemption Details Report | F25: 2 | G25: 4 | H25: =WORKDAY(I24,#REF!) -> #REF! | I25: =WORKDAY(表格1_32[[#This Row],[Detailed req est. 2]],#REF!) -> #REF! | J25: 2 | L25: =WORKDAY(M24,表格1_32[[#This Row],[Detailed req est. ]]/表格1_32[[#This Row],[Full Time Estimate(%)]]) -> 46083 | M25: =WORKDAY(表格1_32[[#This Row],[Req ETA]],表格1_32[[#This Row],[Dev + Unit test est.]]/表格1_32[[#This Row],[Full Time Estimate(%)]]) -> 46085
A26: FAS | B26: Mandate | E26: Full Discretionary NAV Import Process (State Street) | F26: 2 | G26: 5 | H26: =WORKDAY(I25,#REF!) -> #REF! | I26: =WORKDAY(表格1_32[[#This Row],[Detailed req est. 2]],#REF!) -> #REF! | J26: 2 | L26: =WORKDAY(M25,表格1_32[[#This Row],[Detailed req est. ]]/表格1_32[[#This Row],[Full Time Estimate(%)]]) -> 46086 | M26: =WORKDAY(表格1_32[[#This Row],[Req ETA]],表格1_32[[#This Row],[Dev + Unit test est.]]/表格1_32[[#This Row],[Full Time Estimate(%)]]) -> 46090
A27: FAS | B27: Mandate | E27: Generate Full Discretionary Subscription/Redemption Data | F27: 4 | G27: 9 | H27: =WORKDAY(I26,#REF!) -> #REF! | I27: =WORKDAY(表格1_32[[#This Row],[Detailed req est. 2]],#REF!) -> #REF! | J27: 2 | L27: =WORKDAY(M26,表格1_32[[#This Row],[Detailed req est. ]]/表格1_32[[#This Row],[Full Time Estimate(%)]]) -> 46092 | M27: =WORKDAY(表格1_32[[#This Row],[Req ETA]],表格1_32[[#This Row],[Dev + Unit test est.]]/表格1_32[[#This Row],[Full Time Estimate(%)]]) -> 46098
A28: FAS | B28: Mandate | E28: Export Full Discretionary Subscription/Redemption Data | F28: 2 | G28: 5 | H28: =WORKDAY(I27,#REF!) -> #REF! | I28: =WORKDAY(表格1_32[[#This Row],[Detailed req est. 2]],#REF!) -> #REF! | J28: 2 | L28: =WORKDAY(M27,表格1_32[[#This Row],[Detailed req est. ]]/表格1_32[[#This Row],[Full Time Estimate(%)]]) -> 46099 | M28: =WORKDAY(表格1_32[[#This Row],[Req ETA]],表格1_32[[#This Row],[Dev + Unit test est.]]/表格1_32[[#This Row],[Full Time Estimate(%)]]) -> 46101
A29: FAS | B29: Mandate | E29: Generate SSB Full Discretionary Subscription/Redemption Data | F29: 4 | G29: 9 | H29: =WORKDAY(I28,#REF!) -> #REF! | I29: =WORKDAY(表格1_32[[#This Row],[Detailed req est. 2]],#REF!) -> #REF! | J29: 2 | L29: =WORKDAY(M28,表格1_32[[#This Row],[Detailed req est. ]]/表格1_32[[#This Row],[Full Time Estimate(%)]]) -> 46105 | M29: =WORKDAY(表格1_32[[#This Row],[Req ETA]],表格1_32[[#This Row],[Dev + Unit test est.]]/表格1_32[[#This Row],[Full Time Estimate(%)]]) -> 46111
A30: FAS | B30: Mandate | E30: Export SSB Full Discretionary Subscription/Redemption Data | F30: 5 | G30: 9 | H30: =WORKDAY(I29,#REF!) -> #REF! | I30: =WORKDAY(表格1_32[[#This Row],[Detailed req est. 2]],#REF!) -> #REF! | J30: 2 | L30: =WORKDAY(M29,表格1_32[[#This Row],[Detailed req est. ]]/表格1_32[[#This Row],[Full Time Estimate(%)]]) -> 46113 | M30: =WORKDAY(表格1_32[[#This Row],[Req ETA]],表格1_32[[#This Row],[Dev + Unit test est.]]/表格1_32[[#This Row],[Full Time Estimate(%)]]) -> 46119
